Workbook

Sheet LISTADO
Q1: =SUM(Q3:Q513)
B2: ÍTEM | C2: PROYECTO | D2: ID LOTE | E2: ETAPA | F2: # LOTES | G2: MANZANA | H2: LOTE | I2: AREA (M2) | J2: PRECIO M2 | K2: PRECIO DE LOTE | L2: ESTADO | M2: CONTRATO | N2: PRECIO DE VENTA | O2: ESCRITURA | P2: FECHA DE ESCRITURA | Q2: % ESCRITURADO | R2: A NOMBRE DE : | S2: OBSERVACIÓN | U2: LOTES RELACIONADOS | V2: ALERTA
B3: 1 | C3: LA CEIBA | D3: ="LC" & E3 & " - " & G3 & " - " & H3 | E3: 1 | F3: 1 | G3: 1 | H3: 1 | I3: 1363.4231 | K3: 0 | L3: NO APTO PARA VENTA | N3: =I3*J3 | U3: =IF($D3="","",IF(OR($F3>1,ISNUMBER(SEARCH(" Y ",$D3)),(LEN($D3)-LEN(SUBSTITUTE(UPPER($D3),"LC","")))/2>1),"MÚLTIPLE","INDIVIDUAL")) | V3: =IF($D3="","",IF(AND(ISNUMBER(SEARCH(" Y ",$D3)),$F3<2),"REVISAR # LOTES",""))
B4: 2 | C4: LA CEIBA | D4: LC1 - 2 Y 3 | E4: 1 | F4: 2 | G4: 1 | H4: 2 - 3 | I4: 196 | K4: 55000000 | L4: VENDIDO | M4: SI | N4: =K4 | U4: =IF($D4="","",IF(OR($F4>1,ISNUMBER(SEARCH(" Y ",$D4)),(LEN($D4)-LEN(SUBSTITUTE(UPPER($D4),"LC","")))/2>1),"MÚLTIPLE","INDIVIDUAL")) | V4: =IF($D4="","",IF(AND(ISNUMBER(SEARCH(" Y ",$D4)),$F4<2),"REVISAR # LOTES",""))
B5: 3 | C5: LA CEIBA | D5: LC1 - 1 - 4 | E5: 1 | F5: 1 | G5: 1 | H5: 4 | I5: 98 | K5: 25000000 | L5: VENDIDO | M5: SI | N5: =K5 | O5: OK | Q5: 9.8e-05 | R5: RUBEN FABIAN BUSTOS | U5: =IF($D5="","",IF(OR($F5>1,ISNUMBER(SEARCH(" Y ",$D5)),(LEN($D5)-LEN(SUBSTITUTE(UPPER($D5),"LC","")))/2>1),"MÚLTIPLE","INDIVIDUAL")) | V5: =IF($D5="","",IF(AND(ISNUMBER(SEARCH(" Y ",$D5)),$F5<2),"REVISAR # LOTES",""))
B6: 4 | C6: LA CEIBA | D6: LC1 - 1 - 5 | E6: 1 | F6: 1 | G6: 1 | H6: 5 | I6: 115.643 | K6: 29500000 | L6: VENDIDO | M6: NO | N6: =K6 | U6: =IF($D6="","",IF(OR($F6>1,ISNUMBER(SEARCH(" Y ",$D6)),(LEN($D6)-LEN(SUBSTITUTE(UPPER($D6),"LC","")))/2>1),"MÚLTIPLE","INDIVIDUAL")) | V6: =IF($D6="","",IF(AND(ISNUMBER(SEARCH(" Y ",$D6)),$F6<2),"REVISAR # LOTES",""))
B7: 5 | C7: LA CEIBA | D7: LC1 - 2 - 1 | E7: 1 | F7: 1 | G7: 2 | H7: 1 | I7: 98 | K7: 30000000 | L7: VENDIDO | M7: SI | N7: =K7 | U7: =IF($D7="","",IF(OR($F7>1,ISNUMBER(SEARCH(" Y ",$D7)),(LEN($D7)-LEN(SUBSTITUTE(UPPER($D7),"LC","")))/2>1),"MÚLTIPLE","INDIVIDUAL")) | V7: =IF($D7="","",IF(AND(ISNUMBER(SEARCH(" Y ",$D7)),$F7<2),"REVISAR # LOTES",""))
B8: 6 | C8: LA CEIBA | D8: LC1 - 2 - 2 | E8: 1 | F8: 1 | G8: 2 | H8: 2 | I8: 98 | K8: 25000000 | L8: VENDIDO | M8: SI | N8: =K8 | U8: =IF($D8="","",IF(OR($F8>1,ISNUMBER(SEARCH(" Y ",$D8)),(LEN($D8)-LEN(SUBSTITUTE(UPPER($D8),"LC","")))/2>1),"MÚLTIPLE","INDIVIDUAL")) | V8: =IF($D8="","",IF(AND(ISNUMBER(SEARCH(" Y ",$D8)),$F8<2),"REVISAR # LOTES",""))
B9: 7 | C9: LA CEIBA | D9: LC1 - 2 - 3 | E9: 1 | F9: 1 | G9: 2 | H9: 3 | I9: 98 | K9: 25000000 | L9: CEDIDO EN FORMA DE PAGO | N9: =K9 | U9: =IF($D9="","",IF(OR($F9>1,ISNUMBER(SEARCH(" Y ",$D9)),(LEN($D9)-LEN(SUBSTITUTE(UPPER($D9),"LC","")))/2>1),"MÚLTIPLE","INDIVIDUAL")) | V9: =IF($D9="","",IF(AND(ISNUMBER(SEARCH(" Y ",$D9)),$F9<2),"REVISAR # LOTES",""))
B10: 8 | C10: LA CEIBA | D10: LC1 - 2 - 4 | E10: 1 | F10: 1 | G10: 2 | H10: 4 | I10: 98 | K10: 25000000 | L10: CEDIDO EN FORMA DE PAGO | N10: =K10 | U10: =IF($D10="","",IF(OR($F10>1,ISNUMBER(SEARCH(" Y ",$D10)),(LEN($D10)-LEN(SUBSTITUTE(UPPER($D10),"LC","")))/2>1),"MÚLTIPLE","INDIVIDUAL")) | V10: =IF($D10="","",IF(AND(ISNUMBER(SEARCH(" Y ",$D10)),$F10<2),"REVISAR # LOTES",""))
B11: 9 | C11: LA CEIBA | D11: LC1 - 2 - 5 | E11: 1 | F11: 1 | G11: 2 | H11: 5 | I11: 121 | K11: 30783000 | L11: CEDIDO EN FORMA DE PAGO | N11: =K11 | U11: =IF($D11="","",IF(OR($F11>1,ISNUMBER(SEARCH(" Y ",$D11)),(LEN($D11)-LEN(SUBSTITUTE(UPPER($D11),"LC","")))/2>1),"MÚLTIPLE","INDIVIDUAL")) | V11: =IF($D11="","",IF(AND(ISNUMBER(SEARCH(" Y ",$D11)),$F11<2),"REVISAR # LOTES",""))
B12: 10 | C12: LA CEIBA | D12: LC1 - 2 - 6 | E12: 1 | F12: 1 | G12: 2 | H12: 6 | I12: 170.068 | K12: 43385000 | L12: VENDIDO | M12: NO | N12: =K12 | U12: =IF($D12="","",IF(OR($F12>1,ISNUMBER(SEARCH(" Y ",$D12)),(LEN($D12)-LEN(SUBSTITUTE(UPPER($D12),"LC","")))/2>1),"MÚLTIPLE","INDIVIDUAL")) | V12: =IF($D12="","",IF(AND(ISNUMBER(SEARCH(" Y ",$D12)),$F12<2),"REVISAR # LOTES",""))
B13: 11 | C13: LA CEIBA | D13: LC1 - 2 - 7 | E13: 1 | F13: 1 | G13: 2 | H13: 7 | I13: 98 | K13: 25000000 | L13: VENDIDO | M13: SI | N13: =K13 | U13: =IF($D13="","",IF(OR($F13>1,ISNUMBER(SEARCH(" Y ",$D13)),(LEN($D13)-LEN(SUBSTITUTE(UPPER($D13),"LC","")))/2>1),"MÚLTIPLE","INDIVIDUAL")) | V13: =IF($D13="","",IF(AND(ISNUMBER(SEARCH(" Y ",$D13)),$F13<2),"REVISAR # LOTES",""))
B14: 12 | C14: LA CEIBA | D14: LC1 - 2 - 8 Y 9 | E14: 1 | F14: 2 | G14: 2 | H14: 8 - 9 | I14: 196 | K14: 55000000 | L14: VENDIDO | M14: SI | N14: =K14 | U14: =IF($D14="","",IF(OR($F14>1,ISNUMBER(SEARCH(" Y ",$D14)),(LEN($D14)-LEN(SUBSTITUTE(UPPER($D14),"LC","")))/2>1),"MÚLTIPLE","INDIVIDUAL")) | V14: =IF($D14="","",IF(AND(ISNUMBER(SEARCH(" Y ",$D14)),$F14<2),"REVISAR # LOTES",""))
B15: 13 | C15: LA CEIBA | D15: LC1 - 3 - 1 | E15: 1 | F15: 1 | G15: 3 | H15: 1 | I15: 98 | K15: 30000000 | L15: CEDIDO EN FORMA DE PAGO | N15: =K15 | U15: =IF($D15="","",IF(OR($F15>1,ISNUMBER(SEARCH(" Y ",$D15)),(LEN($D15)-LEN(SUBSTITUTE(UPPER($D15),"LC","")))/2>1),"MÚLTIPLE","INDIVIDUAL")) | V15: =IF($D15="","",IF(AND(ISNUMBER(SEARCH(" Y ",$D15)),$F15<2),"REVISAR # LOTES",""))
B16: 14 | C16: LA CEIBA | D16: LC1 - 3 - 2 | E16: 1 | F16: 1 | G16: 3 | H16: 2 | I16: 98 | K16: 25000000 | L16: EN NEGOCIACIÓN | N16: =K16 | U16: =IF($D16="","",IF(OR($F16>1,ISNUMBER(SEARCH(" Y ",$D16)),(LEN($D16)-LEN(SUBSTITUTE(UPPER($D16),"LC","")))/2>1),"MÚLTIPLE","INDIVIDUAL")) | V16: =IF($D16="","",IF(AND(ISNUMBER(SEARCH(" Y ",$D16)),$F16<2),"REVISAR # LOTES",""))
B17: 15 | C17: LA CEIBA | D17: LC1 - 3 - 3 | E17: 1 | F17: 1 | G17: 3 | H17: 3 | I17: 98 | K17: 25000000 | L17: VENDIDO | M17: SI | N17: =K17 | O17: OK | P17: 46176 | Q17: 9.8e-05 | R17: JOHN ALBERTO BOHORQUEZ | U17: =IF($D17="","",IF(OR($F17>1,ISNUMBER(SEARCH(" Y ",$D17)),(LEN($D17)-LEN(SUBSTITUTE(UPPER($D17),"LC","")))/2>1),"MÚLTIPLE","INDIVIDUAL")) | V17: =IF($D17="","",IF(AND(ISNUMBER(SEARCH(" Y ",$D17)),$F17<2),"REVISAR # LOTES",""))
B18: 16 | C18: LA CEIBA | D18: LC1 - 3 - 4 | E18: 1 | F18: 1 | G18: 3 | H18: 4 | I18: 98 | K18: 25000000 | L18: VENDIDO | M18: SI | N18: =K18 | U18: =IF($D18="","",IF(OR($F18>1,ISNUMBER(SEARCH(" Y ",$D18)),(LEN($D18)-LEN(SUBSTITUTE(UPPER($D18),"LC","")))/2>1),"MÚLTIPLE","INDIVIDUAL")) | V18: =IF($D18="","",IF(AND(ISNUMBER(SEARCH(" Y ",$D18)),$F18<2),"REVISAR # LOTES",""))
B19: 17 | C19: LA CEIBA | D19: LC1 - 3 - 5 | E19: 1 | F19: 1 | G19: 3 | H19: 5 | I19: 98 | K19: 25000000 | L19: VENDIDO | M19: SI | N19: =K19 | U19: =IF($D19="","",IF(OR($F19>1,ISNUMBER(SEARCH(" Y ",$D19)),(LEN($D19)-LEN(SUBSTITUTE(UPPER($D19),"LC","")))/2>1),"MÚLTIPLE","INDIVIDUAL")) | V19: =IF($D19="","",IF(AND(ISNUMBER(SEARCH(" Y ",$D19)),$F19<2),"REVISAR # LOTES",""))
B20: 18 | C20: LA CEIBA | D20: LC1 - 3 - 6 | E20: 1 | F20: 1 | G20: 3 | H20: 6 | I20: 149.2 | K20: 38058000 | L20: VENDIDO | N20: =K20 | U20: =IF($D20="","",IF(OR($F20>1,ISNUMBER(SEARCH(" Y ",$D20)),(LEN($D20)-LEN(SUBSTITUTE(UPPER($D20),"LC","")))/2>1),"MÚLTIPLE","INDIVIDUAL")) | V20: =IF($D20="","",IF(AND(ISNUMBER(SEARCH(" Y ",$D20)),$F20<2),"REVISAR # LOTES",""))
B21: 19 | C21: LA CEIBA | D21: LC1 - 3 - 7 | E21: 1 | F21: 1 | G21: 3 | H21: 7 | I21: 99.8 | K21: 25470000 | L21: DISPONIBLE | N21: =K21 | U21: =IF($D21="","",IF(OR($F21>1,ISNUMBER(SEARCH(" Y ",$D21)),(LEN($D21)-LEN(SUBSTITUTE(UPPER($D21),"LC","")))/2>1),"MÚLTIPLE","INDIVIDUAL")) | V21: =IF($D21="","",IF(AND(ISNUMBER(SEARCH(" Y ",$D21)),$F21<2),"REVISAR # LOTES",""))
B22: 20 | C22: LA CEIBA | D22: LC1 - 3 - 8 | E22: 1 | F22: 1 | G22: 3 | H22: 8 | I22: 98 | K22: 25000000 | L22: DISPONIBLE | N22: =K22 | U22: =IF($D22="","",IF(OR($F22>1,ISNUMBER(SEARCH(" Y ",$D22)),(LEN($D22)-LEN(SUBSTITUTE(UPPER($D22),"LC","")))/2>1),"MÚLTIPLE","INDIVIDUAL")) | V22: =IF($D22="","",IF(AND(ISNUMBER(SEARCH(" Y ",$D22)),$F22<2),"REVISAR # LOTES",""))
B23: 21 | C23: LA CEIBA | D23: LC1 - 3 - 9 | E23: 1 | F23: 1 | G23: 3 | H23: 9 | I23: 99.846 | K23: 25000000 | L23: VENDIDO | M23: NO | N23: =K23 | U23: =IF($D23="","",IF(OR($F23>1,ISNUMBER(SEARCH(" Y ",$D23)),(LEN($D23)-LEN(SUBSTITUTE(UPPER($D23),"LC","")))/2>1),"MÚLTIPLE","INDIVIDUAL")) | V23: =IF($D23="","",IF(AND(ISNUMBER(SEARCH(" Y ",$D23)),$F23<2),"REVISAR # LOTES",""))
B24: 22 | C24: LA CEIBA | D24: LC1 - 3 - 10 Y 11 | E24: 1 | F24: 2 | G24: 3 | H24: 10 - 11 | I24: 196 | K24: 50000000 | L24: VENDIDO | M24: NO | N24: =K24 | U24: =IF($D24="","",IF(OR($F24>1,ISNUMBER(SEARCH(" Y ",$D24)),(LEN($D24)-LEN(SUBSTITUTE(UPPER($D24),"LC","")))/2>1),"MÚLTIPLE","INDIVIDUAL")) | V24: =IF($D24="","",IF(AND(ISNUMBER(SEARCH(" Y ",$D24)),$F24<2),"REVISAR # LOTES",""))
B25: 23 | C25: LA CEIBA | D25: LC1 - 3 - 12 | E25: 1 | F25: 1 | G25: 3 | H25: 12 | I25: 98 | K25: 30000000 | L25: CEDIDO EN FORMA DE PAGO | N25: =K25 | U25: =IF($D25="","",IF(OR($F25>1,ISNUMBER(SEARCH(" Y ",$D25)),(LEN($D25)-LEN(SUBSTITUTE(UPPER($D25),"LC","")))/2>1),"MÚLTIPLE","INDIVIDUAL")) | V25: =IF($D25="","",IF(AND(ISNUMBER(SEARCH(" Y ",$D25)),$F25<2),"REVISAR # LOTES",""))
B26: 24 | C26: LA CEIBA | D26: LC1 - 4 - 1 | E26: 1 | F26: 1 | G26: 4 | H26: 1 | I26: 150.4 | K26: 43380000 | L26: VENDIDO | N26: =K26 | U26: =IF($D26="","",IF(OR($F26>1,ISNUMBER(SEARCH(" Y ",$D26)),(LEN($D26)-LEN(SUBSTITUTE(UPPER($D26),"LC","")))/2>1),"MÚLTIPLE","INDIVIDUAL")) | V26: =IF($D26="","",IF(AND(ISNUMBER(SEARCH(" Y ",$D26)),$F26<2),"REVISAR # LOTES",""))
B27: 25 | C27: LA CEIBA | D27: LC1 - 4 - 2 | E27: 1 | F27: 1 | G27: 4 | H27: 2 | I27: 140.999 | K27: 35970000 | L27: VENDIDO | M27: SI | N27: =K27 | U27: =IF($D27="","",IF(OR($F27>1,ISNUMBER(SEARCH(" Y ",$D27)),(LEN($D27)-LEN(SUBSTITUTE(UPPER($D27),"LC","")))/2>1),"MÚLTIPLE","INDIVIDUAL")) | V27: =IF($D27="","",IF(AND(ISNUMBER(SEARCH(" Y ",$D27)),$F27<2),"REVISAR # LOTES",""))
B28: 26 | C28: LA CEIBA | D28: LC1 - 4 - 3 | E28: 1 | F28: 1 | G28: 4 | H28: 3 | I28: 130.981 | K28: 33413000 | L28: VENDIDO | M28: SI | N28: =K28 | U28: =IF($D28="","",IF(OR($F28>1,ISNUMBER(SEARCH(" Y ",$D28)),(LEN($D28)-LEN(SUBSTITUTE(UPPER($D28),"LC","")))/2>1),"MÚLTIPLE","INDIVIDUAL")) | V28: =IF($D28="","",IF(AND(ISNUMBER(SEARCH(" Y ",$D28)),$F28<2),"REVISAR # LOTES",""))
B29: 27 | C29: LA CEIBA | D29: LC1 - 4 - 4 | E29: 1 | F29: 1 | G29: 4 | H29: 4 | I29: 120.928 | K29: 30849000 | L29: VENDIDO | M29: SI | N29: =K29 | U29: =IF($D29="","",IF(OR($F29>1,ISNUMBER(SEARCH(" Y ",$D29)),(LEN($D29)-LEN(SUBSTITUTE(UPPER($D29),"LC","")))/2>1),"MÚLTIPLE","INDIVIDUAL")) | V29: =IF($D29="","",IF(AND(ISNUMBER(SEARCH(" Y ",$D29)),$F29<2),"REVISAR # LOTES",""))
B30: 28 | C30: LA CEIBA | D30: LC1 - 4 - 5 | E30: 1 | F30: 1 | G30: 4 | H30: 5 | I30: 110.8 | K30: 28276000 | L30: VENDIDO | N30: =K30 | U30: =IF($D30="","",IF(OR($F30>1,ISNUMBER(SEARCH(" Y ",$D30)),(LEN($D30)-LEN(SUBSTITUTE(UPPER($D30),"LC","")))/2>1),"MÚLTIPLE","INDIVIDUAL")) | V30: =IF($D30="","",IF(AND(ISNUMBER(SEARCH(" Y ",$D30)),$F30<2),"REVISAR # LOTES",""))
B31: 29 | C31: LA CEIBA | D31: LC1 - 4 - 6 | E31: 1 | F31: 1 | G31: 4 | H31: 6 | I31: 98.223 | K31: 25056000 | L31: VENDIDO | M31: NO | N31: =K31 | U31: =IF($D31="","",IF(OR($F31>1,ISNUMBER(SEARCH(" Y ",$D31)),(LEN($D31)-LEN(SUBSTITUTE(UPPER($D31),"LC","")))/2>1),"MÚLTIPLE","INDIVIDUAL")) | V31: =IF($D31="","",IF(AND(ISNUMBER(SEARCH(" Y ",$D31)),$F31<2),"REVISAR # LOTES",""))
B32: 30 | C32: LA CEIBA | D32: LC1 - 4 - 7 | E32: 1 | F32: 1 | G32: 4 | H32: 7 | I32: 95.303 | K32: 25000000 | L32: VENDIDO | M32: NO | N32: =K32 | U32: =IF($D32="","",IF(OR($F32>1,ISNUMBER(SEARCH(" Y ",$D32)),(LEN($D32)-LEN(SUBSTITUTE(UPPER($D32),"LC","")))/2>1),"MÚLTIPLE","INDIVIDUAL")) | V32: =IF($D32="","",IF(AND(ISNUMBER(SEARCH(" Y ",$D32)),$F32<2),"REVISAR # LOTES",""))
B33: 31 | C33: LA CEIBA | D33: LC1- 5 - 1 | E33: 1 | F33: 1 | G33: 5 | H33: 1 | I33: 162.2 | K33: 41380000 | L33: VENDIDO | N33: =K33 | U33: =IF($D33="","",IF(OR($F33>1,ISNUMBER(SEARCH(" Y ",$D33)),(LEN($D33)-LEN(SUBSTITUTE(UPPER($D33),"LC","")))/2>1),"MÚLTIPLE","INDIVIDUAL")) | V33: =IF($D33="","",IF(AND(ISNUMBER(SEARCH(" Y ",$D33)),$F33<2),"REVISAR # LOTES",""))
B34: 32 | C34: LA CEIBA | D34: LC1 - 5 - 2 | E34: 1 | F34: 1 | G34: 5 | H34: 2 | I34: 98 | K34: 25000000 | L34: VENDIDO | M34: SI | N34: =K34 | U34: =IF($D34="","",IF(OR($F34>1,ISNUMBER(SEARCH(" Y ",$D34)),(LEN($D34)-LEN(SUBSTITUTE(UPPER($D34),"LC","")))/2>1),"MÚLTIPLE","INDIVIDUAL")) | V34: =IF($D34="","",IF(AND(ISNUMBER(SEARCH(" Y ",$D34)),$F34<2),"REVISAR # LOTES",""))
B35: 33 | C35: LA CEIBA | D35: LC1 - 5 - 3 | E35: 1 | F35: 1 | G35: 5 | H35: 3 | I35: 98 | K35: 30000000 | L35: VENDIDO | M35: SI | N35: =K35 | U35: =IF($D35="","",IF(OR($F35>1,ISNUMBER(SEARCH(" Y ",$D35)),(LEN($D35)-LEN(SUBSTITUTE(UPPER($D35),"LC","")))/2>1),"MÚLTIPLE","INDIVIDUAL")) | V35: =IF($D35="","",IF(AND(ISNUMBER(SEARCH(" Y ",$D35)),$F35<2),"REVISAR # LOTES",""))
B36: 34 | C36: LA CEIBA | D36: LC1 - 5 - 4 | E36: 1 | F36: 1 | G36: 5 | H36: 4 | I36: 98 | K36: 30000000 | L36: VENDIDO | M36: SI | N36: =K36 | U36: =IF($D36="","",IF(OR($F36>1,ISNUMBER(SEARCH(" Y ",$D36)),(LEN($D36)-LEN(SUBSTITUTE(UPPER($D36),"LC","")))/2>1),"MÚLTIPLE","INDIVIDUAL")) | V36: =IF($D36="","",IF(AND(ISNUMBER(SEARCH(" Y ",$D36)),$F36<2),"REVISAR # LOTES",""))
B37: 35 | C37: LA CEIBA | D37: LC1 - 5 - 5 | E37: 1 | F37: 1 | G37: 5 | H37: 5 | I37: 98 | K37: 25000000 | L37: VENDIDO | M37: SI | N37: =K37 | O37: OK | Q37: 0.0098 | R37: RUBEN FABIAN BUSTOS | U37: =IF($D37="","",IF(OR($F37>1,ISNUMBER(SEARCH(" Y ",$D37)),(LEN($D37)-LEN(SUBSTITUTE(UPPER($D37),"LC","")))/2>1),"MÚLTIPLE","INDIVIDUAL")) | V37: =IF($D37="","",IF(AND(ISNUMBER(SEARCH(" Y ",$D37)),$F37<2),"REVISAR # LOTES",""))
B38: 36 | C38: LA CEIBA | D38: LC1 - 5 - 6 | E38: 1 | F38: 1 | G38: 5 | H38: 6 | I38: 131.484 | K38: 33541000 | L38: VENDIDO | M38: NO | N38: =K38 | U38: =IF($D38="","",IF(OR($F38>1,ISNUMBER(SEARCH(" Y ",$D38)),(LEN($D38)-LEN(SUBSTITUTE(UPPER($D38),"LC","")))/2>1),"MÚLTIPLE","INDIVIDUAL")) | V38: =IF($D38="","",IF(AND(ISNUMBER(SEARCH(" Y ",$D38)),$F38<2),"REVISAR # LOTES",""))
B39: 37 | C39: LA CEIBA | D39: LC1 - 6 - 1 | E39: 1 | F39: 1 | G39: 6 | H39: 1 | I39: 98 | K39: 30000000 | L39: VENDIDO | M39: NO | N39: =K39 | U39: =IF($D39="","",IF(OR($F39>1,ISNUMBER(SEARCH(" Y ",$D39)),(LEN($D39)-LEN(SUBSTITUTE(UPPER($D39),"LC","")))/2>1),"MÚLTIPLE","INDIVIDUAL")) | V39: =IF($D39="","",IF(AND(ISNUMBER(SEARCH(" Y ",$D39)),$F39<2),"REVISAR # LOTES",""))
B40: 38 | C40: LA CEIBA | D40: LC1 - 6 - 2 | E40: 1 | F40: 1 | G40: 6 | H40: 2 | I40: 98 | K40: 25000000 | L40: VENDIDO | M40: SI | N40: =K40 | U40: =IF($D40="","",IF(OR($F40>1,ISNUMBER(SEARCH(" Y ",$D40)),(LEN($D40)-LEN(SUBSTITUTE(UPPER($D40),"LC","")))/2>1),"MÚLTIPLE","INDIVIDUAL")) | V40: =IF($D40="","",IF(AND(ISNUMBER(SEARCH(" Y ",$D40)),$F40<2),"REVISAR # LOTES",""))
B41: 39 | C41: LA CEIBA | D41: LC1 - 6 - 3 | E41: 1 | F41: 1 | G41: 6 | H41: 3 | I41: 98 | K41: 25000000 | L41: VENDIDO | M41: NO | N41: =K41 | U41: =IF($D41="","",IF(OR($F41>1,ISNUMBER(SEARCH(" Y ",$D41)),(LEN($D41)-LEN(SUBSTITUTE(UPPER($D41),"LC","")))/2>1),"MÚLTIPLE","INDIVIDUAL")) | V41: =IF($D41="","",IF(AND(ISNUMBER(SEARCH(" Y ",$D41)),$F41<2),"REVISAR # LOTES",""))
B42: 40 | C42: LA CEIBA | D42: LC1 - 6 - 4 | E42: 1 | F42: 1 | G42: 6 | H42: 4 | I42: 98 | K42: 30000000 | L42: VENDIDO | M42: SI | N42: =K42 | U42: =IF($D42="","",IF(OR($F42>1,ISNUMBER(SEARCH(" Y ",$D42)),(LEN($D42)-LEN(SUBSTITUTE(UPPER($D42),"LC","")))/2>1),"MÚLTIPLE","INDIVIDUAL")) | V42: =IF($D42="","",IF(AND(ISNUMBER(SEARCH(" Y ",$D42)),$F42<2),"REVISAR # LOTES",""))
B43: 41 | C43: LA CEIBA | D43: LC1 - 6 - 5 | E43: 1 | F43: 1 | G43: 6 | H43: 5 | I43: 98 | K43: 30000000 | L43: VENDIDO | M43: SI | N43: =K43 | U43: =IF($D43="","",IF(OR($F43>1,ISNUMBER(SEARCH(" Y ",$D43)),(LEN($D43)-LEN(SUBSTITUTE(UPPER($D43),"LC","")))/2>1),"MÚLTIPLE","INDIVIDUAL")) | V43: =IF($D43="","",IF(AND(ISNUMBER(SEARCH(" Y ",$D43)),$F43<2),"REVISAR # LOTES",""))
B44: 42 | C44: LA CEIBA | D44: LC1 - 6 - 6 | E44: 1 | F44: 1 | G44: 6 | H44: 6 | I44: 98 | K44: 25000000 | L44: VENDIDO | M44: NO | N44: =K44 | U44: =IF($D44="","",IF(OR($F44>1,ISNUMBER(SEARCH(" Y ",$D44)),(LEN($D44)-LEN(SUBSTITUTE(UPPER($D44),"LC","")))/2>1),"MÚLTIPLE","INDIVIDUAL")) | V44: =IF($D44="","",IF(AND(ISNUMBER(SEARCH(" Y ",$D44)),$F44<2),"REVISAR # LOTES",""))
B45: 43 | C45: LA CEIBA | D45: LC1 - 6 - 7 | E45: 1 | F45: 1 | G45: 6 | H45: 7 | I45: 98 | K45: 25000000 | L45: VENDIDO | M45: SI | N45: =K45 | U45: =IF($D45="","",IF(OR($F45>1,ISNUMBER(SEARCH(" Y ",$D45)),(LEN($D45)-LEN(SUBSTITUTE(UPPER($D45),"LC","")))/2>1),"MÚLTIPLE","INDIVIDUAL")) | V45: =IF($D45="","",IF(AND(ISNUMBER(SEARCH(" Y ",$D45)),$F45<2),"REVISAR # LOTES",""))
B46: 44 | C46: LA CEIBA | D46: LC1 - 6 - 8 | E46: 1 | F46: 1 | G46: 6 | H46: 8 | I46: 98 | K46: 30000000 | L46: VENDIDO | M46: SI | N46: =K46 | U46: =IF($D46="","",IF(OR($F46>1,ISNUMBER(SEARCH(" Y ",$D46)),(LEN($D46)-LEN(SUBSTITUTE(UPPER($D46),"LC","")))/2>1),"MÚLTIPLE","INDIVIDUAL")) | V46: =IF($D46="","",IF(AND(ISNUMBER(SEARCH(" Y ",$D46)),$F46<2),"REVISAR # LOTES",""))
B47: 45 | C47: LA CEIBA | D47: LC1 - 7 - 1 Y 2 - LC1 - 8 - 7 Y 8 | E47: 1 | F47: 4 | G47: 7 Y 8 | H47: 1 - 2 Y 7 - 8 | I47: 392 | K47: 110000000 | L47: VENDIDO | M47: NO | N47: =K47 | U47: =IF($D47="","",IF(OR($F47>1,ISNUMBER(SEARCH(" Y ",$D47)),(LEN($D47)-LEN(SUBSTITUTE(UPPER($D47),"LC","")))/2>1),"MÚLTIPLE","INDIVIDUAL")) | V47: =IF($D47="","",IF(AND(ISNUMBER(SEARCH(" Y ",$D47)),$F47<2),"REVISAR # LOTES",""))
B48: 46 | C48: LA CEIBA | D48: LC1 - 7 - 3 | E48: 1 | F48: 1 | G48: 7 | H48: 3 | I48: 98 | K48: 25000000 | L48: VENDIDO | M48: SI | N48: =K48 | U48: =IF($D48="","",IF(OR($F48>1,ISNUMBER(SEARCH(" Y ",$D48)),(LEN($D48)-LEN(SUBSTITUTE(UPPER($D48),"LC","")))/2>1),"MÚLTIPLE","INDIVIDUAL")) | V48: =IF($D48="","",IF(AND(ISNUMBER(SEARCH(" Y ",$D48)),$F48<2),"REVISAR # LOTES",""))
B49: 47 | C49: LA CEIBA | D49: LC1 - 7 - 4 | E49: 1 | F49: 1 | G49: 7 | H49: 4 | I49: 98 | K49: 25000000 | L49: CEDIDO EN FORMA DE PAGO | N49: =K49 | U49: =IF($D49="","",IF(OR($F49>1,ISNUMBER(SEARCH(" Y ",$D49)),(LEN($D49)-LEN(SUBSTITUTE(UPPER($D49),"LC","")))/2>1),"MÚLTIPLE","INDIVIDUAL")) | V49: =IF($D49="","",IF(AND(ISNUMBER(SEARCH(" Y ",$D49)),$F49<2),"REVISAR # LOTES",""))
B50: 48 | C50: LA CEIBA | D50: LC1 - 7 - 5 | E50: 1 | F50: 1 | G50: 7 | H50: 5 | I50: 98 | K50: 25000000 | L50: VENDIDO | M50: SI | N50: =K50 | U50: =IF($D50="","",IF(OR($F50>1,ISNUMBER(SEARCH(" Y ",$D50)),(LEN($D50)-LEN(SUBSTITUTE(UPPER($D50),"LC","")))/2>1),"MÚLTIPLE","INDIVIDUAL")) | V50: =IF($D50="","",IF(AND(ISNUMBER(SEARCH(" Y ",$D50)),$F50<2),"REVISAR # LOTES",""))
B51: 49 | C51: LA CEIBA | D51: LC1 - 7 - 6 | E51: 1 | F51: 1 | G51: 7 | H51: 6 | I51: 98 | K51: 25000000 | L51: VENDIDO | M51: SI | N51: =K51 | U51: =IF($D51="","",IF(OR($F51>1,ISNUMBER(SEARCH(" Y ",$D51)),(LEN($D51)-LEN(SUBSTITUTE(UPPER($D51),"LC","")))/2>1),"MÚLTIPLE","INDIVIDUAL")) | V51: =IF($D51="","",IF(AND(ISNUMBER(SEARCH(" Y ",$D51)),$F51<2),"REVISAR # LOTES",""))
B52: 50 | C52: LA CEIBA | D52: LC1 - 7 - 7 | E52: 1 | F52: 1 | G52: 7 | H52: 7 | I52: 192.8 | K52: 49179000 | L52: DISPONIBLE | N52: =K52 | U52: =IF($D52="","",IF(OR($F52>1,ISNUMBER(SEARCH(" Y ",$D52)),(LEN($D52)-LEN(SUBSTITUTE(UPPER($D52),"LC","")))/2>1),"MÚLTIPLE","INDIVIDUAL")) | V52: =IF($D52="","",IF(AND(ISNUMBER(SEARCH(" Y ",$D52)),$F52<2),"REVISAR # LOTES",""))
B53: 51 | C53: LA CEIBA | D53: LC1 - 7 - 8 | E53: 1 | F53: 1 | G53: 7 | H53: 8 | I53: 98 | K53: 30000000 | L53: VENDIDO | M53: NO | N53: =K53 | U53: =IF($D53="","",IF(OR($F53>1,ISNUMBER(SEARCH(" Y ",$D53)),(LEN($D53)-LEN(SUBSTITUTE(UPPER($D53),"LC","")))/2>1),"MÚLTIPLE","INDIVIDUAL")) | V53: =IF($D53="","",IF(AND(ISNUMBER(SEARCH(" Y ",$D53)),$F53<2),"REVISAR # LOTES",""))
B54: 52 | C54: LA CEIBA | D54: LC1 - 7 - 9 | E54: 1 | F54: 1 | G54: 7 | H54: 9 | I54: 98 | K54: 25000000 | L54: VENDIDO | M54: SI | N54: =K54 | O54: OK | Q54: 0.0098 | R54: RUBEN FABIAN BUSTOS | S54: PAGO COMPLETO | U54: =IF($D54="","",IF(OR($F54>1,ISNUMBER(SEARCH(" Y ",$D54)),(LEN($D54)-LEN(SUBSTITUTE(UPPER($D54),"LC","")))/2>1),"MÚLTIPLE","INDIVIDUAL")) | V54: =IF($D54="","",IF(AND(ISNUMBER(SEARCH(" Y ",$D54)),$F54<2),"REVISAR # LOTES",""))
B55: 53 | C55: LA CEIBA | D55: LC1 - 7 - 10 | E55: 1 | F55: 1 | G55: 7 | H55: 10 | I55: 98 | K55: 25000000 | L55: VENDIDO | M55: SI | N55: =K55 | U55: =IF($D55="","",IF(OR($F55>1,ISNUMBER(SEARCH(" Y ",$D55)),(LEN($D55)-LEN(SUBSTITUTE(UPPER($D55),"LC","")))/2>1),"MÚLTIPLE","INDIVIDUAL")) | V55: =IF($D55="","",IF(AND(ISNUMBER(SEARCH(" Y ",$D55)),$F55<2),"REVISAR # LOTES",""))
B56: 54 | C56: LA CEIBA | D56: LC1 - 7 - 11 | E56: 1 | F56: 1 | G56: 7 | H56: 11 | I56: 98 | K56: 25000000 | L56: VENDIDO | M56: NO | N56: =K56 | U56: =IF($D56="","",IF(OR($F56>1,ISNUMBER(SEARCH(" Y ",$D56)),(LEN($D56)-LEN(SUBSTITUTE(UPPER($D56),"LC","")))/2>1),"MÚLTIPLE","INDIVIDUAL")) | V56: =IF($D56="","",IF(AND(ISNUMBER(SEARCH(" Y ",$D56)),$F56<2),"REVISAR # LOTES",""))
B57: 55 | C57: LA CEIBA | D57: LC1 - 7 - 12 | E57: 1 | F57: 1 | G57: 7 | H57: 12 | I57: 98 | K57: 25000000 | L57: VENDIDO | M57: NO | N57: =K57 | U57: =IF($D57="","",IF(OR($F57>1,ISNUMBER(SEARCH(" Y ",$D57)),(LEN($D57)-LEN(SUBSTITUTE(UPPER($D57),"LC","")))/2>1),"MÚLTIPLE","INDIVIDUAL")) | V57: =IF($D57="","",IF(AND(ISNUMBER(SEARCH(" Y ",$D57)),$F57<2),"REVISAR # LOTES",""))
B58: 56 | C58: LA CEIBA | D58: LC1 - 7 - 13 | E58: 1 | F58: 1 | G58: 7 | H58: 13 | I58: 98 | K58: 25000000 | L58: VENDIDO | M58: NO | N58: =K58 | U58: =IF($D58="","",IF(OR($F58>1,ISNUMBER(SEARCH(" Y ",$D58)),(LEN($D58)-LEN(SUBSTITUTE(UPPER($D58),"LC","")))/2>1),"MÚLTIPLE","INDIVIDUAL")) | V58: =IF($D58="","",IF(AND(ISNUMBER(SEARCH(" Y ",$D58)),$F58<2),"REVISAR # LOTES",""))
B59: 57 | C59: LA CEIBA | D59: LC1 - 7 - 14 | E59: 1 | F59: 1 | G59: 7 | H59: 14 | I59: 98 | K59: 25000000 | L59: VENDIDO | M59: NO | N59: =K59 | U59: =IF($D59="","",IF(OR($F59>1,ISNUMBER(SEARCH(" Y ",$D59)),(LEN($D59)-LEN(SUBSTITUTE(UPPER($D59),"LC","")))/2>1),"MÚLTIPLE","INDIVIDUAL")) | V59: =IF($D59="","",IF(AND(ISNUMBER(SEARCH(" Y ",$D59)),$F59<2),"REVISAR # LOTES",""))
B60: 58 | C60: LA CEIBA | D60: LC1 - 7 - 15 | E60: 1 | F60: 1 | G60: 7 | H60: 15 | I60: 98 | K60: 25000000 | L60: VENDIDO | M60: NO | N60: =K60 | U60: =IF($D60="","",IF(OR($F60>1,ISNUMBER(SEARCH(" Y ",$D60)),(LEN($D60)-LEN(SUBSTITUTE(UPPER($D60),"LC","")))/2>1),"MÚLTIPLE","INDIVIDUAL")) | V60: =IF($D60="","",IF(AND(ISNUMBER(SEARCH(" Y ",$D60)),$F60<2),"REVISAR # LOTES",""))
B61: 59 | C61: LA CEIBA | D61: LC1 - 7 - 16 | E61: 1 | F61: 1 | G61: 7 | H61: 16 | I61: 155.953 | K61: 39784000 | L61: VENDIDO | M61: NO | N61: =K61 | U61: =IF($D61="","",IF(OR($F61>1,ISNUMBER(SEARCH(" Y ",$D61)),(LEN($D61)-LEN(SUBSTITUTE(UPPER($D61),"LC","")))/2>1),"MÚLTIPLE","INDIVIDUAL")) | V61: =IF($D61="","",IF(AND(ISNUMBER(SEARCH(" Y ",$D61)),$F61<2),"REVISAR # LOTES",""))
B62: 60 | C62: LA CEIBA | D62: LC1 - 7 - 17 | E62: 1 | F62: 1 | G62: 7 | H62: 17 | I62: 125.892 | K62: 32115000 | L62: VENDIDO | M62: NO | N62: =K62 | U62: =IF($D62="","",IF(OR($F62>1,ISNUMBER(SEARCH(" Y ",$D62)),(LEN($D62)-LEN(SUBSTITUTE(UPPER($D62),"LC","")))/2>1),"MÚLTIPLE","INDIVIDUAL")) | V62: =IF($D62="","",IF(AND(ISNUMBER(SEARCH(" Y ",$D62)),$F62<2),"REVISAR # LOTES",""))
B63: 61 | C63: LA CEIBA | D63: LC1 - 7 - 18 | E63: 1 | F63: 1 | G63: 7 | H63: 18 | I63: 107.848 | K63: 27512000 | L63: VENDIDO | M63: SI | N63: =K63 | U63: =IF($D63="","",IF(OR($F63>1,ISNUMBER(SEARCH(" Y ",$D63)),(LEN($D63)-LEN(SUBSTITUTE(UPPER($D63),"LC","")))/2>1),"MÚLTIPLE","INDIVIDUAL")) | V63: =IF($D63="","",IF(AND(ISNUMBER(SEARCH(" Y ",$D63)),$F63<2),"REVISAR # LOTES",""))
B64: 62 | C64: LA CEIBA | D64: LC1 - 7 - 19 | E64: 1 | F64: 1 | G64: 7 | H64: 19 | I64: 107.848 | K64: 27512000 | L64: VENDIDO | M64: NO | N64: =K64 | U64: =IF($D64="","",IF(OR($F64>1,ISNUMBER(SEARCH(" Y ",$D64)),(LEN($D64)-LEN(SUBSTITUTE(UPPER($D64),"LC","")))/2>1),"MÚLTIPLE","INDIVIDUAL")) | V64: =IF($D64="","",IF(AND(ISNUMBER(SEARCH(" Y ",$D64)),$F64<2),"REVISAR # LOTES",""))
B65: 63 | C65: LA CEIBA | D65: LC1 - 7 - 20 | E65: 1 | F65: 1 | G65: 7 | H65: 20 | I65: 233.888 | K65: 59665000 | L65: VENDIDO | M65: SI | N65: =K65 | U65: =IF($D65="","",IF(OR($F65>1,ISNUMBER(SEARCH(" Y ",$D65)),(LEN($D65)-LEN(SUBSTITUTE(UPPER($D65),"LC","")))/2>1),"MÚLTIPLE","INDIVIDUAL")) | V65: =IF($D65="","",IF(AND(ISNUMBER(SEARCH(" Y ",$D65)),$F65<2),"REVISAR # LOTES",""))
B66: 64 | C66: LA CEIBA | D66: LC1 - 8 - 1 | E66: 1 | F66: 1 | G66: 8 | H66: 1 | I66: 98 | K66: 30000000 | L66: VENDIDO | M66: NO | N66: =K66 | U66: =IF($D66="","",IF(OR($F66>1,ISNUMBER(SEARCH(" Y ",$D66)),(LEN($D66)-LEN(SUBSTITUTE(UPPER($D66),"LC","")))/2>1),"MÚLTIPLE","INDIVIDUAL")) | V66: =IF($D66="","",IF(AND(ISNUMBER(SEARCH(" Y ",$D66)),$F66<2),"REVISAR # LOTES",""))
B67: 65 | C67: LA CEIBA | D67: LC1 - 8 - 2 | E67: 1 | F67: 1 | G67: 8 | H67: 2 | I67: 98 | K67: 25000000 | L67: VENDIDO | M67: NO | N67: =K67 | U67: =IF($D67="","",IF(OR($F67>1,ISNUMBER(SEARCH(" Y ",$D67)),(LEN($D67)-LEN(SUBSTITUTE(UPPER($D67),"LC","")))/2>1),"MÚLTIPLE","INDIVIDUAL")) | V67: =IF($D67="","",IF(AND(ISNUMBER(SEARCH(" Y ",$D67)),$F67<2),"REVISAR # LOTES",""))
B68: 66 | C68: LA CEIBA | D68: LC1 - 8 - 3 Y 4 | E68: 1 | F68: 1 | G68: 8 | H68: 3 Y 4 | I68: 207.678 | K68: 55482000 | L68: VENDIDO | M68: SI | N68: 55482000 | O68: 2026-09-17 | P68: 0.0002 | Q68: 0.0002 | R68: JOHN ALBERTO BOHORQUEZ | S68: PAGO COMPLETO | U68: =IF($D68="","",IF(OR($F68>1,ISNUMBER(SEARCH(" Y ",$D68)),(LEN($D68)-LEN(SUBSTITUTE(UPPER($D68),"LC","")))/2>1),"MÚLTIPLE","INDIVIDUAL")) | V68: =IF($D68="","",IF(AND(ISNUMBER(SEARCH(" Y ",$D68)),$F68<2),"REVISAR # LOTES",""))
B69: 67 | C69: LA CEIBA | D69: LC1 - 8 - 4 (UNIFICADO EN LC1 - 8 - 3 Y 4) | E69: 1 | F69: 1 | G69: 8 | H69: 4 | I69: 207.678 | K69: 27982000 | L69: VENDIDO | N69: =K69 | S69: UNIFICADO CON LC1 - 8 - 3 EN LC1 - 8 - 3 Y 4 | U69: =IF($D69="","",IF(OR($F69>1,ISNUMBER(SEARCH(" Y ",$D69)),(LEN($D69)-LEN(SUBSTITUTE(UPPER($D69),"LC","")))/2>1),"MÚLTIPLE","INDIVIDUAL")) | V69: =IF($D69="","",IF(AND(ISNUMBER(SEARCH(" Y ",$D69)),$F69<2),"REVISAR # LOTES",""))
B70: 68 | C70: LA CEIBA | D70: LC1 - 8 - 5 | E70: 1 | F70: 1 | G70: 8 | H70: 5 | I70: 141.6 | K70: 36132000 | L70: DISPONIBLE | N70: =K70 | U70: =IF($D70="","",IF(OR($F70>1,ISNUMBER(SEARCH(" Y ",$D70)),(LEN($D70)-LEN(SUBSTITUTE(UPPER($D70),"LC","")))/2>1),"MÚLTIPLE","INDIVIDUAL")) | V70: =IF($D70="","",IF(AND(ISNUMBER(SEARCH(" Y ",$D70)),$F70<2),"REVISAR # LOTES",""))
B71: 69 | C71: LA CEIBA | D71: LC1 - 8 - 6 | E71: 1 | F71: 1 | G71: 8 | H71: 6 | I71: 98 | K71: 25000000 | L71: VENDIDO | M71: NO | N71: =K71 | U71: =IF($D71="","",IF(OR($F71>1,ISNUMBER(SEARCH(" Y ",$D71)),(LEN($D71)-LEN(SUBSTITUTE(UPPER($D71),"LC","")))/2>1),"MÚLTIPLE","INDIVIDUAL")) | V71: =IF($D71="","",IF(AND(ISNUMBER(SEARCH(" Y ",$D71)),$F71<2),"REVISAR # LOTES",""))
B72: 70 | C72: LA CEIBA | D72: LC1 - 9 - 1 | E72: 1 | F72: 1 | G72: 9 | H72: 1 | I72: 98 | K72: 30000000 | L72: VENDIDO | M72: SI | N72: =K72 | P72: parque | S72: PAGO COMPLETO | U72: =IF($D72="","",IF(OR($F72>1,ISNUMBER(SEARCH(" Y ",$D72)),(LEN($D72)-LEN(SUBSTITUTE(UPPER($D72),"LC","")))/2>1),"MÚLTIPLE","INDIVIDUAL")) | V72: =IF($D72="","",IF(AND(ISNUMBER(SEARCH(" Y ",$D72)),$F72<2),"REVISAR # LOTES",""))
B73: 71 | C73: LA CEIBA | D73: LC1 - 9 - 2 | E73: 1 | F73: 1 | G73: 9 | H73: 2 | I73: 98 | K73: 25000000 | L73: VENDIDO | M73: SI | N73: =K73 | U73: =IF($D73="","",IF(OR($F73>1,ISNUMBER(SEARCH(" Y ",$D73)),(LEN($D73)-LEN(SUBSTITUTE(UPPER($D73),"LC","")))/2>1),"MÚLTIPLE","INDIVIDUAL")) | V73: =IF($D73="","",IF(AND(ISNUMBER(SEARCH(" Y ",$D73)),$F73<2),"REVISAR # LOTES",""))
B74: 72 | C74: LA CEIBA | D74: LC1 - 9 - 3 | E74: 1 | F74: 1 | G74: 9 | H74: 3 | I74: 98 | K74: 25000000 | L74: VENDIDO | M74: NO | N74: =K74 | U74: =IF($D74="","",IF(OR($F74>1,ISNUMBER(SEARCH(" Y ",$D74)),(LEN($D74)-LEN(SUBSTITUTE(UPPER($D74),"LC","")))/2>1),"MÚLTIPLE","INDIVIDUAL")) | V74: =IF($D74="","",IF(AND(ISNUMBER(SEARCH(" Y ",$D74)),$F74<2),"REVISAR # LOTES",""))
B75: 73 | C75: LA CEIBA | D75: LC1 - 9 - 4 | E75: 1 | F75: 1 | G75: 9 | H75: 4 | I75: 98 | K75: 30000000 | L75: VENDIDO | M75: SI | N75: =K75 | U75: =IF($D75="","",IF(OR($F75>1,ISNUMBER(SEARCH(" Y ",$D75)),(LEN($D75)-LEN(SUBSTITUTE(UPPER($D75),"LC","")))/2>1),"MÚLTIPLE","INDIVIDUAL")) | V75: =IF($D75="","",IF(AND(ISNUMBER(SEARCH(" Y ",$D75)),$F75<2),"REVISAR # LOTES",""))
B76: 74 | C76: LA CEIBA | D76: LC1 - 9 - 5 | E76: 1 | F76: 1 | G76: 9 | H76: 5 | I76: 98 | K76: 30000000 | L76: VENDIDO | M76: SI | N76: =K76 | O76: OK | Q76: 0.00056 | R76: RUBEN FABIAN BUSTOS | S76: PAGO COMPLETO | U76: =IF($D76="","",IF(OR($F76>1,ISNUMBER(SEARCH(" Y ",$D76)),(LEN($D76)-LEN(SUBSTITUTE(UPPER($D76),"LC","")))/2>1),"MÚLTIPLE","INDIVIDUAL")) | V76: =IF($D76="","",IF(AND(ISNUMBER(SEARCH(" Y ",$D76)),$F76<2),"REVISAR # LOTES",""))
B77: 75 | C77: LA CEIBA | D77: LC1 - 9 - 6 | E77: 1 | F77: 1 | G77: 9 | H77: 6 | I77: 98 | K77: 25000000 | L77: VENDIDO | M77: SI | N77: =K77 | U77: =IF($D77="","",IF(OR($F77>1,ISNUMBER(SEARCH(" Y ",$D77)),(LEN($D77)-LEN(SUBSTITUTE(UPPER($D77),"LC","")))/2>1),"MÚLTIPLE","INDIVIDUAL")) | V77: =IF($D77="","",IF(AND(ISNUMBER(SEARCH(" Y ",$D77)),$F77<2),"REVISAR # LOTES",""))
B78: 76 | C78: LA CEIBA | D78: LC1 - 9 - 7 | E78: 1 | F78: 1 | G78: 9 | H78: 7 | I78: 98 | K78: 25000000 | L78: VENDIDO | M78: NO | N78: =K78 | U78: =IF($D78="","",IF(OR($F78>1,ISNUMBER(SEARCH(" Y ",$D78)),(LEN($D78)-LEN(SUBSTITUTE(UPPER($D78),"LC","")))/2>1),"MÚLTIPLE","INDIVIDUAL")) | V78: =IF($D78="","",IF(AND(ISNUMBER(SEARCH(" Y ",$D78)),$F78<2),"REVISAR # LOTES",""))
B79: 77 | C79: LA CEIBA | D79: LC1 - 9 - 8 - LC1 - 12 - 11 | E79: 1 | F79: 2 | G79: 9 | H79: 8 - 11 | I79: 196 | K79: 60000000 | L79: VENDIDO | M79: SI | N79: =K79 | U79: =IF($D79="","",IF(OR($F79>1,ISNUMBER(SEARCH(" Y ",$D79)),(LEN($D79)-LEN(SUBSTITUTE(UPPER($D79),"LC","")))/2>1),"MÚLTIPLE","INDIVIDUAL")) | V79: =IF($D79="","",IF(AND(ISNUMBER(SEARCH(" Y ",$D79)),$F79<2),"REVISAR # LOTES",""))
B80: 78 | C80: LA CEIBA | D80: LC1 - 10 - 1 | E80: 1 | F80: 1 | G80: 10 | H80: 1 | I80: 175.4 | K80: 44740000 | L80: VENDIDO | M80: SI | N80: =K80 | U80: =IF($D80="","",IF(OR($F80>1,ISNUMBER(SEARCH(" Y ",$D80)),(LEN($D80)-LEN(SUBSTITUTE(UPPER($D80),"LC","")))/2>1),"MÚLTIPLE","INDIVIDUAL")) | V80: =IF($D80="","",IF(AND(ISNUMBER(SEARCH(" Y ",$D80)),$F80<2),"REVISAR # LOTES",""))
B81: 79 | C81: LA CEIBA | D81: LC1 - 10 - 2 | E81: 1 | F81: 1 | G81: 10 | H81: 2 | I81: 98 | K81: 25000000 | L81: VENDIDO | M81: NO | N81: =K81 | U81: =IF($D81="","",IF(OR($F81>1,ISNUMBER(SEARCH(" Y ",$D81)),(LEN($D81)-LEN(SUBSTITUTE(UPPER($D81),"LC","")))/2>1),"MÚLTIPLE","INDIVIDUAL")) | V81: =IF($D81="","",IF(AND(ISNUMBER(SEARCH(" Y ",$D81)),$F81<2),"REVISAR # LOTES",""))
B82: 80 | C82: LA CEIBA | D82: LC1 - 10 - 3 | E82: 1 | F82: 1 | G82: 10 | H82: 3 | I82: 98 | K82: 25000000 | L82: VENDIDO | M82: NO | N82: =K82 | U82: =IF($D82="","",IF(OR($F82>1,ISNUMBER(SEARCH(" Y ",$D82)),(LEN($D82)-LEN(SUBSTITUTE(UPPER($D82),"LC","")))/2>1),"MÚLTIPLE","INDIVIDUAL")) | V82: =IF($D82="","",IF(AND(ISNUMBER(SEARCH(" Y ",$D82)),$F82<2),"REVISAR # LOTES",""))
B83: 81 | C83: LA CEIBA | D83: LC1 - 10 - 4 | E83: 1 | F83: 1 | G83: 10 | H83: 4 | I83: 98 | K83: 30000000 | L83: VENDIDO | M83: NO | N83: =K83 | U83: =IF($D83="","",IF(OR($F83>1,ISNUMBER(SEARCH(" Y ",$D83)),(LEN($D83)-LEN(SUBSTITUTE(UPPER($D83),"LC","")))/2>1),"MÚLTIPLE","INDIVIDUAL")) | V83: =IF($D83="","",IF(AND(ISNUMBER(SEARCH(" Y ",$D83)),$F83<2),"REVISAR # LOTES",""))
B84: 82 | C84: LA CEIBA | D84: LC1 - 10 - 5 | E84: 1 | F84: 1 | G84: 10 | H84: 5 | I84: 98 | K84: 30000000 | L84: VENDIDO | M84: SI | N84: =K84 | U84: =IF($D84="","",IF(OR($F84>1,ISNUMBER(SEARCH(" Y ",$D84)),(LEN($D84)-LEN(SUBSTITUTE(UPPER($D84),"LC","")))/2>1),"MÚLTIPLE","INDIVIDUAL")) | V84: =IF($D84="","",IF(AND(ISNUMBER(SEARCH(" Y ",$D84)),$F84<2),"REVISAR # LOTES",""))
B85: 83 | C85: LA CEIBA | D85: LC1 - 10 - 6 | E85: 1 | F85: 1 | G85: 10 | H85: 6 | I85: 98 | K85: 25000000 | L85: VENDIDO | M85: SI | N85: =K85 | U85: =IF($D85="","",IF(OR($F85>1,ISNUMBER(SEARCH(" Y ",$D85)),(LEN($D85)-LEN(SUBSTITUTE(UPPER($D85),"LC","")))/2>1),"MÚLTIPLE","INDIVIDUAL")) | V85: =IF($D85="","",IF(AND(ISNUMBER(SEARCH(" Y ",$D85)),$F85<2),"REVISAR # LOTES",""))
B86: 84 | C86: LA CEIBA | D86: LC1 - 10 - 7 | E86: 1 | F86: 1 | G86: 10 | H86: 7 | I86: 98 | K86: 25000000 | L86: VENDIDO | N86: =K86 | U86: =IF($D86="","",IF(OR($F86>1,ISNUMBER(SEARCH(" Y ",$D86)),(LEN($D86)-LEN(SUBSTITUTE(UPPER($D86),"LC","")))/2>1),"MÚLTIPLE","INDIVIDUAL")) | V86: =IF($D86="","",IF(AND(ISNUMBER(SEARCH(" Y ",$D86)),$F86<2),"REVISAR # LOTES",""))
B87: 85 | C87: LA CEIBA | D87: LC1 - 10 - 8 | E87: 1 | F87: 1 | G87: 10 | H87: 8 | I87: 132.1 | K87: 33688000 | L87: VENDIDO | N87: =K87 | U87: =IF($D87="","",IF(OR($F87>1,ISNUMBER(SEARCH(" Y ",$D87)),(LEN($D87)-LEN(SUBSTITUTE(UPPER($D87),"LC","")))/2>1),"MÚLTIPLE","INDIVIDUAL")) | V87: =IF($D87="","",IF(AND(ISNUMBER(SEARCH(" Y ",$D87)),$F87<2),"REVISAR # LOTES",""))
B88: 86 | C88: LA CEIBA | D88: LC1 - 11- 1 | E88: 1 | F88: 1 | G88: 11 | H88: 1 | I88: 157.338 | K88: 40137000 | L88: VENDIDO | M88: SI | N88: =K88 | U88: =IF($D88="","",IF(OR($F88>1,ISNUMBER(SEARCH(" Y ",$D88)),(LEN($D88)-LEN(SUBSTITUTE(UPPER($D88),"LC","")))/2>1),"MÚLTIPLE","INDIVIDUAL")) | V88: =IF($D88="","",IF(AND(ISNUMBER(SEARCH(" Y ",$D88)),$F88<2),"REVISAR # LOTES",""))
B89: 87 | C89: LA CEIBA | D89: LC1 - 11 - 2 | E89: 1 | F89: 1 | G89: 11 | H89: 2 | I89: 89 | K89: 25000000 | L89: VENDIDO | M89: NO | N89: =K89 | U89: =IF($D89="","",IF(OR($F89>1,ISNUMBER(SEARCH(" Y ",$D89)),(LEN($D89)-LEN(SUBSTITUTE(UPPER($D89),"LC","")))/2>1),"MÚLTIPLE","INDIVIDUAL")) | V89: =IF($D89="","",IF(AND(ISNUMBER(SEARCH(" Y ",$D89)),$F89<2),"REVISAR # LOTES",""))
B90: 88 | C90: LA CEIBA | D90: LC1 - 11 - 3 | E90: 1 | F90: 1 | G90: 11 | H90: 3 | I90: 98 | K90: 25000000 | L90: VENDIDO | N90: =K90 | U90: =IF($D90="","",IF(OR($F90>1,ISNUMBER(SEARCH(" Y ",$D90)),(LEN($D90)-LEN(SUBSTITUTE(UPPER($D90),"LC","")))/2>1),"MÚLTIPLE","INDIVIDUAL")) | V90: =IF($D90="","",IF(AND(ISNUMBER(SEARCH(" Y ",$D90)),$F90<2),"REVISAR # LOTES",""))
B91: 89 | C91: LA CEIBA | D91: LC1 - 11 - 4 | E91: 1 | F91: 1 | G91: 11 | H91: 4 | I91: 98 | K91: 25000000 | L91: VENDIDO | M91: NO | N91: =K91 | U91: =IF($D91="","",IF(OR($F91>1,ISNUMBER(SEARCH(" Y ",$D91)),(LEN($D91)-LEN(SUBSTITUTE(UPPER($D91),"LC","")))/2>1),"MÚLTIPLE","INDIVIDUAL")) | V91: =IF($D91="","",IF(AND(ISNUMBER(SEARCH(" Y ",$D91)),$F91<2),"REVISAR # LOTES",""))
B92: 90 | C92: LA CEIBA | D92: LC1 - 11 - 5 | E92: 1 | F92: 1 | G92: 11 | H92: 5 | I92: 98 | K92: 25000000 | L92: VENDIDO | M92: SI | N92: =K92 | U92: =IF($D92="","",IF(OR($F92>1,ISNUMBER(SEARCH(" Y ",$D92)),(LEN($D92)-LEN(SUBSTITUTE(UPPER($D92),"LC","")))/2>1),"MÚLTIPLE","INDIVIDUAL")) | V92: =IF($D92="","",IF(AND(ISNUMBER(SEARCH(" Y ",$D92)),$F92<2),"REVISAR # LOTES",""))
B93: 91 | C93: LA CEIBA | D93: LC1 - 11 - 6 Y 7 | E93: 1 | F93: 2 | G93: 11 | H93: 6 - 7 | I93: 196 | K93: 50000000 | L93: VENDIDO | M93: SI | N93: =K93 | U93: =IF($D93="","",IF(OR($F93>1,ISNUMBER(SEARCH(" Y ",$D93)),(LEN($D93)-LEN(SUBSTITUTE(UPPER($D93),"LC","")))/2>1),"MÚLTIPLE","INDIVIDUAL")) | V93: =IF($D93="","",IF(AND(ISNUMBER(SEARCH(" Y ",$D93)),$F93<2),"REVISAR # LOTES",""))
B94: 92 | C94: LA CEIBA | D94: LC1 - 11 - 8 | E94: 1 | F94: 1 | G94: 11 | H94: 8 | I94: 98 | K94: 30000000 | L94: VENDIDO | M94: NO | N94: =K94 | U94: =IF($D94="","",IF(OR($F94>1,ISNUMBER(SEARCH(" Y ",$D94)),(LEN($D94)-LEN(SUBSTITUTE(UPPER($D94),"LC","")))/2>1),"MÚLTIPLE","INDIVIDUAL")) | V94: =IF($D94="","",IF(AND(ISNUMBER(SEARCH(" Y ",$D94)),$F94<2),"REVISAR # LOTES",""))
B95: 93 | C95: LA CEIBA | D95: LC1 - 11 - 9 | E95: 1 | F95: 1 | G95: 11 | H95: 9 | I95: 98 | K95: 30000000 | L95: VENDIDO | M95: SI | N95: =K95 | U95: =IF($D95="","",IF(OR($F95>1,ISNUMBER(SEARCH(" Y ",$D95)),(LEN($D95)-LEN(SUBSTITUTE(UPPER($D95),"LC","")))/2>1),"MÚLTIPLE","INDIVIDUAL")) | V95: =IF($D95="","",IF(AND(ISNUMBER(SEARCH(" Y ",$D95)),$F95<2),"REVISAR # LOTES",""))
B96: 94 | C96: LA CEIBA | D96: LC1 - 11 - 10 | E96: 1 | F96: 1 | G96: 11 | H96: 10 | I96: 98 | K96: 25000000 | L96: EN NEGOCIACIÓN | N96: =K96 | U96: =IF($D96="","",IF(OR($F96>1,ISNUMBER(SEARCH(" Y ",$D96)),(LEN($D96)-LEN(SUBSTITUTE(UPPER($D96),"LC","")))/2>1),"MÚLTIPLE","INDIVIDUAL")) | V96: =IF($D96="","",IF(AND(ISNUMBER(SEARCH(" Y ",$D96)),$F96<2),"REVISAR # LOTES",""))
B97: 95 | C97: LA CEIBA | D97: LC1 - 11 - 11 | E97: 1 | F97: 1 | G97: 11 | H97: 11 | I97: 98 | K97: 25000000 | L97: VENDIDO | M97: NO | N97: =K97 | U97: =IF($D97="","",IF(OR($F97>1,ISNUMBER(SEARCH(" Y ",$D97)),(LEN($D97)-LEN(SUBSTITUTE(UPPER($D97),"LC","")))/2>1),"MÚLTIPLE","INDIVIDUAL")) | V97: =IF($D97="","",IF(AND(ISNUMBER(SEARCH(" Y ",$D97)),$F97<2),"REVISAR # LOTES",""))
B98: 96 | C98: LA CEIBA | D98: LC1 - 11 - 12 | E98: 1 | F98: 1 | G98: 11 | H98: 12 | I98: 98 | K98: 24500000 | L98: VENDIDO | M98: SI | N98: =K98 | U98: =IF($D98="","",IF(OR($F98>1,ISNUMBER(SEARCH(" Y ",$D98)),(LEN($D98)-LEN(SUBSTITUTE(UPPER($D98),"LC","")))/2>1),"MÚLTIPLE","INDIVIDUAL")) | V98: =IF($D98="","",IF(AND(ISNUMBER(SEARCH(" Y ",$D98)),$F98<2),"REVISAR # LOTES",""))
B99: 97 | C99: LA CEIBA | D99: LC1 - 11 - 13 | E99: 1 | F99: 1 | G99: 11 | H99: 13 | I99: 98 | K99: 24500000 | L99: VENDIDO | M99: NO | N99: =K99 | U99: =IF($D99="","",IF(OR($F99>1,ISNUMBER(SEARCH(" Y ",$D99)),(LEN($D99)-LEN(SUBSTITUTE(UPPER($D99),"LC","")))/2>1),"MÚLTIPLE","INDIVIDUAL")) | V99: =IF($D99="","",IF(AND(ISNUMBER(SEARCH(" Y ",$D99)),$F99<2),"REVISAR # LOTES",""))
B100: 98 | C100: LA CEIBA | D100: LC1 - 11 - 14 | E100: 1 | F100: 1 | G100: 11 | H100: 14 | I100: 197.567 | K100: 49900000 | L100: VENDIDO | M100: SI | N100: =K100 | U100: =IF($D100="","",IF(OR($F100>1,ISNUMBER(SEARCH(" Y ",$D100)),(LEN($D100)-LEN(SUBSTITUTE(UPPER($D100),"LC","")))/2>1),"MÚLTIPLE","INDIVIDUAL")) | V100: =IF($D100="","",IF(AND(ISNUMBER(SEARCH(" Y ",$D100)),$F100<2),"REVISAR # LOTES",""))
...

Sheet VENTAS
A2: ITEM | B2: ID LOTE | C2: ESTADO | D2: PRECIO DE VENTA | E2: APARTADOS | F2: FECHA DE VENTA | G2: VALOR CUOTA INICIAL | H2: FECHA DE PAGO DE LA CUOTA INICIAL | I2: MEDIO DE PAGO | J2: SALDO FINANCIADO | K2: PLAZO/CUOTAS | L2: VALOR CUOTA | M2: DIAS DE PAGO | N2: # DOC CLIENTE | O2: NOMBRE Y APELLIDOS | P2: CELULAR | Q2: DIRECCIÓN | R2: CIUDAD | T2: COMISIÓN VENDEDOR | U2: ABONOS | V2: DESCUENTOS | W2: SALDO
A3: =LISTADO!B3 | B3: =LISTADO!D3 | C3: =LISTADO!L3 | D3: =LISTADO!K3 | J3: =D3-G3 | W3: =T3-U3-V3
A4: =LISTADO!B4 | B4: =LISTADO!D4 | C4: =LISTADO!L4 | D4: =LISTADO!K4 | F4: 45839 | G4: 8000000 | H4: 45870 | I4: EFECTIVO | J4: =D4-G4 | K4: 24 | L4: =J4/K4 | M4: 01 DE CADA MES | N4: 52466375 | O4: ANA MILENA CHAVES/JOSE IGNACIO DIAZ | P4: 311 5303163 | R4: BOGOTA | S4: SNEIDER | T4: 10000000 | U4: 6000000 | W4: =T4-U4-V4
A5: =LISTADO!B5 | B5: =LISTADO!D5 | C5: =LISTADO!L5 | D5: =LISTADO!K5 | F5: 45890 | G5: 4000000 | H5: 45921 | I5: EFECTIVO | J5: =D5-G5 | K5: 24 | L5: =J5/K5 | M5: 21 DE CADA MES | N5: 46645364 | O5: MARIA EUGENIA RIOS/ARTURO CARRILLO MEJIA | P5: 316 3162386 | R5: BOYACA | S5: SNEIDER | T5: 5000000 | U5: 5000000 | W5: =T5-U5-V5
A6: =LISTADO!B6 | B6: =LISTADO!D6 | C6: =LISTADO!L6 | D6: =LISTADO!K6 | F6: 46002 | G6: 5400000 | H6: 46033 | I6: EFECTIVO | J6: =D6-G6 | K6: 24 | L6: =J6/K6 | M6: 11 DE CADA MES | N6: 1000001654 | O6: FREDY LEANDRO CASTRO DULCEY | P6: 300 5655877 | R6: BOGOTA | S6: DANIEL BARRETO | T6: 5000000 | U6: 3000000 | W6: =T6-U6-V6
A7: =LISTADO!B7 | B7: =LISTADO!D7 | C7: =LISTADO!L7 | D7: =LISTADO!K7 | F7: 45845 | G7: 4000000 | H7: 45876 | I7: EFECTIVO | J7: =D7-G7 | K7: 24 | L7: =J7/K7 | M7: 07 DE CADA MES | N7: 1016011597 | O7: DIVIANGI PAOLA LARREA AVILA | P7: 320 3658707 | R7: BOGOTA | S7: YURANY PEREZ | T7: 5000000 | U7: 3000000 | W7: =T7-U7-V7
A8: =LISTADO!B8 | B8: =LISTADO!D8 | C8: =LISTADO!L8 | D8: =LISTADO!K8 | F8: 45855 | G8: 4000000 | H8: 45886 | I8: EFECTIVO | J8: =D8-G8 | K8: 24 | L8: =J8/K8 | M8: 17 DE CADA MES | N8: 1065606738 | O8: DIANA CAROLINA SANTIAGO BELLO | P8: 324 4168643 | R8: BOGOTA | S8: DANIA | T8: 5000000 | U8: 3000000 | W8: =T8-U8-V8
A9: =LISTADO!B9 | B9: =LISTADO!D9 | C9: =LISTADO!L9 | D9: =LISTADO!K9 | J9: =D9-G9 | K9: 1 | L9: =J9/K9 | O9: RUBEN FABIAN BUSTOS | W9: =T9-U9-V9
A10: =LISTADO!B10 | B10: =LISTADO!D10 | C10: =LISTADO!L10 | D10: =LISTADO!K10 | J10: =D10-G10 | K10: 1 | L10: =J10/K10 | O10: RUBEN FABIAN BUSTOS | W10: =T10-U10-V10
A11: =LISTADO!B11 | B11: =LISTADO!D11 | C11: =LISTADO!L11 | D11: =LISTADO!K11 | J11: =D11-G11 | K11: 1 | L11: =J11/K11 | O11: RUBEN FABIAN BUSTOS | W11: =T11-U11-V11
A12: =LISTADO!B12 | B12: =LISTADO!D12 | C12: =LISTADO!L12 | D12: =LISTADO!K12 | F12: 46041 | G12: 4000000 | H12: 46072 | I12: EFECTIVO | J12: =D12-G12 | K12: 24 | L12: =J12/K12 | M12: 19 DE CADA MES | N12: 51803549 | O12: MARTHA EUGENIA OCAMPO GOMEZ | P12: 3223810013 | R12: ACACIAS | S12: KATHERINE TACHA | T12: 5000000 | U12: 3000000 | W12: =T12-U12-V12
A13: =LISTADO!B13 | B13: =LISTADO!D13 | C13: =LISTADO!L13 | D13: =LISTADO!K13 | F13: 45855 | G13: 4000000 | H13: 45886 | I13: EFECTIVO | J13: =D13-G13 | K13: 24 | L13: =J13/K13 | M13: 17 DE CADA MES | N13: 49595489 | O13: JOSSY XIMENA CASTELLANOS CARRILLO | P13: 305 4524007 | R13: BOSCONIA | S13: DANIA | T13: 5000000 | U13: 3000000 | W13: =T13-U13-V13
A14: =LISTADO!B14 | B14: =LISTADO!D14 | C14: =LISTADO!L14 | D14: =LISTADO!K14 | F14: 45865 | G14: 8000000 | H14: 45896 | I14: EFECTIVO | J14: =D14-G14 | K14: 24 | L14: =J14/K14 | M14: 27 DE CADA MES | N14: 36622525 | O14: BETTY ENCARNACION CARRILLO | P14: 304 5900648 | R14: ACACIAS | S14: DANIA | T14: 10000000 | U14: 6000000 | W14: =T14-U14-V14
A15: =LISTADO!B15 | B15: =LISTADO!D15 | C15: =LISTADO!L15 | D15: =LISTADO!K15 | J15: =D15-G15 | K15: 1 | L15: =J15/K15 | O15: RUBEN FABIAN BUSTO | W15: =T15-U15-V15
A16: =LISTADO!B16 | B16: =LISTADO!D16 | C16: =LISTADO!L16 | D16: =LISTADO!K16 | J16: =D16-G16 | L16: =J16/K16 | W16: =T16-U16-V16
A17: =LISTADO!B17 | B17: =LISTADO!D17 | C17: =LISTADO!L17 | D17: =LISTADO!K17 | F17: 45936 | G17: 4000000 | H17: 45967 | I17: EFECTIVO | J17: =D17-G17 | K17: 24 | L17: =J17/K17 | M17: 06 DE CADA MES | N17: 7182722 | O17: EDGAR VICENTE CARDENAS LOPEZ | P17: 313 2213086 | R17: TUNJA | S17: JHON JAIRO RINCON | T17: 5000000 | U17: 3000000 | W17: =T17-U17-V17
A18: =LISTADO!B18 | B18: =LISTADO!D18 | C18: =LISTADO!L18 | D18: =LISTADO!K18 | F18: 46102 | G18: 4000000 | H18: 46086 | I18: EFECTIVO | J18: =D18-G18 | K18: 24 | L18: =J18/K18 | M18: 05 DE CADA MES | N18: 41627694 | O18: RAQUEL ABELLA VALBUENA | P18: 316 3901345 | R18: BOGOTA | S18: GUSTAVO | T18: 5000000 | U18: 3000000 | W18: =T18-U18-V18
A19: =LISTADO!B19 | B19: =LISTADO!D19 | C19: =LISTADO!L19 | D19: =LISTADO!K19 | F19: 46102 | G19: 4000000 | H19: 46086 | I19: EFECTIVO | J19: =D19-G19 | K19: 24 | L19: =J19/K19 | M19: 05 DE CADA MES | N19: 41627694 | O19: RAQUEL ABELLA VALBUENA | P19: 316 3901345 | R19: BOGOTA | S19: GUSTAVO | T19: 5000000 | U19: 3000000 | W19: =T19-U19-V19
A20: =LISTADO!B20 | B20: =LISTADO!D20 | C20: =LISTADO!L20 | D20: =LISTADO!K20 | F20: 46128 | G20: 4000000 | H20: 46128 | I20: TRANSFERENCIA | J20: =D20-G20 | K20: 24 | L20: =J20/K20 | M20: 16 DE CADA MES | N20: 1026277934 | O20: SAMANTA VALENSUELA BARRAZA | S20: YURANY PEREZ | T20: 5000000 | W20: =T20-U20-V20
A21: =LISTADO!B21 | B21: =LISTADO!D21 | C21: =LISTADO!L21 | D21: =LISTADO!K21 | J21: =D21-G21 | L21: =J21/K21 | W21: =T21-U21-V21
A22: =LISTADO!B22 | B22: =LISTADO!D22 | C22: =LISTADO!L22 | D22: =LISTADO!K22 | J22: =D22-G22 | L22: =J22/K22 | W22: =T22-U22-V22
A23: =LISTADO!B23 | B23: =LISTADO!D23 | C23: =LISTADO!L23 | D23: =LISTADO!K23 | F23: 45920 | G23: 4000000 | H23: 45950 | I23: EFECTIVO | J23: =D23-G23 | K23: 24 | L23: =J23/K23 | M23: 20 DE CADA MES | N23: 1121947747 | O23: LUISA FERNANDA GOMEZ CARRERO/JUAN DAVID REY | P23: 310 6673835 | R23: VILLAVICENCIO | S23: INGRID | T23: 5000000 | U23: 3000000 | W23: =T23-U23-V23
A24: =LISTADO!B24 | B24: =LISTADO!D24 | C24: =LISTADO!L24 | D24: =LISTADO!K24 | F24: 45902 | G24: 8000000 | H24: 45932 | I24: EFECTIVO | J24: =D24-G24 | K24: 24 | L24: =J24/K24 | M24: 02 DE CADA MES | N24: 26203383 | O24: FATIMA RAMIREZ MORALES | P24: 313 22006339 | R24: MONTERIA | S24: DANIA | T24: 10000000 | U24: 6000000 | W24: =T24-U24-V24
A25: =LISTADO!B25 | B25: =LISTADO!D25 | C25: =LISTADO!L25 | D25: =LISTADO!K25 | J25: =D25-G25 | L25: =J25/K25 | O25: RUBEN FABIAN BUSTOS | W25: =T25-U25-V25
A26: =LISTADO!B26 | B26: =LISTADO!D26 | C26: =LISTADO!L26 | D26: =LISTADO!K26 | F26: 46178 | G26: 4000000 | H26: 46178 | I26: TRANSFERENCIA | J26: 39380000 | K26: 24 | L26: =J26/K26 | M26: 5 DE CADA MES | N26: 51648764 | O26: MARIA YOLANDA CARACAS LEÓN | P26: 321 4612934 | S26: JEFFERSON | T26: 5000000 | U26: 3000000 | W26: =T26-U26-V26
A27: =LISTADO!B27 | B27: =LISTADO!D27 | C27: =LISTADO!L27 | D27: =LISTADO!K27 | F27: 30/02/2026 | G27: 8000000 | H27: 46111 | I27: EFECTIVO | J27: =D27-G27 | K27: 30 | L27: =J27/K27 | M27: 30 DE CADA MES | N27: 1007157001 | O27: LEIDY JOHANNA SAENZ/JHOJAN STIVEN GUTIERREZ | P27: 301 2669937 | R27: BOGOTA | S27: INGRID | T27: 5000000 | U27: 3000000 | W27: =T27-U27-V27
A28: =LISTADO!B28 | B28: =LISTADO!D28 | C28: =LISTADO!L28 | D28: =LISTADO!K28 | F28: 46063 | G28: 9000000 | H28: 46091 | I28: EFECTIVO | J28: =D28-G28 | K28: 30 | L28: =J28/K28 | M28: 10 DE CADA MES | N28: 41795576 | O28: AURA ALICIA SAENZ | P28: 312 3756562 | R28: BOGOTA | S28: INGRID | T28: 5000000 | U28: 3000000 | W28: =T28-U28-V28
A29: =LISTADO!B29 | B29: =LISTADO!D29 | C29: =LISTADO!L29 | D29: =LISTADO!K29 | F29: 46060 | G29: 13000000 | H29: 46088 | I29: EFECTIVO | J29: =D29-G29 | K29: 30 | L29: =J29/K29 | M29: 07 DE CADA MES | N29: 1007157000 | O29: EDUINXON ALEXANDER SAENZ PINZON | P29: 301 7284433 | R29: BOGOTA | S29: INGRID | T29: 5000000 | U29: 3000000 | W29: =T29-U29-V29
A30: =LISTADO!B30 | B30: =LISTADO!D30 | C30: =LISTADO!L30 | D30: =LISTADO!K30 | J30: =D30-G30 | K30: 1 | L30: =J30/K30 | N30: 80390046 | O30: JORGE HUMBERTO RODRIGUEZ BORBON | W30: =T30-U30-V30
A31: =LISTADO!B31 | B31: =LISTADO!D31 | C31: =LISTADO!L31 | D31: =LISTADO!K31 | F31: 46031 | G31: 4000000 | H31: 46062 | I31: EFECTIVO | J31: =D31-G31 | K31: 24 | L31: =J31/K31 | M31: 09 DE CADA MES | N31: 51578847 | O31: LUZ MYRIAM DÍAZ | P31: 312 3492087 | R31: BOGOTA | S31: LUBIN DIAZ | T31: 5000000 | U31: 3000000 | W31: =T31-U31-V31
A32: =LISTADO!B32 | B32: =LISTADO!D32 | C32: =LISTADO!L32 | D32: =LISTADO!K32 | F32: 46031 | G32: 4500000 | H32: 46062 | I32: EFECTIVO | J32: =D32-G32 | K32: 24 | L32: =J32/K32 | M32: 09 DE CADA MES | N32: 1085039584 | O32: ALEXIS JOSE PABA MARTINEZ | P32: 34 62419 4900 | R32: EL BANCO | S32: LUBIN DIAZ | T32: 5000000 | U32: 3000000 | W32: =T32-U32-V32
A33: =LISTADO!B33 | B33: =LISTADO!D33 | C33: =LISTADO!L33 | D33: =LISTADO!K33 | F33: 46150 | G33: 4000000 | H33: 46150 | I33: TRANSFERENCIA | J33: =D33-G33 | K33: 24 | L33: =J33/K33 | M33: 30 DE CADA MES | N33: 1024499636 | O33: DANNA LIZETH ALVAREZ SANCHEZ | P33: 310 240 1772 | R33: CUNDINAMARCA | S33: YURANY PEREZ | T33: 5000000 | W33: =T33-U33-V33
A34: =LISTADO!B34 | B34: =LISTADO!D34 | C34: =LISTADO!L34 | D34: =LISTADO!K34 | F34: 45701 | G34: 4000000 | H34: 45729 | I34: EFECTIVO | J34: =D34-G34 | K34: 24 | L34: =J34/K34 | M34: 13 DE CADA MES | N34: 1015408595 | O34: LUIS AGUSTO PALACIOS RODRIGUEZ | P34: 3228636376 | R34: BOGOTA | W34: =T34-U34-V34
A35: =LISTADO!B35 | B35: =LISTADO!D35 | C35: =LISTADO!L35 | D35: =LISTADO!K35 | F35: 45874 | G35: 4500000 | H35: 45905 | I35: EFECTIVO | J35: =D35-G35 | K35: 24 | L35: =J35/K35 | M35: 05 DE CADA MES | N35: 1012356817 | O35: YULEY SERRANO PAVA/DIEGO FERNANDO BUITRAGO | P35: 311 2085098 | R35: BOGOTA | S35: JHON CARVAJAL | T35: 5000000 | U35: 3000000 | W35: =T35-U35-V35
A36: =LISTADO!B36 | B36: =LISTADO!D36 | C36: =LISTADO!L36 | D36: =LISTADO!K36 | F36: 45874 | G36: 4500000 | H36: 45905 | I36: EFECTIVO | J36: =D36-G36 | K36: 24 | L36: =J36/K36 | M36: 05 DE CADA MES | N36: 1030701120 | O36: ANDRÉS FELIPE CARDONA ARCHILA | P36: 315 4450034 | R36: BOGOTA | S36: MAYERLY | T36: 5000000 | U36: 3000000 | W36: =T36-U36-V36
A37: =LISTADO!B37 | B37: =LISTADO!D37 | C37: =LISTADO!L37 | D37: =LISTADO!K37 | F37: 45874 | G37: 7500000 | H37: 45905 | I37: EFECTIVO | J37: =D37-G37 | K37: 24 | L37: =J37/K37 | M37: 05 DE CADA MES | N37: 1123433099 | O37: JEIDER HERNEY POVEDA ROSO | P37: 3195907896 | R37: CASTILLA LA NUEVA | S37: YULIAN CARDENAS | T37: 5000000 | U37: 5000000 | W37: =T37-U37-V37
A38: =LISTADO!B38 | B38: =LISTADO!D38 | C38: =LISTADO!L38 | D38: =LISTADO!K38 | F38: 46073 | G38: 4000000 | H38: 46101 | I38: EFECTIVO | J38: =D38-G38 | K38: 24 | L38: =J38/K38 | M38: 20 DE CADA MES | N38: 1123085644 | O38: MILENA JOHANNA COCA MEJIA/YEISON ALBERTO MONROY | P38: 313 3458707 | R38: GUAMAL | S38: YURANY PEREZ | T38: 5000000 | U38: 3000000 | W38: =T38-U38-V38
A39: =LISTADO!B39 | B39: =LISTADO!D39 | C39: =LISTADO!L39 | D39: =LISTADO!K39 | F39: 45842 | G39: 4000000 | H39: 45873 | I39: EFECTIVO | J39: =D39-G39 | K39: 24 | L39: =J39/K39 | M39: 04 DE CADA MES | N39: 1003519576 | O39: YARID MARIANA MONROY VIVAS | P39: 704 2989061 | R39: FUSAGASUGA | S39: CARLOS JULIAN | T39: 5000000 | U39: 3000000 | W39: =T39-U39-V39
A40: =LISTADO!B40 | B40: =LISTADO!D40 | C40: =LISTADO!L40 | D40: =LISTADO!K40 | F40: 45888 | G40: 10000000 | H40: 45919 | I40: EFECTIVO | J40: =D40-G40 | K40: 24 | L40: =J40/K40 | M40: 19 DE CADA MES | N40: 4157914 | O40: LUIS ENRIQUE ALARCON CRUZ | P40: 316 3355530 | R40: BOYACA | S40: YULIAN CARDENAS | T40: 5000000 | U40: 3000000 | W40: =T40-U40-V40
A41: =LISTADO!B41 | B41: =LISTADO!D41 | C41: =LISTADO!L41 | D41: =LISTADO!K41 | F41: 45656 | G41: 4000000 | H41: 45687 | I41: EFECTIVO | J41: =D41-G41 | K41: 24 | L41: =J41/K41 | M41: 30 DE CADA MES | N41: 86011972 | O41: JOSÉ ALCIDES QUINTERO GAITAN | P41: 322 2458447 | R41: GRANADA | W41: =T41-U41-V41
A42: =LISTADO!B42 | B42: =LISTADO!D42 | C42: =LISTADO!L42 | D42: =LISTADO!K42 | F42: 45859 | G42: 4000000 | H42: 45890 | I42: EFECTIVO | J42: =D42-G42 | K42: 24 | L42: =J42/K42 | M42: 21 DE CADA MES | N42: 1032411465 | O42: NORLEIDY GARZON SANCHEZ | P42: 310 2983071 | R42: BOGOTA | S42: SNEIDER | T42: 5000000 | U42: 3000000 | W42: =T42-U42-V42
A43: =LISTADO!B43 | B43: =LISTADO!D43 | C43: =LISTADO!L43 | D43: =LISTADO!K43 | F43: 45832 | G43: 4000000 | H43: 45862 | I43: EFECTIVO | J43: =D43-G43 | K43: 24 | L43: =J43/K43 | M43: 24 DE CADA MES | N43: 39664442 | O43: LUZ DARY MANCERA CAMELO | P43: 321 3212040 | R43: BOGOTA | W43: =T43-U43-V43
A44: =LISTADO!B44 | B44: =LISTADO!D44 | C44: =LISTADO!L44 | D44: =LISTADO!K44 | F44: 45899 | G44: 4000000 | H44: 45920 | I44: EFECTIVO | J44: =D44-G44 | K44: 24 | L44: =J44/K44 | M44: 30 DE CADA MES | N44: 1123513435 | O44: YULY PAOLA POVEDA ROSO | P44: 320 8381815 | R44: CASTILLA LA NUEVA | S44: YULIAN CARDENAS | T44: 5000000 | U44: 3000000 | W44: =T44-U44-V44
A45: =LISTADO!B45 | B45: =LISTADO!D45 | C45: =LISTADO!L45 | D45: =LISTADO!K45 | F45: 45845 | G45: 4000000 | H45: 45876 | I45: EFECTIVO | J45: =D45-G45 | K45: 24 | L45: =J45/K45 | M45: 07 DE CADA MES | N45: 1006837128 | O45: DIEGO FABIAN GRANADA SILVA | P45: 321 4573910 | R45: GRANADA | S45: YURANY PEREZ | T45: 5000000 | U45: 3000000 | W45: =T45-U45-V45
A46: =LISTADO!B46 | B46: =LISTADO!D46 | C46: =LISTADO!L46 | D46: =LISTADO!K46 | F46: 45508 | G46: 4000000 | H46: 45904 | I46: EFECTIVO | J46: =D46-G46 | K46: 24 | L46: =J46/K46 | M46: 04 DE CADA MES | N46: 79925440 | O46: OSCAR ESNEIDER PEREZ RODRIGUEZ | P46: 310 3309150 | R46: BOGOTA | S46: MAYERLY | T46: 5000000 | U46: 3000000 | W46: =T46-U46-V46
A47: =LISTADO!B47 | B47: =LISTADO!D47 | C47: =LISTADO!L47 | D47: =LISTADO!K47 | F47: 45895 | G47: 16000000 | H47: 45926 | I47: EFECTIVO | J47: =D47-G47 | K47: 24 | L47: =J47/K47 | M47: 26 DE CADA MES | N47: 51734969 | O47: NOHELIA ALZATE GIRALDO | P47: 301 4003174 | R47: BOGOTA | S47: YURANY PEREZ | T47: 20000000 | U47: 12000000 | W47: =T47-U47-V47
A48: =LISTADO!B48 | B48: =LISTADO!D48 | C48: =LISTADO!L48 | D48: =LISTADO!K48 | F48: 45881 | G48: 4000000 | H48: 45912 | I48: EFECTIVO | J48: =D48-G48 | K48: 24 | L48: =J48/K48 | M48: 12 DE CADA MES | N48: 79254901 | O48: ORLANDO ANTONIO MESA PLATA | P48: 313 8876930 | R48: BOGOTA | S48: EIDER PARDO | T48: 5000000 | U48: 3000000 | W48: =T48-U48-V48
A49: =LISTADO!B49 | B49: =LISTADO!D49 | C49: =LISTADO!L49 | D49: =LISTADO!K49 | J49: =D49-G49 | L49: =J49/K49 | O49: RUBEN FABIAN BUSTOS | W49: =T49-U49-V49
A50: =LISTADO!B50 | B50: =LISTADO!D50 | C50: =LISTADO!L50 | D50: =LISTADO!K50 | F50: 45881 | G50: 4000000 | H50: 45912 | I50: EFECTIVO | J50: =D50-G50 | K50: 24 | L50: =J50/K50 | M50: 12 DE CADA MES | N50: 79254901 | O50: ORLANDO ANTONIO MESA PLATA | P50: 313 8876930 | R50: BOGOTA | S50: EIDER PARDO | T50: 5000000 | U50: 3000000 | W50: =T50-U50-V50
A51: =LISTADO!B51 | B51: =LISTADO!D51 | C51: =LISTADO!L51 | D51: =LISTADO!K51 | F51: 45881 | G51: 4000000 | H51: 45912 | I51: EFECTIVO | J51: =D51-G51 | K51: 24 | L51: =J51/K51 | M51: 12 DE CADA MES | N51: 79254901 | O51: ORLANDO ANTONIO MESA PLATA | P51: 313 8876930 | R51: BOGOTA | S51: EIDER PARDO | T51: 5000000 | U51: 3000000 | W51: =T51-U51-V51
A52: =LISTADO!B52 | B52: =LISTADO!D52 | C52: =LISTADO!L52 | D52: =LISTADO!K52 | J52: =D52-G52 | L52: =J52/K52 | W52: =T52-U52-V52
A53: =LISTADO!B53 | B53: =LISTADO!D53 | C53: =LISTADO!L53 | D53: =LISTADO!K53 | F53: 45852 | G53: 4000000 | H53: 45883 | I53: EFECTIVO | J53: =D53-G53 | K53: 24 | L53: =J53/K53 | M53: 14 DE CADA MES | N53: 51781576 | O53: LUCINDA CLAVIJO CLAVIJO/LUIS ROBERTO MENDEZ | P53: 321 445 4526 | R53: BOGOTA | S53: COCO | T53: 5000000 | U53: 3000000 | W53: =T53-U53-V53
A54: =LISTADO!B54 | B54: =LISTADO!D54 | C54: =LISTADO!L54 | D54: =LISTADO!K54 | F54: 45897 | G54: 25000000 | H54: 45897 | I54: EFECTIVO | J54: =D54-G54 | K54: 1 | L54: 0 | N54: 1122653962 | O54: DIEGO FABIAN REY BOBADILLA | P54: 322 4398529 | R54: RESTREPO | S54: YULIAN CARDENAS | T54: 5000000 | U54: 5000000 | W54: =T54-U54-V54
A55: =LISTADO!B55 | B55: =LISTADO!D55 | C55: =LISTADO!L55 | D55: =LISTADO!K55 | F55: 45859 | G55: 4000000 | H55: 45890 | I55: EFECTIVO | J55: =D55-G55 | K55: 24 | L55: =J55/K55 | M55: 21 DE CADA MES | N55: 1121906209 | O55: WILMER STEVEN ROMERO CESPEDES | P55: 318 4910833 | R55: VILLAVICENCIO | S55: DANIA | T55: 5000000 | U55: 3000000 | W55: =T55-U55-V55
A56: =LISTADO!B56 | B56: =LISTADO!D56 | C56: =LISTADO!L56 | D56: =LISTADO!K56 | F56: 45827 | G56: 4000000 | H56: 45857 | I56: EFECTIVO | J56: =D56-G56 | K56: 24 | L56: =J56/K56 | M56: 19 DE CADA MES | N56: 1016038981 | O56: ANDREA MILENA SEGURA SEGURA | P56: 313 3023199 | R56: ACACIAS | S56: JUAN DAVID | T56: 5000000 | U56: 3000000 | W56: =T56-U56-V56
A57: =LISTADO!B57 | B57: =LISTADO!D57 | C57: =LISTADO!L57 | D57: =LISTADO!K57 | F57: 45857 | G57: 4000000 | H57: 45888 | I57: EFECTIVO | J57: =D57-G57 | K57: 24 | L57: =J57/K57 | M57: 19 DE CADA MES | N57: 51823486 | O57: MARIA EUGENIA SEGURA SEGURA | P57: 310 7831185 | R57: BOGOTA | S57: JUAN DAVID | T57: 5000000 | U57: 3000000 | W57: =T57-U57-V57
A58: =LISTADO!B58 | B58: =LISTADO!D58 | C58: =LISTADO!L58 | D58: =LISTADO!K58 | F58: 45857 | G58: 4000000 | H58: 45888 | I58: EFECTIVO | J58: =D58-G58 | K58: 24 | L58: =J58/K58 | M58: 19 DE CADA MES | N58: 1067465637 | O58: EMILIANO SEGURA SEGURA | P58: 314 3934068 | R58: CUNDINAMARCA | S58: JUAN DAVID | T58: 5000000 | U58: 3000000 | W58: =T58-U58-V58
A59: =LISTADO!B59 | B59: =LISTADO!D59 | C59: =LISTADO!L59 | D59: =LISTADO!K59 | F59: 45827 | G59: 4000000 | H59: 45857 | I59: EFECTIVO | J59: =D59-G59 | K59: 24 | L59: =J59/K59 | M59: 19 DE CADA MES | N59: 1000515503 | O59: EDGAR SANTIAGO SEGURA PRIETO | P59: 322 2619134 | R59: BOGOTA | S59: JUAN DAVID | T59: 5000000 | U59: 3000000 | W59: =T59-U59-V59
A60: =LISTADO!B60 | B60: =LISTADO!D60 | C60: =LISTADO!L60 | D60: =LISTADO!K60 | F60: 45857 | G60: 4000000 | H60: 45888 | I60: EFECTIVO | J60: =D60-G60 | K60: 24 | L60: =J60/K60 | M60: 19 DE CADA MES | N60: 1019987010 | O60: IVAN DARIO SEGURA | P60: 302 7064860 | R60: BOGOTA | S60: JUAN DAVID | T60: 5000000 | U60: 3000000 | W60: =T60-U60-V60
A61: =LISTADO!B61 | B61: =LISTADO!D61 | C61: =LISTADO!L61 | D61: =LISTADO!K61 | F61: 45892 | G61: 4000000 | H61: 45558 | I61: EFECTIVO | J61: =D61-G61 | K61: 24 | L61: =J61/K61 | M61: 23 DE CADA MES | N61: 1234791108 | O61: MARIA JULIETH AGUILERA/MIGUEL ANGEL AGUILERA | P61: 310 8639797 | R61: BOGOTA | S61: DANIA | T61: 5000000 | U61: 3000000 | W61: =T61-U61-V61
A62: =LISTADO!B62 | B62: =LISTADO!D62 | C62: =LISTADO!L62 | D62: =LISTADO!K62 | F62: 45892 | G62: 4000000 | H62: 45558 | I62: EFECTIVO | J62: =D62-G62 | K62: 24 | L62: =J62/K62 | M62: 23 DE CADA MES | N62: 1234791108 | O62: MARIA JULIETH AGUILERA/MIGUEL ANGEL AGUILERA | P62: 310 8639797 | R62: BOGOTA | S62: DANIA | T62: 5000000 | U62: 3000000 | W62: =T62-U62-V62
A63: =LISTADO!B63 | B63: =LISTADO!D63 | C63: =LISTADO!L63 | D63: =LISTADO!K63 | F63: 45892 | G63: 4000000 | H63: 45558 | I63: EFECTIVO | J63: =D63-G63 | K63: 24 | L63: =J63/K63 | M63: 23 DE CADA MES | N63: 1234791108 | O63: MARIA JULIETH AGUILERA/MIGUEL ANGEL AGUILERA | P63: 310 8639797 | R63: BOGOTA | S63: DANIA | T63: 5000000 | U63: 3000000 | W63: =T63-U63-V63
A64: =LISTADO!B64 | B64: =LISTADO!D64 | C64: =LISTADO!L64 | D64: =LISTADO!K64 | F64: 45869 | G64: 5000000 | H64: 45900 | I64: EFECTIVO | J64: =D64-G64 | K64: 24 | L64: =J64/K64 | M64: 31 DE CADA MES | N64: 51565729 | O64: MARIA ELVIRA GONZALEZ DE HERNANDEZ | P64: 3107694546 | R64: BOGOTA | S64: JHON JAIRO RINCON | T64: 5000000 | U64: 3000000 | W64: =T64-U64-V64
A65: =LISTADO!B65 | B65: =LISTADO!D65 | C65: =LISTADO!L65 | D65: =LISTADO!K65 | F65: 45842 | G65: 4000000 | H65: 45873 | I65: EFECTIVO | J65: =D65-G65 | K65: 24 | L65: =J65/K65 | M65: 04 DE CADA MES | N65: 39629726 | O65: MARITZA VIVAS GARZON/WILBER MAURICIO MONROY | P65: 1 (980) 780-1604 | R65: FUSAGASUGA | S65: CARLOS JULIAN | T65: 5000000 | U65: 3000000 | W65: =T65-U65-V65
A66: =LISTADO!B66 | B66: =LISTADO!D66 | C66: =LISTADO!L66 | D66: =LISTADO!K66 | F66: 45896 | G66: 4000000 | H66: 45927 | I66: EFECTIVO | J66: =D66-G66 | K66: 24 | L66: =J66/K66 | M66: 27 DE CADA MES | N66: 39797652 | O66: ROSALBA VELANDIA AYALA/LUCAS PACHON ROZO | P66: 3202512298 | R66: BOGOTA | S66: SAMUEL | T66: 5000000 | U66: 3000000 | W66: =T66-U66-V66
A67: =LISTADO!B67 | B67: =LISTADO!D67 | C67: =LISTADO!L67 | D67: =LISTADO!K67 | F67: 45896 | G67: 4000000 | H67: 45927 | I67: EFECTIVO | J67: =D67-G67 | K67: 24 | L67: =J67/K67 | M67: 27 DE CADA MES | N67: 39797652 | O67: ROSALBA VELANDIA AYALA/LUCAS PACHON ROZO | P67: 3202512298 | R67: BOGOTA | S67: SAMUEL | T67: 5000000 | U67: 3000000 | W67: =T67-U67-V67
A68: 66 | B68: LC1 - 8 - 3 Y 4 | C68: PAGADO EN SU TOTALIDAD | D68: 55482000 | F68: 2026-09-17 | G68: 55482000 | H68: 2026-09-17 | I68: TRANSFERENCIA | J68: 0 | K68: 1 | L68: 0 | M68: - | N68: ESCRITURA | O68: JOHN ALBERTO BOHORQUEZ | R68: LA CEIBA | S68: JHON ALBERTO | W68: 0
A69: 67 | B69: LC1 - 8 - 4 (UNIFICADO EN LC1 - 8 - 3 Y 4) | C69: VENDIDO | D69: 27982000 | J69: 0 | L69: 0 | W69: 0 | X69: UNIFICADO EN LC1 - 8 - 3 Y 4
A70: =LISTADO!B70 | B70: =LISTADO!D70 | C70: =LISTADO!L70 | D70: =LISTADO!K70 | J70: =D70-G70 | L70: =J70/K70 | W70: =T70-U70-V70
A71: =LISTADO!B71 | B71: =LISTADO!D71 | C71: =LISTADO!L71 | D71: =LISTADO!K71 | F71: 45965 | G71: 4000000 | H71: 45995 | I71: EFECTIVO | J71: =D71-G71 | K71: 24 | L71: =J71/K71 | M71: 04 DE CADA MES | N71: 194393 | O71: JESUS MARIA CASTILLO BARACALDO | P71: 313 2450133 | R71: BOGOTA | S71: YURANY PEREZ | T71: 5000000 | U71: 3000000 | W71: =T71-U71-V71
A72: =LISTADO!B72 | B72: =LISTADO!D72 | C72: =LISTADO!L72 | D72: =LISTADO!K72 | F72: 45927 | G72: 30000000 | H72: 45927 | I72: PERMUTA | J72: =D72-G72 | L72: =J72/K72 | M72: 0 | N72: 1000467332 | O72: SAMUEL ANDRES BARRETO DONCEL | P72: 3183282991 | R72: BOGOTA | S72: DANIEL | T72: 5000000 | U72: 3000000 | W72: =T72-U72-V72
A73: =LISTADO!B73 | B73: =LISTADO!D73 | C73: =LISTADO!L73 | D73: =LISTADO!K73 | F73: 45917 | G73: 4000000 | H73: 45947 | I73: EFECTIVO | J73: =D73-G73 | K73: 24 | L73: =J73/K73 | M73: 17 DE CADA MES | N73: 1012317659 | O73: JOSE DANIEL BARRETO DONCEL | P73: 3183282991 | R73: GUAMAL | S73: DANIEL | T73: 5000000 | U73: 3000000 | W73: =T73-U73-V73
A74: =LISTADO!B74 | B74: =LISTADO!D74 | C74: =LISTADO!L74 | D74: =LISTADO!K74 | F74: 46021 | G74: 4000000 | H74: 46052 | I74: EFECTIVO | J74: =D74-G74 | K74: 24 | L74: =J74/K74 | M74: 30 DE CADA MES | N74: 1122126040 | O74: DIANA MARCELA CARRANZA OSPINA | P74: 322 3165311 | R74: PUERTO RICO - META | S74: YURANY PEREZ | T74: 5000000 | U74: 3000000 | W74: =T74-U74-V74
A75: =LISTADO!B75 | B75: =LISTADO!D75 | C75: =LISTADO!L75 | D75: =LISTADO!K75 | F75: 45886 | G75: 2500000 | H75: 45917 | I75: EFECTIVO | J75: =D75-G75 | K75: 12 | L75: =J75/K75 | M75: 17 CADA DOS MESES | N75: 79703676 | O75: LUIS ALEXANDER HERNANDEZ VERA | P75: 320 4329783 | R75: BOGOTA | S75: YURANY PEREZ | T75: 5000000 | W75: =T75-U75-V75
A76: =LISTADO!B76 | B76: =LISTADO!D76 | C76: =LISTADO!L76 | D76: =LISTADO!K76 | F76: 45821 | G76: 30000000 | H76: 45821 | I76: EFECTIVO | J76: =D76-G76 | K76: 1 | L76: =J76/K76 | M76: 0 | N76: 7060277 | O76: YESID LOPEZ GUEVARA | P76: 3212903833 | R76: BOGOTA | S76: SNEIDER | T76: 5000000 | U76: 5000000 | W76: =T76-U76-V76
A77: =LISTADO!B77 | B77: =LISTADO!D77 | C77: =LISTADO!L77 | D77: =LISTADO!K77 | F77: 45877 | G77: 4000000 | H77: 45908 | I77: EFECTIVO | J77: =D77-G77 | K77: 24 | L77: =J77/K77 | M77: 08 DE CADA MES | N77: 1120373816 | O77: ANGIE CATHERINE FORERO CALDERON | P77: 3208895598 | R77: GRANADA | S77: LAURA CAMACHO | T77: 5000000 | U77: 3000000 | W77: =T77-U77-V77
A78: =LISTADO!B78 | B78: =LISTADO!D78 | C78: =LISTADO!L78 | D78: =LISTADO!K78 | F78: 45845 | G78: 4000000 | H78: 45876 | I78: EFECTIVO | J78: =D78-G78 | K78: 24 | L78: =J78/K78 | M78: 07 DE CADA MES | N78: 1006780320 | O78: YULIETH TATIANA MOZO SANCHEZ | P78: 310 2714006 | R78: ACACIAS | S78: MARLON | T78: 5000000 | U78: 3000000 | W78: =T78-U78-V78
A79: =LISTADO!B79 | B79: =LISTADO!D79 | C79: =LISTADO!L79 | D79: =LISTADO!K79 | F79: 45811 | G79: 8000000 | H79: 45841 | I79: EFECTIVO | J79: =D79-G79 | K79: 24 | L79: =J79/K79 | M79: 03 DE CADA MES | N79: 1120373816 | O79: ANGIE CATHERINE FORERO CALDERON | P79: 3208895598 | R79: GRANADA | S79: LAURA CAMACHO | T79: 10000000 | U79: 6000000 | W79: =T79-U79-V79
A80: =LISTADO!B80 | B80: =LISTADO!D80 | C80: =LISTADO!L80 | D80: =LISTADO!K80 | F80: 46132 | G80: 4000000 | H80: 46132 | I80: TRANSFERENCIA | J80: =D80-G80 | K80: 24 | L80: =J80/K80 | M80: 20 DE CADA MES | N80: 86070732 | O80: ALBEIRO BERNAL BOCANEGRA | P80: 314 3417339 | R80: VILLAVICENCIO | S80: YURANY PEREZ | T80: 5000000 | W80: =T80-U80-V80
A81: =LISTADO!B81 | B81: =LISTADO!D81 | C81: =LISTADO!L81 | D81: =LISTADO!K81 | F81: 46029 | G81: 4000000 | H81: 46060 | I81: EFECTIVO | J81: =D81-G81 | K81: 30 | L81: =J81/K81 | M81: 07 DE CADA MES | N81: 36068421 | O81: ANDREA VIOLET CANO | P81: 313 4226619 | R81: NEIVA | S81: YURANY PEREZ | T81: 5000000 | U81: 3000000 | W81: =T81-U81-V81
A82: =LISTADO!B82 | B82: =LISTADO!D82 | C82: =LISTADO!L82 | D82: =LISTADO!K82 | F82: 46029 | G82: 4000000 | H82: 46060 | I82: EFECTIVO | J82: =D82-G82 | K82: 30 | L82: =J82/K82 | M82: 07 DE CADA MES | N82: 36068421 | O82: ANDREA VIOLET CANO | P82: 313 4226619 | R82: NEIVA | S82: YURANY PEREZ | T82: 5000000 | U82: 3000000 | W82: =T82-U82-V82
A83: =LISTADO!B83 | B83: =LISTADO!D83 | C83: =LISTADO!L83 | D83: =LISTADO!K83 | F83: 45843 | G83: 9500000 | H83: 45874 | I83: PERMUTA | J83: =D83-G83 | K83: 24 | L83: =J83/K83 | M83: 05 DE CADA MES | N83: 80014270 | O83: EDWIN GILDARDO VILLARREAL VARON | R83: IBAGUE | S83: SNEIDER | T83: 5000000 | U83: 3000000 | W83: =T83-U83-V83
A84: =LISTADO!B84 | B84: =LISTADO!D84 | C84: =LISTADO!L84 | D84: =LISTADO!K84 | F84: 45811 | G84: 4000000 | H84: 45841 | I84: EFECTIVO | J84: =D84-G84 | K84: 24 | L84: =J84/K84 | M84: 03 DE CADA MES | N84: 1022447197 | O84: JUAN DAVID FORERO YAZO | P84: 320 2337426 | R84: BOGOTA | S84: LAURA CAMACHO | T84: 5000000 | U84: 3000000 | W84: =T84-U84-V84
A85: =LISTADO!B85 | B85: =LISTADO!D85 | C85: =LISTADO!L85 | D85: =LISTADO!K85 | F85: 46090 | G85: 4000000 | H85: 46090 | I85: TRANSFERENCIA | J85: =D85-G85 | K85: 24 | L85: =J85/K85 | M85: 5 DE CADA MES | N85: 86011972 | O85: JOSÉ ALCIDES QUINTERO GAITAN | P85: 322 2458447 | R85: GRANADA | S85: YURANY PEREZ | T85: 5000000 | W85: =T85-U85-V85
A86: =LISTADO!B86 | B86: =LISTADO!D86 | C86: =LISTADO!L86 | D86: =LISTADO!K86 | J86: =D86-G86 | L86: =J86/K86 | O86: ingrid y duvan | W86: =T86-U86-V86
A87: =LISTADO!B87 | B87: =LISTADO!D87 | C87: =LISTADO!L87 | D87: =LISTADO!K87 | J87: =D87-G87 | L87: =J87/K87 | O87: ingrid y duvan | W87: =T87-U87-V87
A88: =LISTADO!B88 | B88: =LISTADO!D88 | C88: =LISTADO!L88 | D88: =LISTADO!K88 | F88: 46068 | G88: 20000000 | H88: 46096 | I88: EFECTIVO | J88: =D88-G88 | K88: 30 | L88: =J88/K88 | M88: 15 DE CADA MES | N88: 74242785 | O88: ABEL SAENZ | P88: 3008564112 | R88: MONIQUIRA | S88: INGRID | T88: 5000000 | U88: 3000000 | W88: =T88-U88-V88
A89: =LISTADO!B89 | B89: =LISTADO!D89 | C89: =LISTADO!L89 | D89: =LISTADO!K89 | F89: 46008 | G89: 4000000 | H89: 46039 | I89: EFECTIVO | J89: =D89-G89 | K89: 24 | L89: =J89/K89 | M89: 17 DE CADA MES | N89: 79280833 | O89: CESAR AUGUSTO LOPEZ BUITRAGO | P89: 312 4463921 | R89: BOGOTA | S89: YURANY PEREZ | T89: 5000000 | U89: 3000000 | W89: =T89-U89-V89
A90: =LISTADO!B90 | B90: =LISTADO!D90 | C90: =LISTADO!L90 | D90: =LISTADO!K90 | F90: 46242 | G90: 4000000 | H90: 46242 | I90: TRANSFERENCIA | J90: =D90-G90 | K90: 24 | L90: =J90/K90 | M90: 8 DE CADA MES | N90: 39679588 | O90: SANDRA MILENA MORENO | P90: 3173503301 | R90: BOGOTA | S90: YURANY PEREZ | W90: =T90-U90-V90
A91: =LISTADO!B91 | B91: =LISTADO!D91 | C91: =LISTADO!L91 | D91: =LISTADO!K91 | F91: 46043 | G91: 4000000 | H91: 46074 | I91: EFECTIVO | J91: =D91-G91 | K91: 24 | L91: =J91/K91 | M91: 21 DE CADA MES | N91: 79208053 | O91: FRANCISCO JAVIER BARON OCHOA | P91: 3176715590 | R91: SOACHA | S91: DANIEL | T91: 5000000 | U91: 3000000 | W91: =T91-U91-V91
A92: =LISTADO!B92 | B92: =LISTADO!D92 | C92: =LISTADO!L92 | D92: =LISTADO!K92 | F92: 46027 | G92: 4000000 | H92: 46058 | I92: EFECTIVO | J92: =D92-G92 | K92: 24 | L92: =J92/K92 | M92: 05 DE CADA MES | N92: 80415697 | O92: JOSE GIRALDO BARRETO FUENTES | P92: 3108460446 | R92: BOGOTA | S92: DANIEL | T92: 5000000 | U92: 3000000 | W92: =T92-U92-V92
A93: =LISTADO!B93 | B93: =LISTADO!D93 | C93: =LISTADO!L93 | D93: =LISTADO!K93 | F93: 45882 | G93: 8000000 | H93: 45913 | I93: EFECTIVO | J93: =D93-G93 | K93: 24 | L93: =J93/K93 | M93: 13 DE CADA MES | N93: 1108930492 | O93: JOSE IGNACIO GOMEZ SAENZ | P93: 320 4516578 | R93: GUAMO | S93: YULIAN CARDENAS | T93: 10000000 | U93: 6000000 | W93: =T93-U93-V93
A94: =LISTADO!B94 | B94: =LISTADO!D94 | C94: =LISTADO!L94 | D94: =LISTADO!K94 | F94: 45843 | G94: 4000000 | H94: 45874 | I94: EFECTIVO | J94: =D94-G94 | K94: 24 | L94: =J94/K94 | M94: 05 DE CADA MES | N94: 52453694 | O94: LUZ MARINA AMAZO MARTINEZ | P94: 310 7973161 | R94: BOGOTA | S94: MAYERLY | T94: 5000000 | U94: 3000000 | W94: =T94-U94-V94
A95: =LISTADO!B95 | B95: =LISTADO!D95 | C95: =LISTADO!L95 | D95: =LISTADO!K95 | F95: 45833 | G95: 4000000 | H95: 45863 | I95: EFECTIVO | J95: =D95-G95 | K95: 24 | L95: =J95/K95 | M95: 25 DE CADA MES | N95: 1015413041 | O95: DIANA CAROLINA RUSSI MANCERA | P95: 3167874723 | R95: BOGOTA | S95: INGRID | T95: 5000000 | U95: 3000000 | W95: =T95-U95-V95
A96: =LISTADO!B96 | B96: =LISTADO!D96 | C96: =LISTADO!L96 | D96: =LISTADO!K96 | J96: =D96-G96 | L96: =J96/K96 | W96: =T96-U96-V96
A97: =LISTADO!B97 | B97: =LISTADO!D97 | C97: =LISTADO!L97 | D97: =LISTADO!K97 | F97: 46045 | G97: 4000000 | H97: 46076 | I97: EFECTIVO | J97: =D97-G97 | K97: 24 | L97: =J97/K97 | M97: 23 DE CADA MES | N97: 1000620103 | O97: OSCAR JAVIER VARGAS DIAZ | P97: 3133043714 | R97: BOGOTA | S97: INGRID | T97: 5000000 | U97: 3000000 | W97: =T97-U97-V97
A98: =LISTADO!B98 | B98: =LISTADO!D98 | C98: =LISTADO!L98 | D98: =LISTADO!K98 | F98: 46057 | G98: 4000000 | H98: 46085 | I98: EFECTIVO | J98: =D98-G98 | K98: 24 | L98: =J98/K98 | M98: 04 DE CADA MES | N98: 52273485 | O98: LAURA ELENA BELLO CARDENAS | P98: 3163755156 | R98: BOGOTA | S98: DANIEL | T98: 5000000 | U98: 3000000 | W98: =T98-U98-V98
A99: =LISTADO!B99 | B99: =LISTADO!D99 | C99: =LISTADO!L99 | D99: =LISTADO!K99 | F99: 46057 | G99: 4000000 | H99: 46085 | I99: EFECTIVO | J99: =D99-G99 | K99: 24 | L99: =J99/K99 | M99: 04 DE CADA MES | N99: 1122676241 | O99: ARGEMIRO BUSTAMANTE | P99: 317 5123910 | R99: BOGOTA | S99: DANIEL | T99: 5000000 | U99: 3000000 | W99: =T99-U99-V99
A100: =LISTADO!B100 | B100: =LISTADO!D100 | C100: =LISTADO!L100 | D100: =LISTADO!K100 | F100: 46057 | G100: 4000000 | H100: 46085 | I100: EFECTIVO | J100: =D100-G100 | K100: 24 | L100: =J100/K100 | M100: 04 DE CADA MES | N100: 52273485 | O100: LAURA ELENA BELLO CARDENAS | P100: 3163755156 | R100: BOGOTA | S100: DANIEL | T100: 5000000 | U100: 3000000 | W100: =T100-U100-V100
A101: =LISTADO!B101 | B101: =LISTADO!D101 | C101: =LISTADO!L101 | D101: =LISTADO!K101 | F101: 45842 | G101: 4000000 | H101: 45873 | I101: EFECTIVO | J101: =D101-G101 | K101: 24 | L101: =J101/K101 | M101: 04 DE CADA MES | N101: 1031123614 | O101: CAROLINA MARTINEZ RIVEROS | P101: 311 2457461 | R101: BOGOTA | S101: KATHERINE TACHA | T101: 5000000 | U101: 3000000 | W101: =T101-U101-V101
...

Sheet PROYECCIÓN
K2: CUOTA 1 | L2: CUOTA 1 | M2: CUOTA 1 | N2: CUOTA 1 | O2: CUOTA 1 | P2: CUOTA 1 | Q2: CUOTA 2 | R2: CUOTA 2 | S2: CUOTA 2 | T2: CUOTA 2 | U2: CUOTA 2 | V2: CUOTA 2 | W2: CUOTA 3 | X2: CUOTA 3 | Y2: CUOTA 3 | Z2: CUOTA 3 | AA2: CUOTA 3 | AB2: CUOTA 3 | AC2: CUOTA 4 | AD2: CUOTA 4 | AE2: CUOTA 4 | AF2: CUOTA 4 | AG2: CUOTA 4 | AH2: CUOTA 4 | AI2: CUOTA 5 | AJ2: CUOTA 5 | AK2: CUOTA 5 | AL2: CUOTA 5 | AM2: CUOTA 5 | AN2: CUOTA 5 | AO2: CUOTA 6 | AP2: CUOTA 6 | AQ2: CUOTA 6 | AR2: CUOTA 6 | AS2: CUOTA 6 | AT2: CUOTA 6 | AU2: CUOTA 7 | AV2: CUOTA 7 | AW2: CUOTA 7 | AX2: CUOTA 7 | AY2: CUOTA 7 | AZ2: CUOTA 7 | BA2: CUOTA 8 | BB2: CUOTA 8 | BC2: CUOTA 8 | BD2: CUOTA 8 | BE2: CUOTA 8 | BF2: CUOTA 8 | BG2: CUOTA 9 | BH2: CUOTA 9 | BI2: CUOTA 9 | BJ2: CUOTA 9 | BK2: CUOTA 9 | BL2: CUOTA 9 | BM2: CUOTA 10 | BN2: CUOTA 10 | BO2: CUOTA 10 | BP2: CUOTA 10 | BQ2: CUOTA 10 | BR2: CUOTA 10 | BS2: CUOTA 11 | BT2: CUOTA 11 | BU2: CUOTA 11 | BV2: CUOTA 11 | BW2: CUOTA 11 | BX2: CUOTA 11 | BY2: CUOTA 12 | BZ2: CUOTA 12 | CA2: CUOTA 12 | CB2: CUOTA 12 | CC2: CUOTA 12 | CD2: CUOTA 12 | CE2: CUOTA 13 | CF2: CUOTA 13 | CG2: CUOTA 13 | CH2: CUOTA 13 | CI2: CUOTA 13 | CJ2: CUOTA 13 | CK2: CUOTA 14 | CL2: CUOTA 14 | CM2: CUOTA 14 | CN2: CUOTA 14 | CO2: CUOTA 14 | CP2: CUOTA 14 | CQ2: CUOTA 15 | CR2: CUOTA 15 | CS2: CUOTA 15 | CT2: CUOTA 15 | CU2: CUOTA 15 | CV2: CUOTA 15 | CW2: CUOTA 16 | CX2: CUOTA 16 | CY2: CUOTA 16 | CZ2: CUOTA 16 | DA2: CUOTA 16 | DB2: CUOTA 16 | DC2: CUOTA 17 | DD2: CUOTA 17 | DE2: CUOTA 17 | DF2: CUOTA 17 | DG2: CUOTA 17 | DH2: CUOTA 17 | DI2: CUOTA 18 | DJ2: CUOTA 18 | DK2: CUOTA 18 | DL2: CUOTA 18 | DM2: CUOTA 18 | DN2: CUOTA 18 | DO2: CUOTA 19 | DP2: CUOTA 19 | DQ2: CUOTA 19 | DR2: CUOTA 19 | DS2: CUOTA 19 | DT2: CUOTA 19 | DU2: CUOTA 20 | DV2: CUOTA 20 | DW2: CUOTA 20 | DX2: CUOTA 20 | DY2: CUOTA 20 | DZ2: CUOTA 20 | EA2: CUOTA 21 | EB2: CUOTA 21 | EC2: CUOTA 21 | ED2: CUOTA 21 | EE2: CUOTA 21 | EF2: CUOTA 21 | EG2: CUOTA 22 | EH2: CUOTA 22 | EI2: CUOTA 22 | EJ2: CUOTA 22 | EK2: CUOTA 22 | EL2: CUOTA 22 | EM2: CUOTA 23 | EN2: CUOTA 23 | EO2: CUOTA 23 | EP2: CUOTA 23 | EQ2: CUOTA 23 | ER2: CUOTA 23 | ES2: CUOTA 24 | ET2: CUOTA 24 | EU2: CUOTA 24 | EV2: CUOTA 24 | EW2: CUOTA 24 | EX2: CUOTA 24 | EY2: CUOTA 25 | EZ2: CUOTA 25 | FA2: CUOTA 25 | FB2: CUOTA 25 | FC2: CUOTA 25 | FD2: CUOTA 25 | FE2: CUOTA 26 | FF2: CUOTA 26 | FG2: CUOTA 26 | FH2: CUOTA 26 | FI2: CUOTA 26 | FJ2: CUOTA 26 | FK2: CUOTA 27 | FL2: CUOTA 27 | FM2: CUOTA 27 | FN2: CUOTA 27 | FO2: CUOTA 27 | FP2: CUOTA 27 | FQ2: CUOTA 28 | FR2: CUOTA 28 | FS2: CUOTA 28 | FT2: CUOTA 28 | FU2: CUOTA 28 | FV2: CUOTA 28 | FW2: CUOTA 29 | FX2: CUOTA 29 | FY2: CUOTA 29 | FZ2: CUOTA 29 | GA2: CUOTA 29 | GB2: CUOTA 29 | GC2: CUOTA 30 | GD2: CUOTA 30 | GE2: CUOTA 30 | GF2: CUOTA 30 | GG2: CUOTA 30 | GH2: CUOTA 30 | GI2: CUOTA 31 | GJ2: CUOTA 31 | GK2: CUOTA 31 | GL2: CUOTA 31 | GM2: CUOTA 31 | GN2: CUOTA 31 | GO2: CUOTA 32 | GP2: CUOTA 32 | GQ2: CUOTA 32 | GR2: CUOTA 32 | GS2: CUOTA 32 | GT2: CUOTA 32 | GU2: CUOTA 33 | GV2: CUOTA 33 | GW2: CUOTA 33 | GX2: CUOTA 33 | GY2: CUOTA 33 | GZ2: CUOTA 33 | HA2: CUOTA 34 | HB2: CUOTA 34 | HC2: CUOTA 34 | HD2: CUOTA 34 | HE2: CUOTA 34 | HF2: CUOTA 34 | HG2: CUOTA 35 | HH2: CUOTA 35 | HI2: CUOTA 35 | HJ2: CUOTA 35 | HK2: CUOTA 35 | HL2: CUOTA 35 | HM2: CUOTA 36 | HN2: CUOTA 36 | HO2: CUOTA 36 | HP2: CUOTA 36 | HQ2: CUOTA 36 | HR2: CUOTA 36
B3: ITEM | C3: ID LOTE | D3: ESTADO | E3: PRECIO DE VENTA | F3: SALDO FINANCIADO | G3: FECHA DE VENTA | H3: PLAZO/CUOTAS | I3: FECHAS DE VENCIMIENTO | J3: VALOR CUOTA | K3: FECHA VENCIMIENTO | L3: DÍAS DE VENCIMIENTO | M3: FECHA DE PAGO | N3: VALOR | O3: ESTADO CUOTA | P3: MEDIO DE PAGO | Q3: FECHA VENCIMIENTO | R3: DÍAS DE VENCIMIENTO | S3: FECHA DE PAGO | T3: VALOR | U3: ESTADO CUOTA | V3: MEDIO DE PAGO | W3: FECHA VENCIMIENTO | X3: DÍAS DE VENCIMIENTO | Y3: FECHA DE PAGO | Z3: VALOR | AA3: ESTADO CUOTA | AB3: MEDIO DE PAGO | AC3: FECHA VENCIMIENTO | AD3: DÍAS DE VENCIMIENTO | AE3: FECHA DE PAGO | AF3: VALOR | AG3: ESTADO CUOTA | AH3: MEDIO DE PAGO | AI3: FECHA VENCIMIENTO | AJ3: DÍAS DE VENCIMIENTO | AK3: FECHA DE PAGO | AL3: VALOR | AM3: ESTADO CUOTA | AN3: MEDIO DE PAGO | AO3: FECHA VENCIMIENTO | AP3: DÍAS DE VENCIMIENTO | AQ3: FECHA DE PAGO | AR3: VALOR | AS3: ESTADO CUOTA | AT3: MEDIO DE PAGO | AU3: FECHA VENCIMIENTO | AV3: DÍAS DE VENCIMIENTO | AW3: FECHA DE PAGO | AX3: VALOR | AY3: ESTADO CUOTA | AZ3: MEDIO DE PAGO | BA3: FECHA VENCIMIENTO | BB3: DÍAS DE VENCIMIENTO | BC3: FECHA DE PAGO | BD3: VALOR | BE3: ESTADO CUOTA | BF3: MEDIO DE PAGO | BG3: FECHA VENCIMIENTO | BH3: DÍAS DE VENCIMIENTO | BI3: FECHA DE PAGO | BJ3: VALOR | BK3: ESTADO CUOTA | BL3: MEDIO DE PAGO | BM3: FECHA VENCIMIENTO | BN3: DÍAS DE VENCIMIENTO | BO3: FECHA DE PAGO | BP3: VALOR | BQ3: ESTADO CUOTA | BR3: MEDIO DE PAGO | BS3: FECHA VENCIMIENTO | BT3: DÍAS DE VENCIMIENTO | BU3: FECHA DE PAGO | BV3: VALOR | BW3: ESTADO CUOTA | BX3: MEDIO DE PAGO | BY3: FECHA VENCIMIENTO | BZ3: DÍAS DE VENCIMIENTO | CA3: FECHA DE PAGO | CB3: VALOR | CC3: ESTADO CUOTA | CD3: MEDIO DE PAGO | CE3: FECHA VENCIMIENTO | CF3: DÍAS DE VENCIMIENTO | CG3: FECHA DE PAGO | CH3: VALOR | CI3: ESTADO CUOTA | CJ3: MEDIO DE PAGO | CK3: FECHA VENCIMIENTO | CL3: DÍAS DE VENCIMIENTO | CM3: FECHA DE PAGO | CN3: VALOR | CO3: ESTADO CUOTA | CP3: MEDIO DE PAGO | CQ3: FECHA VENCIMIENTO | CR3: DÍAS DE VENCIMIENTO | CS3: FECHA DE PAGO | CT3: VALOR | CU3: ESTADO CUOTA | CV3: MEDIO DE PAGO | CW3: FECHA VENCIMIENTO | CX3: DÍAS DE VENCIMIENTO | CY3: FECHA DE PAGO | CZ3: VALOR | DA3: ESTADO CUOTA | DB3: MEDIO DE PAGO | DC3: FECHA VENCIMIENTO | DD3: DÍAS DE VENCIMIENTO | DE3: FECHA DE PAGO | DF3: VALOR | DG3: ESTADO CUOTA | DH3: MEDIO DE PAGO | DI3: FECHA VENCIMIENTO | DJ3: DÍAS DE VENCIMIENTO | DK3: FECHA DE PAGO | DL3: VALOR | DM3: ESTADO CUOTA | DN3: MEDIO DE PAGO | DO3: FECHA VENCIMIENTO | DP3: DÍAS DE VENCIMIENTO | DQ3: FECHA DE PAGO | DR3: VALOR | DS3: ESTADO CUOTA | DT3: MEDIO DE PAGO | DU3: FECHA VENCIMIENTO | DV3: DÍAS DE VENCIMIENTO | DW3: FECHA DE PAGO | DX3: VALOR | DY3: ESTADO CUOTA | DZ3: MEDIO DE PAGO | EA3: FECHA VENCIMIENTO | EB3: DÍAS DE VENCIMIENTO | EC3: FECHA DE PAGO | ED3: VALOR | EE3: ESTADO CUOTA | EF3: MEDIO DE PAGO | EG3: FECHA VENCIMIENTO | EH3: DÍAS DE VENCIMIENTO | EI3: FECHA DE PAGO | EJ3: VALOR | EK3: ESTADO CUOTA | EL3: MEDIO DE PAGO | EM3: FECHA VENCIMIENTO | EN3: DÍAS DE VENCIMIENTO | EO3: FECHA DE PAGO | EP3: VALOR | EQ3: ESTADO CUOTA | ER3: MEDIO DE PAGO | ES3: FECHA VENCIMIENTO | ET3: DÍAS DE VENCIMIENTO | EU3: FECHA DE PAGO | EV3: VALOR | EW3: ESTADO CUOTA | EX3: MEDIO DE PAGO | EY3: FECHA VENCIMIENTO | EZ3: DÍAS DE VENCIMIENTO | FA3: FECHA DE PAGO | FB3: VALOR | FC3: ESTADO CUOTA | FD3: MEDIO DE PAGO | FE3: FECHA VENCIMIENTO | FF3: DÍAS DE VENCIMIENTO | FG3: FECHA DE PAGO | FH3: VALOR | FI3: ESTADO CUOTA | FJ3: MEDIO DE PAGO | FK3: FECHA VENCIMIENTO | FL3: DÍAS DE VENCIMIENTO | FM3: FECHA DE PAGO | FN3: VALOR | FO3: ESTADO CUOTA | FP3: MEDIO DE PAGO | FQ3: FECHA VENCIMIENTO | FR3: DÍAS DE VENCIMIENTO | FS3: FECHA DE PAGO | FT3: VALOR | FU3: ESTADO CUOTA | FV3: MEDIO DE PAGO | FW3: FECHA VENCIMIENTO | FX3: DÍAS DE VENCIMIENTO | FY3: FECHA DE PAGO | FZ3: VALOR | GA3: ESTADO CUOTA | GB3: MEDIO DE PAGO | GC3: FECHA VENCIMIENTO | GD3: DÍAS DE VENCIMIENTO | GE3: FECHA DE PAGO | GF3: VALOR | GG3: ESTADO CUOTA | GH3: MEDIO DE PAGO | GI3: FECHA VENCIMIENTO | GJ3: DÍAS DE VENCIMIENTO | GK3: FECHA DE PAGO | GL3: VALOR | GM3: ESTADO CUOTA | GN3: MEDIO DE PAGO | GO3: FECHA VENCIMIENTO | GP3: DÍAS DE VENCIMIENTO | GQ3: FECHA DE PAGO | GR3: VALOR | GS3: ESTADO CUOTA | GT3: MEDIO DE PAGO | GU3: FECHA VENCIMIENTO | GV3: DÍAS DE VENCIMIENTO | GW3: FECHA DE PAGO | GX3: VALOR | GY3: ESTADO CUOTA | GZ3: MEDIO DE PAGO | HA3: FECHA VENCIMIENTO | HB3: DÍAS DE VENCIMIENTO | HC3: FECHA DE PAGO | HD3: VALOR | HE3: ESTADO CUOTA | HF3: MEDIO DE PAGO | HG3: FECHA VENCIMIENTO | HH3: DÍAS DE VENCIMIENTO | HI3: FECHA DE PAGO | HJ3: VALOR | HK3: ESTADO CUOTA | HL3: MEDIO DE PAGO | HM3: FECHA VENCIMIENTO | HN3: DÍAS DE VENCIMIENTO | HO3: FECHA DE PAGO | HP3: VALOR | HQ3: ESTADO CUOTA | HR3: MEDIO DE PAGO | HS3: TOTAL PAGADO | HU3: VALOR CUOTA (LIMPIO) | HW3: RECAUDO MES (VALOR) | HX3: RECAUDO MES (N° CUOTAS)
B4: =VENTAS!A3 | C4: =VENTAS!B3 | D4: =VENTAS!C3 | E4: =VENTAS!D3 | F4: =VENTAS!J3 | G4: =VENTAS!F3 | H4: =VENTAS!K3 | I4: =VENTAS!M3 | J4: =VENTAS!L3 | K4: =IF(N($H4)<1,"",$G4+31) | L4: =IF(K4="","",TODAY()-K4) | O4: =IF(K4="","SIN ESTADO",IF(M4<>"","PAGA",IF(L4>0,"VENCIDA",IF(L4>=-5,"POR VENCER","AL DÍA")))) | Q4: =IF(N($H4)<2,"",IF(K4="","",K4+31)) | R4: =IF(Q4="","",TODAY()-Q4) | U4: =IF(Q4="","SIN ESTADO",IF(S4<>"","PAGA",IF(R4>0,"VENCIDA",IF(R4>=-5,"POR VENCER","AL DÍA")))) | W4: =IF(N($H4)<3,"",IF(Q4="","",Q4+31)) | X4: =IF(W4="","",TODAY()-W4) | AA4: =IF(W4="","SIN ESTADO",IF(Y4<>"","PAGA",IF(X4>0,"VENCIDA",IF(X4>=-5,"POR VENCER","AL DÍA")))) | AC4: =IF(N($H4)<4,"",IF(W4="","",W4+31)) | AD4: =IF(AC4="","",TODAY()-AC4) | AG4: =IF(AC4="","SIN ESTADO",IF(AE4<>"","PAGA",IF(AD4>0,"VENCIDA",IF(AD4>=-5,"POR VENCER","AL DÍA")))) | AI4: =IF(N($H4)<5,"",IF(AC4="","",AC4+31)) | AJ4: =IF(AI4="","",TODAY()-AI4) | AM4: =IF(AI4="","SIN ESTADO",IF(AK4<>"","PAGA",IF(AJ4>0,"VENCIDA",IF(AJ4>=-5,"POR VENCER","AL DÍA")))) | AO4: =IF(N($H4)<6,"",IF(AI4="","",AI4+31)) | AP4: =IF(AO4="","",TODAY()-AO4) | AS4: =IF(AO4="","SIN ESTADO",IF(AQ4<>"","PAGA",IF(AP4>0,"VENCIDA",IF(AP4>=-5,"POR VENCER","AL DÍA")))) | AU4: =IF(N($H4)<7,"",IF(AO4="","",AO4+31)) | AV4: =IF(AU4="","",TODAY()-AU4) | AY4: =IF(AU4="","SIN ESTADO",IF(AW4<>"","PAGA",IF(AV4>0,"VENCIDA",IF(AV4>=-5,"POR VENCER","AL DÍA")))) | BA4: =IF(N($H4)<8,"",IF(AU4="","",AU4+31)) | BB4: =IF(BA4="","",TODAY()-BA4) | BE4: =IF(BA4="","SIN ESTADO",IF(BC4<>"","PAGA",IF(BB4>0,"VENCIDA",IF(BB4>=-5,"POR VENCER","AL DÍA")))) | BG4: =IF(N($H4)<9,"",IF(BA4="","",BA4+31)) | BH4: =IF(BG4="","",TODAY()-BG4) | BK4: =IF(BG4="","SIN ESTADO",IF(BI4<>"","PAGA",IF(BH4>0,"VENCIDA",IF(BH4>=-5,"POR VENCER","AL DÍA")))) | BM4: =IF(N($H4)<10,"",IF(BG4="","",BG4+31)) | BN4: =IF(BM4="","",TODAY()-BM4) | BQ4: =IF(BM4="","SIN ESTADO",IF(BO4<>"","PAGA",IF(BN4>0,"VENCIDA",IF(BN4>=-5,"POR VENCER","AL DÍA")))) | BS4: =IF(N($H4)<11,"",IF(BM4="","",BM4+31)) | BT4: =IF(BS4="","",TODAY()-BS4) | BW4: =IF(BS4="","SIN ESTADO",IF(BU4<>"","PAGA",IF(BT4>0,"VENCIDA",IF(BT4>=-5,"POR VENCER","AL DÍA")))) | BY4: =IF(N($H4)<12,"",IF(BS4="","",BS4+31)) | BZ4: =IF(BY4="","",TODAY()-BY4) | CC4: =IF(BY4="","SIN ESTADO",IF(CA4<>"","PAGA",IF(BZ4>0,"VENCIDA",IF(BZ4>=-5,"POR VENCER","AL DÍA")))) | CE4: =IF(N($H4)<13,"",IF(BY4="","",BY4+31)) | CF4: =IF(CE4="","",TODAY()-CE4) | CI4: =IF(CE4="","SIN ESTADO",IF(CG4<>"","PAGA",IF(CF4>0,"VENCIDA",IF(CF4>=-5,"POR VENCER","AL DÍA")))) | CK4: =IF(N($H4)<14,"",IF(CE4="","",CE4+31)) | CL4: =IF(CK4="","",TODAY()-CK4) | CO4: =IF(CK4="","SIN ESTADO",IF(CM4<>"","PAGA",IF(CL4>0,"VENCIDA",IF(CL4>=-5,"POR VENCER","AL DÍA")))) | CQ4: =IF(N($H4)<15,"",IF(CK4="","",CK4+31)) | CR4: =IF(CQ4="","",TODAY()-CQ4) | CU4: =IF(CQ4="","SIN ESTADO",IF(CS4<>"","PAGA",IF(CR4>0,"VENCIDA",IF(CR4>=-5,"POR VENCER","AL DÍA")))) | CW4: =IF(N($H4)<16,"",IF(CQ4="","",CQ4+31)) | CX4: =IF(CW4="","",TODAY()-CW4) | DA4: =IF(CW4="","SIN ESTADO",IF(CY4<>"","PAGA",IF(CX4>0,"VENCIDA",IF(CX4>=-5,"POR VENCER","AL DÍA")))) | DC4: =IF(N($H4)<17,"",IF(CW4="","",CW4+31)) | DD4: =IF(DC4="","",TODAY()-DC4) | DG4: =IF(DC4="","SIN ESTADO",IF(DE4<>"","PAGA",IF(DD4>0,"VENCIDA",IF(DD4>=-5,"POR VENCER","AL DÍA")))) | DI4: =IF(N($H4)<18,"",IF(DC4="","",DC4+31)) | DJ4: =IF(DI4="","",TODAY()-DI4) | DM4: =IF(DI4="","SIN ESTADO",IF(DK4<>"","PAGA",IF(DJ4>0,"VENCIDA",IF(DJ4>=-5,"POR VENCER","AL DÍA")))) | DO4: =IF(N($H4)<19,"",IF(DI4="","",DI4+31)) | DP4: =IF(DO4="","",TODAY()-DO4) | DS4: =IF(DO4="","SIN ESTADO",IF(DQ4<>"","PAGA",IF(DP4>0,"VENCIDA",IF(DP4>=-5,"POR VENCER","AL DÍA")))) | DU4: =IF(N($H4)<20,"",IF(DO4="","",DO4+31)) | DV4: =IF(DU4="","",TODAY()-DU4) | DY4: =IF(DU4="","SIN ESTADO",IF(DW4<>"","PAGA",IF(DV4>0,"VENCIDA",IF(DV4>=-5,"POR VENCER","AL DÍA")))) | EA4: =IF(N($H4)<21,"",IF(DU4="","",DU4+31)) | EB4: =IF(EA4="","",TODAY()-EA4) | EE4: =IF(EA4="","SIN ESTADO",IF(EC4<>"","PAGA",IF(EB4>0,"VENCIDA",IF(EB4>=-5,"POR VENCER","AL DÍA")))) | EG4: =IF(N($H4)<22,"",IF(EA4="","",EA4+31)) | EH4: =IF(EG4="","",TODAY()-EG4) | EK4: =IF(EG4="","SIN ESTADO",IF(EI4<>"","PAGA",IF(EH4>0,"VENCIDA",IF(EH4>=-5,"POR VENCER","AL DÍA")))) | EM4: =IF(N($H4)<23,"",IF(EG4="","",EG4+31)) | EN4: =IF(EM4="","",TODAY()-EM4) | EQ4: =IF(EM4="","SIN ESTADO",IF(EO4<>"","PAGA",IF(EN4>0,"VENCIDA",IF(EN4>=-5,"POR VENCER","AL DÍA")))) | ES4: =IF(N($H4)<24,"",IF(EM4="","",EM4+31)) | ET4: =IF(ES4="","",TODAY()-ES4) | EW4: =IF(ES4="","SIN ESTADO",IF(EU4<>"","PAGA",IF(ET4>0,"VENCIDA",IF(ET4>=-5,"POR VENCER","AL DÍA")))) | EY4: =IF(N($H4)<25,"",IF(ES4="","",ES4+31)) | EZ4: =IF(EY4="","",TODAY()-EY4) | FC4: =IF(EY4="","SIN ESTADO",IF(FA4<>"","PAGA",IF(EZ4>0,"VENCIDA",IF(EZ4>=-5,"POR VENCER","AL DÍA")))) | FE4: =IF(N($H4)<26,"",IF(EY4="","",EY4+31)) | FF4: =IF(FE4="","",TODAY()-FE4) | FI4: =IF(FE4="","SIN ESTADO",IF(FG4<>"","PAGA",IF(FF4>0,"VENCIDA",IF(FF4>=-5,"POR VENCER","AL DÍA")))) | FK4: =IF(N($H4)<27,"",IF(FE4="","",FE4+31)) | FL4: =IF(FK4="","",TODAY()-FK4) | FO4: =IF(FK4="","SIN ESTADO",IF(FM4<>"","PAGA",IF(FL4>0,"VENCIDA",IF(FL4>=-5,"POR VENCER","AL DÍA")))) | FQ4: =IF(N($H4)<28,"",IF(FK4="","",FK4+31)) | FR4: =IF(FQ4="","",TODAY()-FQ4) | FU4: =IF(FQ4="","SIN ESTADO",IF(FS4<>"","PAGA",IF(FR4>0,"VENCIDA",IF(FR4>=-5,"POR VENCER","AL DÍA")))) | FW4: =IF(N($H4)<29,"",IF(FQ4="","",FQ4+31)) | FX4: =IF(FW4="","",TODAY()-FW4) | GA4: =IF(FW4="","SIN ESTADO",IF(FY4<>"","PAGA",IF(FX4>0,"VENCIDA",IF(FX4>=-5,"POR VENCER","AL DÍA")))) | GC4: =IF(N($H4)<30,"",IF(FW4="","",FW4+31)) | GD4: =IF(GC4="","",TODAY()-GC4) | GG4: =IF(GC4="","SIN ESTADO",IF(GE4<>"","PAGA",IF(GD4>0,"VENCIDA",IF(GD4>=-5,"POR VENCER","AL DÍA")))) | GI4: =IF(N($H4)<31,"",IF(GC4="","",GC4+31)) | GJ4: =IF(GI4="","",TODAY()-GI4) | GM4: =IF(GI4="","SIN ESTADO",IF(GK4<>"","PAGA",IF(GJ4>0,"VENCIDA",IF(GJ4>=-5,"POR VENCER","AL DÍA")))) | GO4: =IF(N($H4)<32,"",IF(GI4="","",GI4+31)) | GP4: =IF(GO4="","",TODAY()-GO4) | GS4: =IF(GO4="","SIN ESTADO",IF(GQ4<>"","PAGA",IF(GP4>0,"VENCIDA",IF(GP4>=-5,"POR VENCER","AL DÍA")))) | GU4: =IF(N($H4)<33,"",IF(GO4="","",GO4+31)) | GV4: =IF(GU4="","",TODAY()-GU4) | GY4: =IF(GU4="","SIN ESTADO",IF(GW4<>"","PAGA",IF(GV4>0,"VENCIDA",IF(GV4>=-5,"POR VENCER","AL DÍA")))) | HA4: =IF(N($H4)<34,"",IF(GU4="","",GU4+31)) | HB4: =IF(HA4="","",TODAY()-HA4) | HE4: =IF(HA4="","SIN ESTADO",IF(HC4<>"","PAGA",IF(HB4>0,"VENCIDA",IF(HB4>=-5,"POR VENCER","AL DÍA")))) | HG4: =IF(N($H4)<35,"",IF(HA4="","",HA4+31)) | HH4: =IF(HG4="","",TODAY()-HG4) | HK4: =IF(HG4="","SIN ESTADO",IF(HI4<>"","PAGA",IF(HH4>0,"VENCIDA",IF(HH4>=-5,"POR VENCER","AL DÍA")))) | HM4: =IF(N($H4)<36,"",IF(HG4="","",HG4+31)) | HN4: =IF(HM4="","",TODAY()-HM4) | HQ4: =IF(HM4="","SIN ESTADO",IF(HO4<>"","PAGA",IF(HN4>0,"VENCIDA",IF(HN4>=-5,"POR VENCER","AL DÍA")))) | HS4: =N4+T4+Z4+AF4+AL4+AR4+AX4+BD4+BJ4+BP4+BV4+CB4+CH4+CN4+CT4+CZ4+DF4+DL4+DR4+DX4+ED4+EJ4+EP4+EV4+FB4+FH4+FN4+FT4+FZ4+GF4+GL4+GR4+GX4+HD4+HJ4+HP4 | HU4: =IFERROR(N($J4),0) | HW4: =SUMPRODUCT((MOD(COLUMN($M4:$HR4)-COLUMN($M4),6)=0)*ISNUMBER($M4:$HR4)*($M4:$HR4>=RESUMEN!$C$26)*($M4:$HR4<=RESUMEN!$C$27)*IFERROR(N($N4:$HS4),0)) | HX4: =SUMPRODUCT((MOD(COLUMN($M4:$HR4)-COLUMN($M4),6)=0)*ISNUMBER($M4:$HR4)*($M4:$HR4>=RESUMEN!$C$26)*($M4:$HR4<=RESUMEN!$C$27))
B5: =VENTAS!A4 | C5: =VENTAS!B4 | D5: =VENTAS!C4 | E5: =VENTAS!D4 | F5: =VENTAS!J4 | G5: =VENTAS!F4 | H5: =VENTAS!K4 | I5: =VENTAS!M4 | J5: =VENTAS!L4 | K5: =IF(N($H5)<1,"",$G5+31) | L5: =IF(K5="","",TODAY()-K5) | M5: 45879 | N5: 1958000 | O5: =IF(K5="","SIN ESTADO",IF(M5<>"","PAGA",IF(L5>0,"VENCIDA",IF(L5>=-5,"POR VENCER","AL DÍA")))) | P5: TRANSFERENCIA | Q5: =IF(N($H5)<2,"",IF(K5="","",K5+31)) | R5: =IF(Q5="","",TODAY()-Q5) | S5: 45911 | T5: 1958000 | U5: =IF(Q5="","SIN ESTADO",IF(S5<>"","PAGA",IF(R5>0,"VENCIDA",IF(R5>=-5,"POR VENCER","AL DÍA")))) | V5: TRANSFERENCIA | W5: =IF(N($H5)<3,"",IF(Q5="","",Q5+31)) | X5: =IF(W5="","",TODAY()-W5) | Y5: 45906 | Z5: 1958000 | AA5: =IF(W5="","SIN ESTADO",IF(Y5<>"","PAGA",IF(X5>0,"VENCIDA",IF(X5>=-5,"POR VENCER","AL DÍA")))) | AB5: TRANSFERENCIA | AC5: =IF(N($H5)<4,"",IF(W5="","",W5+31)) | AD5: =IF(AC5="","",TODAY()-AC5) | AE5: 45955 | AF5: 1958000 | AG5: =IF(AC5="","SIN ESTADO",IF(AE5<>"","PAGA",IF(AD5>0,"VENCIDA",IF(AD5>=-5,"POR VENCER","AL DÍA")))) | AH5: TRANSFERENCIA | AI5: =IF(N($H5)<5,"",IF(AC5="","",AC5+31)) | AJ5: =IF(AI5="","",TODAY()-AI5) | AK5: 45991 | AL5: 1958000 | AM5: =IF(AI5="","SIN ESTADO",IF(AK5<>"","PAGA",IF(AJ5>0,"VENCIDA",IF(AJ5>=-5,"POR VENCER","AL DÍA")))) | AN5: TRANSFERENCIA | AO5: =IF(N($H5)<6,"",IF(AI5="","",AI5+31)) | AP5: =IF(AO5="","",TODAY()-AO5) | AQ5: 46386 | AR5: 1958000 | AS5: =IF(AO5="","SIN ESTADO",IF(AQ5<>"","PAGA",IF(AP5>0,"VENCIDA",IF(AP5>=-5,"POR VENCER","AL DÍA")))) | AT5: TRANSFERENCIA | AU5: =IF(N($H5)<7,"",IF(AO5="","",AO5+31)) | AV5: =IF(AU5="","",TODAY()-AU5) | AW5: 46058 | AX5: 1958000 | AY5: =IF(AU5="","SIN ESTADO",IF(AW5<>"","PAGA",IF(AV5>0,"VENCIDA",IF(AV5>=-5,"POR VENCER","AL DÍA")))) | AZ5: TRANSFERENCIA | BA5: =IF(N($H5)<8,"",IF(AU5="","",AU5+31)) | BB5: =IF(BA5="","",TODAY()-BA5) | BC5: 46094 | BD5: 3000000 | BE5: =IF(BA5="","SIN ESTADO",IF(BC5<>"","PAGA",IF(BB5>0,"VENCIDA",IF(BB5>=-5,"POR VENCER","AL DÍA")))) | BF5: TRANSFERENCIA | BG5: =IF(N($H5)<9,"",IF(BA5="","",BA5+31)) | BH5: =IF(BG5="","",TODAY()-BG5) | BI5: 46096 | BJ5: 3000000 | BK5: =IF(BG5="","SIN ESTADO",IF(BI5<>"","PAGA",IF(BH5>0,"VENCIDA",IF(BH5>=-5,"POR VENCER","AL DÍA")))) | BL5: TRANSFERENCIA | BM5: =IF(N($H5)<10,"",IF(BG5="","",BG5+31)) | BN5: =IF(BM5="","",TODAY()-BM5) | BO5: 46131 | BP5: 5000000 | BQ5: =IF(BM5="","SIN ESTADO",IF(BO5<>"","PAGA",IF(BN5>0,"VENCIDA",IF(BN5>=-5,"POR VENCER","AL DÍA")))) | BR5: TRANSFERENCIA | BS5: =IF(N($H5)<11,"",IF(BM5="","",BM5+31)) | BT5: =IF(BS5="","",TODAY()-BS5) | BU5: 46177 | BV5: 5000000 | BW5: =IF(BS5="","SIN ESTADO",IF(BU5<>"","PAGA",IF(BT5>0,"VENCIDA",IF(BT5>=-5,"POR VENCER","AL DÍA")))) | BX5: TRANSFERENCIA | BY5: =IF(N($H5)<12,"",IF(BS5="","",BS5+31)) | BZ5: =IF(BY5="","",TODAY()-BY5) | CA5: 46223 | CB5: 3000000 | CC5: =IF(BY5="","SIN ESTADO",IF(CA5<>"","PAGA",IF(BZ5>0,"VENCIDA",IF(BZ5>=-5,"POR VENCER","AL DÍA")))) | CD5: TRANSFERENCIA | CE5: =IF(N($H5)<13,"",IF(BY5="","",BY5+31)) | CF5: =IF(CE5="","",TODAY()-CE5) | CG5: 46251 | CH5: 2500000 | CI5: =IF(CE5="","SIN ESTADO",IF(CG5<>"","PAGA",IF(CF5>0,"VENCIDA",IF(CF5>=-5,"POR VENCER","AL DÍA")))) | CJ5: TRANSFERENCIA | CK5: =IF(N($H5)<14,"",IF(CE5="","",CE5+31)) | CL5: =IF(CK5="","",TODAY()-CK5) | CM5: 46259 | CN5: 5000000 | CO5: =IF(CK5="","SIN ESTADO",IF(CM5<>"","PAGA",IF(CL5>0,"VENCIDA",IF(CL5>=-5,"POR VENCER","AL DÍA")))) | CP5: TRANSFERENCIA | CQ5: =IF(N($H5)<15,"",IF(CK5="","",CK5+31)) | CR5: =IF(CQ5="","",TODAY()-CQ5) | CU5: =IF(CQ5="","SIN ESTADO",IF(CS5<>"","PAGA",IF(CR5>0,"VENCIDA",IF(CR5>=-5,"POR VENCER","AL DÍA")))) | CW5: =IF(N($H5)<16,"",IF(CQ5="","",CQ5+31)) | CX5: =IF(CW5="","",TODAY()-CW5) | DA5: =IF(CW5="","SIN ESTADO",IF(CY5<>"","PAGA",IF(CX5>0,"VENCIDA",IF(CX5>=-5,"POR VENCER","AL DÍA")))) | DC5: =IF(N($H5)<17,"",IF(CW5="","",CW5+31)) | DD5: =IF(DC5="","",TODAY()-DC5) | DG5: =IF(DC5="","SIN ESTADO",IF(DE5<>"","PAGA",IF(DD5>0,"VENCIDA",IF(DD5>=-5,"POR VENCER","AL DÍA")))) | DI5: =IF(N($H5)<18,"",IF(DC5="","",DC5+31)) | DJ5: =IF(DI5="","",TODAY()-DI5) | DM5: =IF(DI5="","SIN ESTADO",IF(DK5<>"","PAGA",IF(DJ5>0,"VENCIDA",IF(DJ5>=-5,"POR VENCER","AL DÍA")))) | DO5: =IF(N($H5)<19,"",IF(DI5="","",DI5+31)) | DP5: =IF(DO5="","",TODAY()-DO5) | DS5: =IF(DO5="","SIN ESTADO",IF(DQ5<>"","PAGA",IF(DP5>0,"VENCIDA",IF(DP5>=-5,"POR VENCER","AL DÍA")))) | DU5: =IF(N($H5)<20,"",IF(DO5="","",DO5+31)) | DV5: =IF(DU5="","",TODAY()-DU5) | DY5: =IF(DU5="","SIN ESTADO",IF(DW5<>"","PAGA",IF(DV5>0,"VENCIDA",IF(DV5>=-5,"POR VENCER","AL DÍA")))) | EA5: =IF(N($H5)<21,"",IF(DU5="","",DU5+31)) | EB5: =IF(EA5="","",TODAY()-EA5) | EE5: =IF(EA5="","SIN ESTADO",IF(EC5<>"","PAGA",IF(EB5>0,"VENCIDA",IF(EB5>=-5,"POR VENCER","AL DÍA")))) | EG5: =IF(N($H5)<22,"",IF(EA5="","",EA5+31)) | EH5: =IF(EG5="","",TODAY()-EG5) | EK5: =IF(EG5="","SIN ESTADO",IF(EI5<>"","PAGA",IF(EH5>0,"VENCIDA",IF(EH5>=-5,"POR VENCER","AL DÍA")))) | EM5: =IF(N($H5)<23,"",IF(EG5="","",EG5+31)) | EN5: =IF(EM5="","",TODAY()-EM5) | EQ5: =IF(EM5="","SIN ESTADO",IF(EO5<>"","PAGA",IF(EN5>0,"VENCIDA",IF(EN5>=-5,"POR VENCER","AL DÍA")))) | ES5: =IF(N($H5)<24,"",IF(EM5="","",EM5+31)) | ET5: =IF(ES5="","",TODAY()-ES5) | EW5: =IF(ES5="","SIN ESTADO",IF(EU5<>"","PAGA",IF(ET5>0,"VENCIDA",IF(ET5>=-5,"POR VENCER","AL DÍA")))) | EY5: =IF(N($H5)<25,"",IF(ES5="","",ES5+31)) | EZ5: =IF(EY5="","",TODAY()-EY5) | FC5: =IF(EY5="","SIN ESTADO",IF(FA5<>"","PAGA",IF(EZ5>0,"VENCIDA",IF(EZ5>=-5,"POR VENCER","AL DÍA")))) | FE5: =IF(N($H5)<26,"",IF(EY5="","",EY5+31)) | FF5: =IF(FE5="","",TODAY()-FE5) | FI5: =IF(FE5="","SIN ESTADO",IF(FG5<>"","PAGA",IF(FF5>0,"VENCIDA",IF(FF5>=-5,"POR VENCER","AL DÍA")))) | FK5: =IF(N($H5)<27,"",IF(FE5="","",FE5+31)) | FL5: =IF(FK5="","",TODAY()-FK5) | FO5: =IF(FK5="","SIN ESTADO",IF(FM5<>"","PAGA",IF(FL5>0,"VENCIDA",IF(FL5>=-5,"POR VENCER","AL DÍA")))) | FQ5: =IF(N($H5)<28,"",IF(FK5="","",FK5+31)) | FR5: =IF(FQ5="","",TODAY()-FQ5) | FU5: =IF(FQ5="","SIN ESTADO",IF(FS5<>"","PAGA",IF(FR5>0,"VENCIDA",IF(FR5>=-5,"POR VENCER","AL DÍA")))) | FW5: =IF(N($H5)<29,"",IF(FQ5="","",FQ5+31)) | FX5: =IF(FW5="","",TODAY()-FW5) | GA5: =IF(FW5="","SIN ESTADO",IF(FY5<>"","PAGA",IF(FX5>0,"VENCIDA",IF(FX5>=-5,"POR VENCER","AL DÍA")))) | GC5: =IF(N($H5)<30,"",IF(FW5="","",FW5+31)) | GD5: =IF(GC5="","",TODAY()-GC5) | GG5: =IF(GC5="","SIN ESTADO",IF(GE5<>"","PAGA",IF(GD5>0,"VENCIDA",IF(GD5>=-5,"POR VENCER","AL DÍA")))) | GI5: =IF(N($H5)<31,"",IF(GC5="","",GC5+31)) | GJ5: =IF(GI5="","",TODAY()-GI5) | GM5: =IF(GI5="","SIN ESTADO",IF(GK5<>"","PAGA",IF(GJ5>0,"VENCIDA",IF(GJ5>=-5,"POR VENCER","AL DÍA")))) | GO5: =IF(N($H5)<32,"",IF(GI5="","",GI5+31)) | GP5: =IF(GO5="","",TODAY()-GO5) | GS5: =IF(GO5="","SIN ESTADO",IF(GQ5<>"","PAGA",IF(GP5>0,"VENCIDA",IF(GP5>=-5,"POR VENCER","AL DÍA")))) | GU5: =IF(N($H5)<33,"",IF(GO5="","",GO5+31)) | GV5: =IF(GU5="","",TODAY()-GU5) | GY5: =IF(GU5="","SIN ESTADO",IF(GW5<>"","PAGA",IF(GV5>0,"VENCIDA",IF(GV5>=-5,"POR VENCER","AL DÍA")))) | HA5: =IF(N($H5)<34,"",IF(GU5="","",GU5+31)) | HB5: =IF(HA5="","",TODAY()-HA5) | HE5: =IF(HA5="","SIN ESTADO",IF(HC5<>"","PAGA",IF(HB5>0,"VENCIDA",IF(HB5>=-5,"POR VENCER","AL DÍA")))) | HG5: =IF(N($H5)<35,"",IF(HA5="","",HA5+31)) | HH5: =IF(HG5="","",TODAY()-HG5) | HK5: =IF(HG5="","SIN ESTADO",IF(HI5<>"","PAGA",IF(HH5>0,"VENCIDA",IF(HH5>=-5,"POR VENCER","AL DÍA")))) | HM5: =IF(N($H5)<36,"",IF(HG5="","",HG5+31)) | HN5: =IF(HM5="","",TODAY()-HM5) | HQ5: =IF(HM5="","SIN ESTADO",IF(HO5<>"","PAGA",IF(HN5>0,"VENCIDA",IF(HN5>=-5,"POR VENCER","AL DÍA")))) | HS5: =N5+T5+Z5+AF5+AL5+AR5+AX5+BD5+BJ5+BP5+BV5+CB5+CH5+CN5+CT5+CZ5+DF5+DL5+DR5+DX5+ED5+EJ5+EP5+EV5+FB5+FH5+FN5+FT5+FZ5+GF5+GL5+GR5+GX5+HD5+HJ5+HP5 | HU5: =IFERROR(N($J5),0) | HW5: =SUMPRODUCT((MOD(COLUMN($M5:$HR5)-COLUMN($M5),6)=0)*ISNUMBER($M5:$HR5)*($M5:$HR5>=RESUMEN!$C$26)*($M5:$HR5<=RESUMEN!$C$27)*IFERROR(N($N5:$HS5),0)) | HX5: =SUMPRODUCT((MOD(COLUMN($M5:$HR5)-COLUMN($M5),6)=0)*ISNUMBER($M5:$HR5)*($M5:$HR5>=RESUMEN!$C$26)*($M5:$HR5<=RESUMEN!$C$27))
B6: =VENTAS!A5 | C6: =VENTAS!B5 | D6: =VENTAS!C5 | E6: =VENTAS!D5 | F6: =VENTAS!J5 | G6: =VENTAS!F5 | H6: =VENTAS!K5 | I6: =VENTAS!M5 | J6: =VENTAS!L5 | K6: =IF(N($H6)<1,"",$G6+31) | L6: =IF(K6="","",TODAY()-K6) | M6: 45920 | N6: 850000 | O6: =IF(K6="","SIN ESTADO",IF(M6<>"","PAGA",IF(L6>0,"VENCIDA",IF(L6>=-5,"POR VENCER","AL DÍA")))) | P6: TRANSFERENCIA | Q6: =IF(N($H6)<2,"",IF(K6="","",K6+31)) | R6: =IF(Q6="","",TODAY()-Q6) | S6: 45951 | T6: 850000 | U6: =IF(Q6="","SIN ESTADO",IF(S6<>"","PAGA",IF(R6>0,"VENCIDA",IF(R6>=-5,"POR VENCER","AL DÍA")))) | V6: TRANSFERENCIA | W6: =IF(N($H6)<3,"",IF(Q6="","",Q6+31)) | X6: =IF(W6="","",TODAY()-W6) | Y6: 45982 | Z6: 850000 | AA6: =IF(W6="","SIN ESTADO",IF(Y6<>"","PAGA",IF(X6>0,"VENCIDA",IF(X6>=-5,"POR VENCER","AL DÍA")))) | AB6: TRANSFERENCIA | AC6: =IF(N($H6)<4,"",IF(W6="","",W6+31)) | AD6: =IF(AC6="","",TODAY()-AC6) | AE6: 45997 | AF6: 8000000 | AG6: =IF(AC6="","SIN ESTADO",IF(AE6<>"","PAGA",IF(AD6>0,"VENCIDA",IF(AD6>=-5,"POR VENCER","AL DÍA")))) | AH6: EFECTIVO | AI6: =IF(N($H6)<5,"",IF(AC6="","",AC6+31)) | AJ6: =IF(AI6="","",TODAY()-AI6) | AK6: 46013 | AL6: 850000 | AM6: =IF(AI6="","SIN ESTADO",IF(AK6<>"","PAGA",IF(AJ6>0,"VENCIDA",IF(AJ6>=-5,"POR VENCER","AL DÍA")))) | AN6: TRANSFERENCIA | AO6: =IF(N($H6)<6,"",IF(AI6="","",AI6+31)) | AP6: =IF(AO6="","",TODAY()-AO6) | AQ6: 46014 | AR6: 5600000 | AS6: =IF(AO6="","SIN ESTADO",IF(AQ6<>"","PAGA",IF(AP6>0,"VENCIDA",IF(AP6>=-5,"POR VENCER","AL DÍA")))) | AT6: EFECTIVO | AU6: =IF(N($H6)<7,"",IF(AO6="","",AO6+31)) | AV6: =IF(AU6="","",TODAY()-AU6) | AY6: =IF(AU6="","SIN ESTADO",IF(AW6<>"","PAGA",IF(AV6>0,"VENCIDA",IF(AV6>=-5,"POR VENCER","AL DÍA")))) | BA6: =IF(N($H6)<8,"",IF(AU6="","",AU6+31)) | BB6: =IF(BA6="","",TODAY()-BA6) | BE6: =IF(BA6="","SIN ESTADO",IF(BC6<>"","PAGA",IF(BB6>0,"VENCIDA",IF(BB6>=-5,"POR VENCER","AL DÍA")))) | BG6: =IF(N($H6)<9,"",IF(BA6="","",BA6+31)) | BH6: =IF(BG6="","",TODAY()-BG6) | BK6: =IF(BG6="","SIN ESTADO",IF(BI6<>"","PAGA",IF(BH6>0,"VENCIDA",IF(BH6>=-5,"POR VENCER","AL DÍA")))) | BM6: =IF(N($H6)<10,"",IF(BG6="","",BG6+31)) | BN6: =IF(BM6="","",TODAY()-BM6) | BQ6: =IF(BM6="","SIN ESTADO",IF(BO6<>"","PAGA",IF(BN6>0,"VENCIDA",IF(BN6>=-5,"POR VENCER","AL DÍA")))) | BS6: =IF(N($H6)<11,"",IF(BM6="","",BM6+31)) | BT6: =IF(BS6="","",TODAY()-BS6) | BW6: =IF(BS6="","SIN ESTADO",IF(BU6<>"","PAGA",IF(BT6>0,"VENCIDA",IF(BT6>=-5,"POR VENCER","AL DÍA")))) | BY6: =IF(N($H6)<12,"",IF(BS6="","",BS6+31)) | BZ6: =IF(BY6="","",TODAY()-BY6) | CC6: =IF(BY6="","SIN ESTADO",IF(CA6<>"","PAGA",IF(BZ6>0,"VENCIDA",IF(BZ6>=-5,"POR VENCER","AL DÍA")))) | CE6: =IF(N($H6)<13,"",IF(BY6="","",BY6+31)) | CF6: =IF(CE6="","",TODAY()-CE6) | CI6: =IF(CE6="","SIN ESTADO",IF(CG6<>"","PAGA",IF(CF6>0,"VENCIDA",IF(CF6>=-5,"POR VENCER","AL DÍA")))) | CK6: =IF(N($H6)<14,"",IF(CE6="","",CE6+31)) | CL6: =IF(CK6="","",TODAY()-CK6) | CO6: =IF(CK6="","SIN ESTADO",IF(CM6<>"","PAGA",IF(CL6>0,"VENCIDA",IF(CL6>=-5,"POR VENCER","AL DÍA")))) | CQ6: =IF(N($H6)<15,"",IF(CK6="","",CK6+31)) | CR6: =IF(CQ6="","",TODAY()-CQ6) | CU6: =IF(CQ6="","SIN ESTADO",IF(CS6<>"","PAGA",IF(CR6>0,"VENCIDA",IF(CR6>=-5,"POR VENCER","AL DÍA")))) | CW6: =IF(N($H6)<16,"",IF(CQ6="","",CQ6+31)) | CX6: =IF(CW6="","",TODAY()-CW6) | DA6: =IF(CW6="","SIN ESTADO",IF(CY6<>"","PAGA",IF(CX6>0,"VENCIDA",IF(CX6>=-5,"POR VENCER","AL DÍA")))) | DC6: =IF(N($H6)<17,"",IF(CW6="","",CW6+31)) | DD6: =IF(DC6="","",TODAY()-DC6) | DG6: =IF(DC6="","SIN ESTADO",IF(DE6<>"","PAGA",IF(DD6>0,"VENCIDA",IF(DD6>=-5,"POR VENCER","AL DÍA")))) | DI6: =IF(N($H6)<18,"",IF(DC6="","",DC6+31)) | DJ6: =IF(DI6="","",TODAY()-DI6) | DM6: =IF(DI6="","SIN ESTADO",IF(DK6<>"","PAGA",IF(DJ6>0,"VENCIDA",IF(DJ6>=-5,"POR VENCER","AL DÍA")))) | DO6: =IF(N($H6)<19,"",IF(DI6="","",DI6+31)) | DP6: =IF(DO6="","",TODAY()-DO6) | DS6: =IF(DO6="","SIN ESTADO",IF(DQ6<>"","PAGA",IF(DP6>0,"VENCIDA",IF(DP6>=-5,"POR VENCER","AL DÍA")))) | DU6: =IF(N($H6)<20,"",IF(DO6="","",DO6+31)) | DV6: =IF(DU6="","",TODAY()-DU6) | DY6: =IF(DU6="","SIN ESTADO",IF(DW6<>"","PAGA",IF(DV6>0,"VENCIDA",IF(DV6>=-5,"POR VENCER","AL DÍA")))) | EA6: =IF(N($H6)<21,"",IF(DU6="","",DU6+31)) | EB6: =IF(EA6="","",TODAY()-EA6) | EE6: =IF(EA6="","SIN ESTADO",IF(EC6<>"","PAGA",IF(EB6>0,"VENCIDA",IF(EB6>=-5,"POR VENCER","AL DÍA")))) | EG6: =IF(N($H6)<22,"",IF(EA6="","",EA6+31)) | EH6: =IF(EG6="","",TODAY()-EG6) | EK6: =IF(EG6="","SIN ESTADO",IF(EI6<>"","PAGA",IF(EH6>0,"VENCIDA",IF(EH6>=-5,"POR VENCER","AL DÍA")))) | EM6: =IF(N($H6)<23,"",IF(EG6="","",EG6+31)) | EN6: =IF(EM6="","",TODAY()-EM6) | EQ6: =IF(EM6="","SIN ESTADO",IF(EO6<>"","PAGA",IF(EN6>0,"VENCIDA",IF(EN6>=-5,"POR VENCER","AL DÍA")))) | ES6: =IF(N($H6)<24,"",IF(EM6="","",EM6+31)) | ET6: =IF(ES6="","",TODAY()-ES6) | EW6: =IF(ES6="","SIN ESTADO",IF(EU6<>"","PAGA",IF(ET6>0,"VENCIDA",IF(ET6>=-5,"POR VENCER","AL DÍA")))) | EY6: =IF(N($H6)<25,"",IF(ES6="","",ES6+31)) | EZ6: =IF(EY6="","",TODAY()-EY6) | FC6: =IF(EY6="","SIN ESTADO",IF(FA6<>"","PAGA",IF(EZ6>0,"VENCIDA",IF(EZ6>=-5,"POR VENCER","AL DÍA")))) | FE6: =IF(N($H6)<26,"",IF(EY6="","",EY6+31)) | FF6: =IF(FE6="","",TODAY()-FE6) | FI6: =IF(FE6="","SIN ESTADO",IF(FG6<>"","PAGA",IF(FF6>0,"VENCIDA",IF(FF6>=-5,"POR VENCER","AL DÍA")))) | FK6: =IF(N($H6)<27,"",IF(FE6="","",FE6+31)) | FL6: =IF(FK6="","",TODAY()-FK6) | FO6: =IF(FK6="","SIN ESTADO",IF(FM6<>"","PAGA",IF(FL6>0,"VENCIDA",IF(FL6>=-5,"POR VENCER","AL DÍA")))) | FQ6: =IF(N($H6)<28,"",IF(FK6="","",FK6+31)) | FR6: =IF(FQ6="","",TODAY()-FQ6) | FU6: =IF(FQ6="","SIN ESTADO",IF(FS6<>"","PAGA",IF(FR6>0,"VENCIDA",IF(FR6>=-5,"POR VENCER","AL DÍA")))) | FW6: =IF(N($H6)<29,"",IF(FQ6="","",FQ6+31)) | FX6: =IF(FW6="","",TODAY()-FW6) | GA6: =IF(FW6="","SIN ESTADO",IF(FY6<>"","PAGA",IF(FX6>0,"VENCIDA",IF(FX6>=-5,"POR VENCER","AL DÍA")))) | GC6: =IF(N($H6)<30,"",IF(FW6="","",FW6+31)) | GD6: =IF(GC6="","",TODAY()-GC6) | GG6: =IF(GC6="","SIN ESTADO",IF(GE6<>"","PAGA",IF(GD6>0,"VENCIDA",IF(GD6>=-5,"POR VENCER","AL DÍA")))) | GI6: =IF(N($H6)<31,"",IF(GC6="","",GC6+31)) | GJ6: =IF(GI6="","",TODAY()-GI6) | GM6: =IF(GI6="","SIN ESTADO",IF(GK6<>"","PAGA",IF(GJ6>0,"VENCIDA",IF(GJ6>=-5,"POR VENCER","AL DÍA")))) | GO6: =IF(N($H6)<32,"",IF(GI6="","",GI6+31)) | GP6: =IF(GO6="","",TODAY()-GO6) | GS6: =IF(GO6="","SIN ESTADO",IF(GQ6<>"","PAGA",IF(GP6>0,"VENCIDA",IF(GP6>=-5,"POR VENCER","AL DÍA")))) | GU6: =IF(N($H6)<33,"",IF(GO6="","",GO6+31)) | GV6: =IF(GU6="","",TODAY()-GU6) | GY6: =IF(GU6="","SIN ESTADO",IF(GW6<>"","PAGA",IF(GV6>0,"VENCIDA",IF(GV6>=-5,"POR VENCER","AL DÍA")))) | HA6: =IF(N($H6)<34,"",IF(GU6="","",GU6+31)) | HB6: =IF(HA6="","",TODAY()-HA6) | HE6: =IF(HA6="","SIN ESTADO",IF(HC6<>"","PAGA",IF(HB6>0,"VENCIDA",IF(HB6>=-5,"POR VENCER","AL DÍA")))) | HG6: =IF(N($H6)<35,"",IF(HA6="","",HA6+31)) | HH6: =IF(HG6="","",TODAY()-HG6) | HK6: =IF(HG6="","SIN ESTADO",IF(HI6<>"","PAGA",IF(HH6>0,"VENCIDA",IF(HH6>=-5,"POR VENCER","AL DÍA")))) | HM6: =IF(N($H6)<36,"",IF(HG6="","",HG6+31)) | HN6: =IF(HM6="","",TODAY()-HM6) | HQ6: =IF(HM6="","SIN ESTADO",IF(HO6<>"","PAGA",IF(HN6>0,"VENCIDA",IF(HN6>=-5,"POR VENCER","AL DÍA")))) | HS6: =N6+T6+Z6+AF6+AL6+AR6+AX6+BD6+BJ6+BP6+BV6+CB6+CH6+CN6+CT6+CZ6+DF6+DL6+DR6+DX6+ED6+EJ6+EP6+EV6+FB6+FH6+FN6+FT6+FZ6+GF6+GL6+GR6+GX6+HD6+HJ6+HP6 | HU6: =IFERROR(N($J6),0) | HW6: =SUMPRODUCT((MOD(COLUMN($M6:$HR6)-COLUMN($M6),6)=0)*ISNUMBER($M6:$HR6)*($M6:$HR6>=RESUMEN!$C$26)*($M6:$HR6<=RESUMEN!$C$27)*IFERROR(N($N6:$HS6),0)) | HX6: =SUMPRODUCT((MOD(COLUMN($M6:$HR6)-COLUMN($M6),6)=0)*ISNUMBER($M6:$HR6)*($M6:$HR6>=RESUMEN!$C$26)*($M6:$HR6<=RESUMEN!$C$27))
B7: =VENTAS!A6 | C7: =VENTAS!B6 | D7: =VENTAS!C6 | E7: =VENTAS!D6 | F7: =VENTAS!J6 | G7: =VENTAS!F6 | H7: =VENTAS!K6 | I7: =VENTAS!M6 | J7: =VENTAS!L6 | K7: =IF(N($H7)<1,"",$G7+31) | L7: =IF(K7="","",TODAY()-K7) | M7: 46229 | N7: 2000000 | O7: =IF(K7="","SIN ESTADO",IF(M7<>"","PAGA",IF(L7>0,"VENCIDA",IF(L7>=-5,"POR VENCER","AL DÍA")))) | P7: TRANSFERENCIA | Q7: =IF(N($H7)<2,"",IF(K7="","",K7+31)) | R7: =IF(Q7="","",TODAY()-Q7) | U7: =IF(Q7="","SIN ESTADO",IF(S7<>"","PAGA",IF(R7>0,"VENCIDA",IF(R7>=-5,"POR VENCER","AL DÍA")))) | W7: =IF(N($H7)<3,"",IF(Q7="","",Q7+31)) | X7: =IF(W7="","",TODAY()-W7) | AA7: =IF(W7="","SIN ESTADO",IF(Y7<>"","PAGA",IF(X7>0,"VENCIDA",IF(X7>=-5,"POR VENCER","AL DÍA")))) | AC7: =IF(N($H7)<4,"",IF(W7="","",W7+31)) | AD7: =IF(AC7="","",TODAY()-AC7) | AG7: =IF(AC7="","SIN ESTADO",IF(AE7<>"","PAGA",IF(AD7>0,"VENCIDA",IF(AD7>=-5,"POR VENCER","AL DÍA")))) | AI7: =IF(N($H7)<5,"",IF(AC7="","",AC7+31)) | AJ7: =IF(AI7="","",TODAY()-AI7) | AM7: =IF(AI7="","SIN ESTADO",IF(AK7<>"","PAGA",IF(AJ7>0,"VENCIDA",IF(AJ7>=-5,"POR VENCER","AL DÍA")))) | AO7: =IF(N($H7)<6,"",IF(AI7="","",AI7+31)) | AP7: =IF(AO7="","",TODAY()-AO7) | AS7: =IF(AO7="","SIN ESTADO",IF(AQ7<>"","PAGA",IF(AP7>0,"VENCIDA",IF(AP7>=-5,"POR VENCER","AL DÍA")))) | AU7: =IF(N($H7)<7,"",IF(AO7="","",AO7+31)) | AV7: =IF(AU7="","",TODAY()-AU7) | AY7: =IF(AU7="","SIN ESTADO",IF(AW7<>"","PAGA",IF(AV7>0,"VENCIDA",IF(AV7>=-5,"POR VENCER","AL DÍA")))) | BA7: =IF(N($H7)<8,"",IF(AU7="","",AU7+31)) | BB7: =IF(BA7="","",TODAY()-BA7) | BE7: =IF(BA7="","SIN ESTADO",IF(BC7<>"","PAGA",IF(BB7>0,"VENCIDA",IF(BB7>=-5,"POR VENCER","AL DÍA")))) | BG7: =IF(N($H7)<9,"",IF(BA7="","",BA7+31)) | BH7: =IF(BG7="","",TODAY()-BG7) | BK7: =IF(BG7="","SIN ESTADO",IF(BI7<>"","PAGA",IF(BH7>0,"VENCIDA",IF(BH7>=-5,"POR VENCER","AL DÍA")))) | BM7: =IF(N($H7)<10,"",IF(BG7="","",BG7+31)) | BN7: =IF(BM7="","",TODAY()-BM7) | BQ7: =IF(BM7="","SIN ESTADO",IF(BO7<>"","PAGA",IF(BN7>0,"VENCIDA",IF(BN7>=-5,"POR VENCER","AL DÍA")))) | BS7: =IF(N($H7)<11,"",IF(BM7="","",BM7+31)) | BT7: =IF(BS7="","",TODAY()-BS7) | BW7: =IF(BS7="","SIN ESTADO",IF(BU7<>"","PAGA",IF(BT7>0,"VENCIDA",IF(BT7>=-5,"POR VENCER","AL DÍA")))) | BY7: =IF(N($H7)<12,"",IF(BS7="","",BS7+31)) | BZ7: =IF(BY7="","",TODAY()-BY7) | CC7: =IF(BY7="","SIN ESTADO",IF(CA7<>"","PAGA",IF(BZ7>0,"VENCIDA",IF(BZ7>=-5,"POR VENCER","AL DÍA")))) | CE7: =IF(N($H7)<13,"",IF(BY7="","",BY7+31)) | CF7: =IF(CE7="","",TODAY()-CE7) | CI7: =IF(CE7="","SIN ESTADO",IF(CG7<>"","PAGA",IF(CF7>0,"VENCIDA",IF(CF7>=-5,"POR VENCER","AL DÍA")))) | CK7: =IF(N($H7)<14,"",IF(CE7="","",CE7+31)) | CL7: =IF(CK7="","",TODAY()-CK7) | CO7: =IF(CK7="","SIN ESTADO",IF(CM7<>"","PAGA",IF(CL7>0,"VENCIDA",IF(CL7>=-5,"POR VENCER","AL DÍA")))) | CQ7: =IF(N($H7)<15,"",IF(CK7="","",CK7+31)) | CR7: =IF(CQ7="","",TODAY()-CQ7) | CU7: =IF(CQ7="","SIN ESTADO",IF(CS7<>"","PAGA",IF(CR7>0,"VENCIDA",IF(CR7>=-5,"POR VENCER","AL DÍA")))) | CW7: =IF(N($H7)<16,"",IF(CQ7="","",CQ7+31)) | CX7: =IF(CW7="","",TODAY()-CW7) | DA7: =IF(CW7="","SIN ESTADO",IF(CY7<>"","PAGA",IF(CX7>0,"VENCIDA",IF(CX7>=-5,"POR VENCER","AL DÍA")))) | DC7: =IF(N($H7)<17,"",IF(CW7="","",CW7+31)) | DD7: =IF(DC7="","",TODAY()-DC7) | DG7: =IF(DC7="","SIN ESTADO",IF(DE7<>"","PAGA",IF(DD7>0,"VENCIDA",IF(DD7>=-5,"POR VENCER","AL DÍA")))) | DI7: =IF(N($H7)<18,"",IF(DC7="","",DC7+31)) | DJ7: =IF(DI7="","",TODAY()-DI7) | DM7: =IF(DI7="","SIN ESTADO",IF(DK7<>"","PAGA",IF(DJ7>0,"VENCIDA",IF(DJ7>=-5,"POR VENCER","AL DÍA")))) | DO7: =IF(N($H7)<19,"",IF(DI7="","",DI7+31)) | DP7: =IF(DO7="","",TODAY()-DO7) | DS7: =IF(DO7="","SIN ESTADO",IF(DQ7<>"","PAGA",IF(DP7>0,"VENCIDA",IF(DP7>=-5,"POR VENCER","AL DÍA")))) | DU7: =IF(N($H7)<20,"",IF(DO7="","",DO7+31)) | DV7: =IF(DU7="","",TODAY()-DU7) | DY7: =IF(DU7="","SIN ESTADO",IF(DW7<>"","PAGA",IF(DV7>0,"VENCIDA",IF(DV7>=-5,"POR VENCER","AL DÍA")))) | EA7: =IF(N($H7)<21,"",IF(DU7="","",DU7+31)) | EB7: =IF(EA7="","",TODAY()-EA7) | EE7: =IF(EA7="","SIN ESTADO",IF(EC7<>"","PAGA",IF(EB7>0,"VENCIDA",IF(EB7>=-5,"POR VENCER","AL DÍA")))) | EG7: =IF(N($H7)<22,"",IF(EA7="","",EA7+31)) | EH7: =IF(EG7="","",TODAY()-EG7) | EK7: =IF(EG7="","SIN ESTADO",IF(EI7<>"","PAGA",IF(EH7>0,"VENCIDA",IF(EH7>=-5,"POR VENCER","AL DÍA")))) | EM7: =IF(N($H7)<23,"",IF(EG7="","",EG7+31)) | EN7: =IF(EM7="","",TODAY()-EM7) | EQ7: =IF(EM7="","SIN ESTADO",IF(EO7<>"","PAGA",IF(EN7>0,"VENCIDA",IF(EN7>=-5,"POR VENCER","AL DÍA")))) | ES7: =IF(N($H7)<24,"",IF(EM7="","",EM7+31)) | ET7: =IF(ES7="","",TODAY()-ES7) | EW7: =IF(ES7="","SIN ESTADO",IF(EU7<>"","PAGA",IF(ET7>0,"VENCIDA",IF(ET7>=-5,"POR VENCER","AL DÍA")))) | EY7: =IF(N($H7)<25,"",IF(ES7="","",ES7+31)) | EZ7: =IF(EY7="","",TODAY()-EY7) | FC7: =IF(EY7="","SIN ESTADO",IF(FA7<>"","PAGA",IF(EZ7>0,"VENCIDA",IF(EZ7>=-5,"POR VENCER","AL DÍA")))) | FE7: =IF(N($H7)<26,"",IF(EY7="","",EY7+31)) | FF7: =IF(FE7="","",TODAY()-FE7) | FI7: =IF(FE7="","SIN ESTADO",IF(FG7<>"","PAGA",IF(FF7>0,"VENCIDA",IF(FF7>=-5,"POR VENCER","AL DÍA")))) | FK7: =IF(N($H7)<27,"",IF(FE7="","",FE7+31)) | FL7: =IF(FK7="","",TODAY()-FK7) | FO7: =IF(FK7="","SIN ESTADO",IF(FM7<>"","PAGA",IF(FL7>0,"VENCIDA",IF(FL7>=-5,"POR VENCER","AL DÍA")))) | FQ7: =IF(N($H7)<28,"",IF(FK7="","",FK7+31)) | FR7: =IF(FQ7="","",TODAY()-FQ7) | FU7: =IF(FQ7="","SIN ESTADO",IF(FS7<>"","PAGA",IF(FR7>0,"VENCIDA",IF(FR7>=-5,"POR VENCER","AL DÍA")))) | FW7: =IF(N($H7)<29,"",IF(FQ7="","",FQ7+31)) | FX7: =IF(FW7="","",TODAY()-FW7) | GA7: =IF(FW7="","SIN ESTADO",IF(FY7<>"","PAGA",IF(FX7>0,"VENCIDA",IF(FX7>=-5,"POR VENCER","AL DÍA")))) | GC7: =IF(N($H7)<30,"",IF(FW7="","",FW7+31)) | GD7: =IF(GC7="","",TODAY()-GC7) | GG7: =IF(GC7="","SIN ESTADO",IF(GE7<>"","PAGA",IF(GD7>0,"VENCIDA",IF(GD7>=-5,"POR VENCER","AL DÍA")))) | GI7: =IF(N($H7)<31,"",IF(GC7="","",GC7+31)) | GJ7: =IF(GI7="","",TODAY()-GI7) | GM7: =IF(GI7="","SIN ESTADO",IF(GK7<>"","PAGA",IF(GJ7>0,"VENCIDA",IF(GJ7>=-5,"POR VENCER","AL DÍA")))) | GO7: =IF(N($H7)<32,"",IF(GI7="","",GI7+31)) | GP7: =IF(GO7="","",TODAY()-GO7) | GS7: =IF(GO7="","SIN ESTADO",IF(GQ7<>"","PAGA",IF(GP7>0,"VENCIDA",IF(GP7>=-5,"POR VENCER","AL DÍA")))) | GU7: =IF(N($H7)<33,"",IF(GO7="","",GO7+31)) | GV7: =IF(GU7="","",TODAY()-GU7) | GY7: =IF(GU7="","SIN ESTADO",IF(GW7<>"","PAGA",IF(GV7>0,"VENCIDA",IF(GV7>=-5,"POR VENCER","AL DÍA")))) | HA7: =IF(N($H7)<34,"",IF(GU7="","",GU7+31)) | HB7: =IF(HA7="","",TODAY()-HA7) | HE7: =IF(HA7="","SIN ESTADO",IF(HC7<>"","PAGA",IF(HB7>0,"VENCIDA",IF(HB7>=-5,"POR VENCER","AL DÍA")))) | HG7: =IF(N($H7)<35,"",IF(HA7="","",HA7+31)) | HH7: =IF(HG7="","",TODAY()-HG7) | HK7: =IF(HG7="","SIN ESTADO",IF(HI7<>"","PAGA",IF(HH7>0,"VENCIDA",IF(HH7>=-5,"POR VENCER","AL DÍA")))) | HM7: =IF(N($H7)<36,"",IF(HG7="","",HG7+31)) | HN7: =IF(HM7="","",TODAY()-HM7) | HQ7: =IF(HM7="","SIN ESTADO",IF(HO7<>"","PAGA",IF(HN7>0,"VENCIDA",IF(HN7>=-5,"POR VENCER","AL DÍA")))) | HS7: =N7+T7+Z7+AF7+AL7+AR7+AX7+BD7+BJ7+BP7+BV7+CB7+CH7+CN7+CT7+CZ7+DF7+DL7+DR7+DX7+ED7+EJ7+EP7+EV7+FB7+FH7+FN7+FT7+FZ7+GF7+GL7+GR7+GX7+HD7+HJ7+HP7 | HU7: =IFERROR(N($J7),0) | HW7: =SUMPRODUCT((MOD(COLUMN($M7:$HR7)-COLUMN($M7),6)=0)*ISNUMBER($M7:$HR7)*($M7:$HR7>=RESUMEN!$C$26)*($M7:$HR7<=RESUMEN!$C$27)*IFERROR(N($N7:$HS7),0)) | HX7: =SUMPRODUCT((MOD(COLUMN($M7:$HR7)-COLUMN($M7),6)=0)*ISNUMBER($M7:$HR7)*($M7:$HR7>=RESUMEN!$C$26)*($M7:$HR7<=RESUMEN!$C$27))
B8: =VENTAS!A7 | C8: =VENTAS!B7 | D8: =VENTAS!C7 | E8: =VENTAS!D7 | F8: =VENTAS!J7 | G8: =VENTAS!F7 | H8: =VENTAS!K7 | I8: =VENTAS!M7 | J8: =VENTAS!L7 | K8: =IF(N($H8)<1,"",$G8+31) | L8: =IF(K8="","",TODAY()-K8) | M8: 45880 | N8: 1083000 | O8: =IF(K8="","SIN ESTADO",IF(M8<>"","PAGA",IF(L8>0,"VENCIDA",IF(L8>=-5,"POR VENCER","AL DÍA")))) | P8: EFECTIVO | Q8: =IF(N($H8)<2,"",IF(K8="","",K8+31)) | R8: =IF(Q8="","",TODAY()-Q8) | S8: 45912 | T8: 1083000 | U8: =IF(Q8="","SIN ESTADO",IF(S8<>"","PAGA",IF(R8>0,"VENCIDA",IF(R8>=-5,"POR VENCER","AL DÍA")))) | V8: TRANSFERENCIA | W8: =IF(N($H8)<3,"",IF(Q8="","",Q8+31)) | X8: =IF(W8="","",TODAY()-W8) | Y8: 45934 | Z8: 1083000 | AA8: =IF(W8="","SIN ESTADO",IF(Y8<>"","PAGA",IF(X8>0,"VENCIDA",IF(X8>=-5,"POR VENCER","AL DÍA")))) | AB8: TRANSFERENCIA | AC8: =IF(N($H8)<4,"",IF(W8="","",W8+31)) | AD8: =IF(AC8="","",TODAY()-AC8) | AE8: 45972 | AF8: 1083000 | AG8: =IF(AC8="","SIN ESTADO",IF(AE8<>"","PAGA",IF(AD8>0,"VENCIDA",IF(AD8>=-5,"POR VENCER","AL DÍA")))) | AH8: TRANSFERENCIA | AI8: =IF(N($H8)<5,"",IF(AC8="","",AC8+31)) | AJ8: =IF(AI8="","",TODAY()-AI8) | AK8: 46008 | AL8: 1083000 | AM8: =IF(AI8="","SIN ESTADO",IF(AK8<>"","PAGA",IF(AJ8>0,"VENCIDA",IF(AJ8>=-5,"POR VENCER","AL DÍA")))) | AN8: TRANSFERENCIA | AO8: =IF(N($H8)<6,"",IF(AI8="","",AI8+31)) | AP8: =IF(AO8="","",TODAY()-AO8) | AQ8: 46038 | AR8: 1083000 | AS8: =IF(AO8="","SIN ESTADO",IF(AQ8<>"","PAGA",IF(AP8>0,"VENCIDA",IF(AP8>=-5,"POR VENCER","AL DÍA")))) | AT8: TRANSFERENCIA | AU8: =IF(N($H8)<7,"",IF(AO8="","",AO8+31)) | AV8: =IF(AU8="","",TODAY()-AU8) | AW8: 46073 | AX8: 1083000 | AY8: =IF(AU8="","SIN ESTADO",IF(AW8<>"","PAGA",IF(AV8>0,"VENCIDA",IF(AV8>=-5,"POR VENCER","AL DÍA")))) | AZ8: TRANSFERENCIA | BA8: =IF(N($H8)<8,"",IF(AU8="","",AU8+31)) | BB8: =IF(BA8="","",TODAY()-BA8) | BC8: 46095 | BD8: 1083000 | BE8: =IF(BA8="","SIN ESTADO",IF(BC8<>"","PAGA",IF(BB8>0,"VENCIDA",IF(BB8>=-5,"POR VENCER","AL DÍA")))) | BF8: TRANSFERENCIA | BG8: =IF(N($H8)<9,"",IF(BA8="","",BA8+31)) | BH8: =IF(BG8="","",TODAY()-BG8) | BI8: 46169 | BJ8: 16500000 | BK8: =IF(BG8="","SIN ESTADO",IF(BI8<>"","PAGA",IF(BH8>0,"VENCIDA",IF(BH8>=-5,"POR VENCER","AL DÍA")))) | BL8: TRANSFERENCIA | BM8: =IF(N($H8)<10,"",IF(BG8="","",BG8+31)) | BN8: =IF(BM8="","",TODAY()-BM8) | BO8: 46169 | BQ8: =IF(BM8="","SIN ESTADO",IF(BO8<>"","PAGA",IF(BN8>0,"VENCIDA",IF(BN8>=-5,"POR VENCER","AL DÍA")))) | BS8: =IF(N($H8)<11,"",IF(BM8="","",BM8+31)) | BT8: =IF(BS8="","",TODAY()-BS8) | BU8: 46163 | BW8: =IF(BS8="","SIN ESTADO",IF(BU8<>"","PAGA",IF(BT8>0,"VENCIDA",IF(BT8>=-5,"POR VENCER","AL DÍA")))) | BY8: =IF(N($H8)<12,"",IF(BS8="","",BS8+31)) | BZ8: =IF(BY8="","",TODAY()-BY8) | CA8: 46169 | CC8: =IF(BY8="","SIN ESTADO",IF(CA8<>"","PAGA",IF(BZ8>0,"VENCIDA",IF(BZ8>=-5,"POR VENCER","AL DÍA")))) | CE8: =IF(N($H8)<13,"",IF(BY8="","",BY8+31)) | CF8: =IF(CE8="","",TODAY()-CE8) | CG8: 46169 | CI8: =IF(CE8="","SIN ESTADO",IF(CG8<>"","PAGA",IF(CF8>0,"VENCIDA",IF(CF8>=-5,"POR VENCER","AL DÍA")))) | CK8: =IF(N($H8)<14,"",IF(CE8="","",CE8+31)) | CL8: =IF(CK8="","",TODAY()-CK8) | CM8: 46169 | CO8: =IF(CK8="","SIN ESTADO",IF(CM8<>"","PAGA",IF(CL8>0,"VENCIDA",IF(CL8>=-5,"POR VENCER","AL DÍA")))) | CQ8: =IF(N($H8)<15,"",IF(CK8="","",CK8+31)) | CR8: =IF(CQ8="","",TODAY()-CQ8) | CS8: 46169 | CU8: =IF(CQ8="","SIN ESTADO",IF(CS8<>"","PAGA",IF(CR8>0,"VENCIDA",IF(CR8>=-5,"POR VENCER","AL DÍA")))) | CW8: =IF(N($H8)<16,"",IF(CQ8="","",CQ8+31)) | CX8: =IF(CW8="","",TODAY()-CW8) | CY8: 46169 | DA8: =IF(CW8="","SIN ESTADO",IF(CY8<>"","PAGA",IF(CX8>0,"VENCIDA",IF(CX8>=-5,"POR VENCER","AL DÍA")))) | DC8: =IF(N($H8)<17,"",IF(CW8="","",CW8+31)) | DD8: =IF(DC8="","",TODAY()-DC8) | DE8: 46169 | DG8: =IF(DC8="","SIN ESTADO",IF(DE8<>"","PAGA",IF(DD8>0,"VENCIDA",IF(DD8>=-5,"POR VENCER","AL DÍA")))) | DI8: =IF(N($H8)<18,"",IF(DC8="","",DC8+31)) | DJ8: =IF(DI8="","",TODAY()-DI8) | DK8: 46169 | DM8: =IF(DI8="","SIN ESTADO",IF(DK8<>"","PAGA",IF(DJ8>0,"VENCIDA",IF(DJ8>=-5,"POR VENCER","AL DÍA")))) | DO8: =IF(N($H8)<19,"",IF(DI8="","",DI8+31)) | DP8: =IF(DO8="","",TODAY()-DO8) | DQ8: 46169 | DS8: =IF(DO8="","SIN ESTADO",IF(DQ8<>"","PAGA",IF(DP8>0,"VENCIDA",IF(DP8>=-5,"POR VENCER","AL DÍA")))) | DU8: =IF(N($H8)<20,"",IF(DO8="","",DO8+31)) | DV8: =IF(DU8="","",TODAY()-DU8) | DW8: 46169 | DY8: =IF(DU8="","SIN ESTADO",IF(DW8<>"","PAGA",IF(DV8>0,"VENCIDA",IF(DV8>=-5,"POR VENCER","AL DÍA")))) | EA8: =IF(N($H8)<21,"",IF(DU8="","",DU8+31)) | EB8: =IF(EA8="","",TODAY()-EA8) | EC8: 46169 | EE8: =IF(EA8="","SIN ESTADO",IF(EC8<>"","PAGA",IF(EB8>0,"VENCIDA",IF(EB8>=-5,"POR VENCER","AL DÍA")))) | EG8: =IF(N($H8)<22,"",IF(EA8="","",EA8+31)) | EH8: =IF(EG8="","",TODAY()-EG8) | EI8: 5/27/2026 | EK8: =IF(EG8="","SIN ESTADO",IF(EI8<>"","PAGA",IF(EH8>0,"VENCIDA",IF(EH8>=-5,"POR VENCER","AL DÍA")))) | EM8: =IF(N($H8)<23,"",IF(EG8="","",EG8+31)) | EN8: =IF(EM8="","",TODAY()-EM8) | EO8: 46169 | EQ8: =IF(EM8="","SIN ESTADO",IF(EO8<>"","PAGA",IF(EN8>0,"VENCIDA",IF(EN8>=-5,"POR VENCER","AL DÍA")))) | ES8: =IF(N($H8)<24,"",IF(EM8="","",EM8+31)) | ET8: =IF(ES8="","",TODAY()-ES8) | EU8: 46169 | EW8: =IF(ES8="","SIN ESTADO",IF(EU8<>"","PAGA",IF(ET8>0,"VENCIDA",IF(ET8>=-5,"POR VENCER","AL DÍA")))) | EY8: =IF(N($H8)<25,"",IF(ES8="","",ES8+31)) | EZ8: =IF(EY8="","",TODAY()-EY8) | FC8: =IF(EY8="","SIN ESTADO",IF(FA8<>"","PAGA",IF(EZ8>0,"VENCIDA",IF(EZ8>=-5,"POR VENCER","AL DÍA")))) | FE8: =IF(N($H8)<26,"",IF(EY8="","",EY8+31)) | FF8: =IF(FE8="","",TODAY()-FE8) | FI8: =IF(FE8="","SIN ESTADO",IF(FG8<>"","PAGA",IF(FF8>0,"VENCIDA",IF(FF8>=-5,"POR VENCER","AL DÍA")))) | FK8: =IF(N($H8)<27,"",IF(FE8="","",FE8+31)) | FL8: =IF(FK8="","",TODAY()-FK8) | FO8: =IF(FK8="","SIN ESTADO",IF(FM8<>"","PAGA",IF(FL8>0,"VENCIDA",IF(FL8>=-5,"POR VENCER","AL DÍA")))) | FQ8: =IF(N($H8)<28,"",IF(FK8="","",FK8+31)) | FR8: =IF(FQ8="","",TODAY()-FQ8) | FU8: =IF(FQ8="","SIN ESTADO",IF(FS8<>"","PAGA",IF(FR8>0,"VENCIDA",IF(FR8>=-5,"POR VENCER","AL DÍA")))) | FW8: =IF(N($H8)<29,"",IF(FQ8="","",FQ8+31)) | FX8: =IF(FW8="","",TODAY()-FW8) | GA8: =IF(FW8="","SIN ESTADO",IF(FY8<>"","PAGA",IF(FX8>0,"VENCIDA",IF(FX8>=-5,"POR VENCER","AL DÍA")))) | GC8: =IF(N($H8)<30,"",IF(FW8="","",FW8+31)) | GD8: =IF(GC8="","",TODAY()-GC8) | GG8: =IF(GC8="","SIN ESTADO",IF(GE8<>"","PAGA",IF(GD8>0,"VENCIDA",IF(GD8>=-5,"POR VENCER","AL DÍA")))) | GI8: =IF(N($H8)<31,"",IF(GC8="","",GC8+31)) | GJ8: =IF(GI8="","",TODAY()-GI8) | GM8: =IF(GI8="","SIN ESTADO",IF(GK8<>"","PAGA",IF(GJ8>0,"VENCIDA",IF(GJ8>=-5,"POR VENCER","AL DÍA")))) | GO8: =IF(N($H8)<32,"",IF(GI8="","",GI8+31)) | GP8: =IF(GO8="","",TODAY()-GO8) | GS8: =IF(GO8="","SIN ESTADO",IF(GQ8<>"","PAGA",IF(GP8>0,"VENCIDA",IF(GP8>=-5,"POR VENCER","AL DÍA")))) | GU8: =IF(N($H8)<33,"",IF(GO8="","",GO8+31)) | GV8: =IF(GU8="","",TODAY()-GU8) | GY8: =IF(GU8="","SIN ESTADO",IF(GW8<>"","PAGA",IF(GV8>0,"VENCIDA",IF(GV8>=-5,"POR VENCER","AL DÍA")))) | HA8: =IF(N($H8)<34,"",IF(GU8="","",GU8+31)) | HB8: =IF(HA8="","",TODAY()-HA8) | HE8: =IF(HA8="","SIN ESTADO",IF(HC8<>"","PAGA",IF(HB8>0,"VENCIDA",IF(HB8>=-5,"POR VENCER","AL DÍA")))) | HG8: =IF(N($H8)<35,"",IF(HA8="","",HA8+31)) | HH8: =IF(HG8="","",TODAY()-HG8) | HK8: =IF(HG8="","SIN ESTADO",IF(HI8<>"","PAGA",IF(HH8>0,"VENCIDA",IF(HH8>=-5,"POR VENCER","AL DÍA")))) | HM8: =IF(N($H8)<36,"",IF(HG8="","",HG8+31)) | HN8: =IF(HM8="","",TODAY()-HM8) | HQ8: =IF(HM8="","SIN ESTADO",IF(HO8<>"","PAGA",IF(HN8>0,"VENCIDA",IF(HN8>=-5,"POR VENCER","AL DÍA")))) | HS8: =N8+T8+Z8+AF8+AL8+AR8+AX8+BD8+BJ8+BP8+BV8+CB8+CH8+CN8+CT8+CZ8+DF8+DL8+DR8+DX8+ED8+EJ8+EP8+EV8+FB8+FH8+FN8+FT8+FZ8+GF8+GL8+GR8+GX8+HD8+HJ8+HP8 | HU8: =IFERROR(N($J8),0) | HW8: =SUMPRODUCT((MOD(COLUMN($M8:$HR8)-COLUMN($M8),6)=0)*ISNUMBER($M8:$HR8)*($M8:$HR8>=RESUMEN!$C$26)*($M8:$HR8<=RESUMEN!$C$27)*IFERROR(N($N8:$HS8),0)) | HX8: =SUMPRODUCT((MOD(COLUMN($M8:$HR8)-COLUMN($M8),6)=0)*ISNUMBER($M8:$HR8)*($M8:$HR8>=RESUMEN!$C$26)*($M8:$HR8<=RESUMEN!$C$27))
B9: =VENTAS!A8 | C9: =VENTAS!B8 | D9: =VENTAS!C8 | E9: =VENTAS!D8 | F9: =VENTAS!J8 | G9: =VENTAS!F8 | H9: =VENTAS!K8 | I9: =VENTAS!M8 | J9: =VENTAS!L8 | K9: =IF(N($H9)<1,"",$G9+31) | L9: =IF(K9="","",TODAY()-K9) | M9: 45880 | N9: 875000 | O9: =IF(K9="","SIN ESTADO",IF(M9<>"","PAGA",IF(L9>0,"VENCIDA",IF(L9>=-5,"POR VENCER","AL DÍA")))) | P9: TRANSFERENCIA | Q9: =IF(N($H9)<2,"",IF(K9="","",K9+31)) | R9: =IF(Q9="","",TODAY()-Q9) | S9: 45908 | T9: 875000 | U9: =IF(Q9="","SIN ESTADO",IF(S9<>"","PAGA",IF(R9>0,"VENCIDA",IF(R9>=-5,"POR VENCER","AL DÍA")))) | V9: TRANSFERENCIA | W9: =IF(N($H9)<3,"",IF(Q9="","",Q9+31)) | X9: =IF(W9="","",TODAY()-W9) | Y9: 45938 | Z9: 875000 | AA9: =IF(W9="","SIN ESTADO",IF(Y9<>"","PAGA",IF(X9>0,"VENCIDA",IF(X9>=-5,"POR VENCER","AL DÍA")))) | AB9: TRANSFERENCIA | AC9: =IF(N($H9)<4,"",IF(W9="","",W9+31)) | AD9: =IF(AC9="","",TODAY()-AC9) | AE9: 45972 | AF9: 875000 | AG9: =IF(AC9="","SIN ESTADO",IF(AE9<>"","PAGA",IF(AD9>0,"VENCIDA",IF(AD9>=-5,"POR VENCER","AL DÍA")))) | AH9: TRANSFERENCIA | AI9: =IF(N($H9)<5,"",IF(AC9="","",AC9+31)) | AJ9: =IF(AI9="","",TODAY()-AI9) | AK9: 46004 | AL9: 875000 | AM9: =IF(AI9="","SIN ESTADO",IF(AK9<>"","PAGA",IF(AJ9>0,"VENCIDA",IF(AJ9>=-5,"POR VENCER","AL DÍA")))) | AN9: TRANSFERENCIA | AO9: =IF(N($H9)<6,"",IF(AI9="","",AI9+31)) | AP9: =IF(AO9="","",TODAY()-AO9) | AQ9: 46063 | AR9: 875000 | AS9: =IF(AO9="","SIN ESTADO",IF(AQ9<>"","PAGA",IF(AP9>0,"VENCIDA",IF(AP9>=-5,"POR VENCER","AL DÍA")))) | AT9: TRANSFERENCIA | AU9: =IF(N($H9)<7,"",IF(AO9="","",AO9+31)) | AV9: =IF(AU9="","",TODAY()-AU9) | AW9: 46063 | AX9: 875000 | AY9: =IF(AU9="","SIN ESTADO",IF(AW9<>"","PAGA",IF(AV9>0,"VENCIDA",IF(AV9>=-5,"POR VENCER","AL DÍA")))) | AZ9: TRANSFERENCIA | BA9: =IF(N($H9)<8,"",IF(AU9="","",AU9+31)) | BB9: =IF(BA9="","",TODAY()-BA9) | BC9: 46091 | BD9: 875000 | BE9: =IF(BA9="","SIN ESTADO",IF(BC9<>"","PAGA",IF(BB9>0,"VENCIDA",IF(BB9>=-5,"POR VENCER","AL DÍA")))) | BF9: TRANSFERENCIA | BG9: =IF(N($H9)<9,"",IF(BA9="","",BA9+31)) | BH9: =IF(BG9="","",TODAY()-BG9) | BI9: 46123 | BJ9: 875000 | BK9: =IF(BG9="","SIN ESTADO",IF(BI9<>"","PAGA",IF(BH9>0,"VENCIDA",IF(BH9>=-5,"POR VENCER","AL DÍA")))) | BL9: TRANSFERENCIA | BM9: =IF(N($H9)<10,"",IF(BG9="","",BG9+31)) | BN9: =IF(BM9="","",TODAY()-BM9) | BO9: 46150 | BP9: 875000 | BQ9: =IF(BM9="","SIN ESTADO",IF(BO9<>"","PAGA",IF(BN9>0,"VENCIDA",IF(BN9>=-5,"POR VENCER","AL DÍA")))) | BR9: TRANSFERENCIA | BS9: =IF(N($H9)<11,"",IF(BM9="","",BM9+31)) | BT9: =IF(BS9="","",TODAY()-BS9) | BU9: 46183 | BV9: 875000 | BW9: =IF(BS9="","SIN ESTADO",IF(BU9<>"","PAGA",IF(BT9>0,"VENCIDA",IF(BT9>=-5,"POR VENCER","AL DÍA")))) | BX9: TRANSFERENCIA | BY9: =IF(N($H9)<12,"",IF(BS9="","",BS9+31)) | BZ9: =IF(BY9="","",TODAY()-BY9) | CA9: 46214 | CB9: 875000 | CC9: =IF(BY9="","SIN ESTADO",IF(CA9<>"","PAGA",IF(BZ9>0,"VENCIDA",IF(BZ9>=-5,"POR VENCER","AL DÍA")))) | CD9: TRANSFERENCIA | CE9: =IF(N($H9)<13,"",IF(BY9="","",BY9+31)) | CF9: =IF(CE9="","",TODAY()-CE9) | CG9: 46244 | CH9: 875000 | CI9: =IF(CE9="","SIN ESTADO",IF(CG9<>"","PAGA",IF(CF9>0,"VENCIDA",IF(CF9>=-5,"POR VENCER","AL DÍA")))) | CJ9: TRANSFERENCIA | CK9: =IF(N($H9)<14,"",IF(CE9="","",CE9+31)) | CL9: =IF(CK9="","",TODAY()-CK9) | CM9: 46279 | CN9: 875000 | CO9: =IF(CK9="","SIN ESTADO",IF(CM9<>"","PAGA",IF(CL9>0,"VENCIDA",IF(CL9>=-5,"POR VENCER","AL DÍA")))) | CP9: TRANSFERENCIA | CQ9: =IF(N($H9)<15,"",IF(CK9="","",CK9+31)) | CR9: =IF(CQ9="","",TODAY()-CQ9) | CU9: =IF(CQ9="","SIN ESTADO",IF(CS9<>"","PAGA",IF(CR9>0,"VENCIDA",IF(CR9>=-5,"POR VENCER","AL DÍA")))) | CW9: =IF(N($H9)<16,"",IF(CQ9="","",CQ9+31)) | CX9: =IF(CW9="","",TODAY()-CW9) | DA9: =IF(CW9="","SIN ESTADO",IF(CY9<>"","PAGA",IF(CX9>0,"VENCIDA",IF(CX9>=-5,"POR VENCER","AL DÍA")))) | DC9: =IF(N($H9)<17,"",IF(CW9="","",CW9+31)) | DD9: =IF(DC9="","",TODAY()-DC9) | DG9: =IF(DC9="","SIN ESTADO",IF(DE9<>"","PAGA",IF(DD9>0,"VENCIDA",IF(DD9>=-5,"POR VENCER","AL DÍA")))) | DI9: =IF(N($H9)<18,"",IF(DC9="","",DC9+31)) | DJ9: =IF(DI9="","",TODAY()-DI9) | DM9: =IF(DI9="","SIN ESTADO",IF(DK9<>"","PAGA",IF(DJ9>0,"VENCIDA",IF(DJ9>=-5,"POR VENCER","AL DÍA")))) | DO9: =IF(N($H9)<19,"",IF(DI9="","",DI9+31)) | DP9: =IF(DO9="","",TODAY()-DO9) | DS9: =IF(DO9="","SIN ESTADO",IF(DQ9<>"","PAGA",IF(DP9>0,"VENCIDA",IF(DP9>=-5,"POR VENCER","AL DÍA")))) | DU9: =IF(N($H9)<20,"",IF(DO9="","",DO9+31)) | DV9: =IF(DU9="","",TODAY()-DU9) | DY9: =IF(DU9="","SIN ESTADO",IF(DW9<>"","PAGA",IF(DV9>0,"VENCIDA",IF(DV9>=-5,"POR VENCER","AL DÍA")))) | EA9: =IF(N($H9)<21,"",IF(DU9="","",DU9+31)) | EB9: =IF(EA9="","",TODAY()-EA9) | EE9: =IF(EA9="","SIN ESTADO",IF(EC9<>"","PAGA",IF(EB9>0,"VENCIDA",IF(EB9>=-5,"POR VENCER","AL DÍA")))) | EG9: =IF(N($H9)<22,"",IF(EA9="","",EA9+31)) | EH9: =IF(EG9="","",TODAY()-EG9) | EK9: =IF(EG9="","SIN ESTADO",IF(EI9<>"","PAGA",IF(EH9>0,"VENCIDA",IF(EH9>=-5,"POR VENCER","AL DÍA")))) | EM9: =IF(N($H9)<23,"",IF(EG9="","",EG9+31)) | EN9: =IF(EM9="","",TODAY()-EM9) | EQ9: =IF(EM9="","SIN ESTADO",IF(EO9<>"","PAGA",IF(EN9>0,"VENCIDA",IF(EN9>=-5,"POR VENCER","AL DÍA")))) | ES9: =IF(N($H9)<24,"",IF(EM9="","",EM9+31)) | ET9: =IF(ES9="","",TODAY()-ES9) | EW9: =IF(ES9="","SIN ESTADO",IF(EU9<>"","PAGA",IF(ET9>0,"VENCIDA",IF(ET9>=-5,"POR VENCER","AL DÍA")))) | EY9: =IF(N($H9)<25,"",IF(ES9="","",ES9+31)) | EZ9: =IF(EY9="","",TODAY()-EY9) | FC9: =IF(EY9="","SIN ESTADO",IF(FA9<>"","PAGA",IF(EZ9>0,"VENCIDA",IF(EZ9>=-5,"POR VENCER","AL DÍA")))) | FE9: =IF(N($H9)<26,"",IF(EY9="","",EY9+31)) | FF9: =IF(FE9="","",TODAY()-FE9) | FI9: =IF(FE9="","SIN ESTADO",IF(FG9<>"","PAGA",IF(FF9>0,"VENCIDA",IF(FF9>=-5,"POR VENCER","AL DÍA")))) | FK9: =IF(N($H9)<27,"",IF(FE9="","",FE9+31)) | FL9: =IF(FK9="","",TODAY()-FK9) | FO9: =IF(FK9="","SIN ESTADO",IF(FM9<>"","PAGA",IF(FL9>0,"VENCIDA",IF(FL9>=-5,"POR VENCER","AL DÍA")))) | FQ9: =IF(N($H9)<28,"",IF(FK9="","",FK9+31)) | FR9: =IF(FQ9="","",TODAY()-FQ9) | FU9: =IF(FQ9="","SIN ESTADO",IF(FS9<>"","PAGA",IF(FR9>0,"VENCIDA",IF(FR9>=-5,"POR VENCER","AL DÍA")))) | FW9: =IF(N($H9)<29,"",IF(FQ9="","",FQ9+31)) | FX9: =IF(FW9="","",TODAY()-FW9) | GA9: =IF(FW9="","SIN ESTADO",IF(FY9<>"","PAGA",IF(FX9>0,"VENCIDA",IF(FX9>=-5,"POR VENCER","AL DÍA")))) | GC9: =IF(N($H9)<30,"",IF(FW9="","",FW9+31)) | GD9: =IF(GC9="","",TODAY()-GC9) | GG9: =IF(GC9="","SIN ESTADO",IF(GE9<>"","PAGA",IF(GD9>0,"VENCIDA",IF(GD9>=-5,"POR VENCER","AL DÍA")))) | GI9: =IF(N($H9)<31,"",IF(GC9="","",GC9+31)) | GJ9: =IF(GI9="","",TODAY()-GI9) | GM9: =IF(GI9="","SIN ESTADO",IF(GK9<>"","PAGA",IF(GJ9>0,"VENCIDA",IF(GJ9>=-5,"POR VENCER","AL DÍA")))) | GO9: =IF(N($H9)<32,"",IF(GI9="","",GI9+31)) | GP9: =IF(GO9="","",TODAY()-GO9) | GS9: =IF(GO9="","SIN ESTADO",IF(GQ9<>"","PAGA",IF(GP9>0,"VENCIDA",IF(GP9>=-5,"POR VENCER","AL DÍA")))) | GU9: =IF(N($H9)<33,"",IF(GO9="","",GO9+31)) | GV9: =IF(GU9="","",TODAY()-GU9) | GY9: =IF(GU9="","SIN ESTADO",IF(GW9<>"","PAGA",IF(GV9>0,"VENCIDA",IF(GV9>=-5,"POR VENCER","AL DÍA")))) | HA9: =IF(N($H9)<34,"",IF(GU9="","",GU9+31)) | HB9: =IF(HA9="","",TODAY()-HA9) | HE9: =IF(HA9="","SIN ESTADO",IF(HC9<>"","PAGA",IF(HB9>0,"VENCIDA",IF(HB9>=-5,"POR VENCER","AL DÍA")))) | HG9: =IF(N($H9)<35,"",IF(HA9="","",HA9+31)) | HH9: =IF(HG9="","",TODAY()-HG9) | HK9: =IF(HG9="","SIN ESTADO",IF(HI9<>"","PAGA",IF(HH9>0,"VENCIDA",IF(HH9>=-5,"POR VENCER","AL DÍA")))) | HM9: =IF(N($H9)<36,"",IF(HG9="","",HG9+31)) | HN9: =IF(HM9="","",TODAY()-HM9) | HQ9: =IF(HM9="","SIN ESTADO",IF(HO9<>"","PAGA",IF(HN9>0,"VENCIDA",IF(HN9>=-5,"POR VENCER","AL DÍA")))) | HS9: =N9+T9+Z9+AF9+AL9+AR9+AX9+BD9+BJ9+BP9+BV9+CB9+CH9+CN9+CT9+CZ9+DF9+DL9+DR9+DX9+ED9+EJ9+EP9+EV9+FB9+FH9+FN9+FT9+FZ9+GF9+GL9+GR9+GX9+HD9+HJ9+HP9 | HU9: =IFERROR(N($J9),0) | HW9: =SUMPRODUCT((MOD(COLUMN($M9:$HR9)-COLUMN($M9),6)=0)*ISNUMBER($M9:$HR9)*($M9:$HR9>=RESUMEN!$C$26)*($M9:$HR9<=RESUMEN!$C$27)*IFERROR(N($N9:$HS9),0)) | HX9: =SUMPRODUCT((MOD(COLUMN($M9:$HR9)-COLUMN($M9),6)=0)*ISNUMBER($M9:$HR9)*($M9:$HR9>=RESUMEN!$C$26)*($M9:$HR9<=RESUMEN!$C$27))
B10: =VENTAS!A9 | C10: =VENTAS!B9 | D10: =VENTAS!C9 | E10: =VENTAS!D9 | F10: =VENTAS!J9 | G10: =VENTAS!F9 | H10: =VENTAS!K9 | I10: =VENTAS!M9 | J10: =VENTAS!L9 | K10: =IF(N($H10)<1,"",$G10+31) | L10: =IF(K10="","",TODAY()-K10) | O10: =IF(K10="","SIN ESTADO",IF(M10<>"","PAGA",IF(L10>0,"VENCIDA",IF(L10>=-5,"POR VENCER","AL DÍA")))) | Q10: =IF(N($H10)<2,"",IF(K10="","",K10+31)) | R10: =IF(Q10="","",TODAY()-Q10) | U10: =IF(Q10="","SIN ESTADO",IF(S10<>"","PAGA",IF(R10>0,"VENCIDA",IF(R10>=-5,"POR VENCER","AL DÍA")))) | W10: =IF(N($H10)<3,"",IF(Q10="","",Q10+31)) | X10: =IF(W10="","",TODAY()-W10) | AA10: =IF(W10="","SIN ESTADO",IF(Y10<>"","PAGA",IF(X10>0,"VENCIDA",IF(X10>=-5,"POR VENCER","AL DÍA")))) | AC10: =IF(N($H10)<4,"",IF(W10="","",W10+31)) | AD10: =IF(AC10="","",TODAY()-AC10) | AG10: =IF(AC10="","SIN ESTADO",IF(AE10<>"","PAGA",IF(AD10>0,"VENCIDA",IF(AD10>=-5,"POR VENCER","AL DÍA")))) | AI10: =IF(N($H10)<5,"",IF(AC10="","",AC10+31)) | AJ10: =IF(AI10="","",TODAY()-AI10) | AM10: =IF(AI10="","SIN ESTADO",IF(AK10<>"","PAGA",IF(AJ10>0,"VENCIDA",IF(AJ10>=-5,"POR VENCER","AL DÍA")))) | AO10: =IF(N($H10)<6,"",IF(AI10="","",AI10+31)) | AP10: =IF(AO10="","",TODAY()-AO10) | AS10: =IF(AO10="","SIN ESTADO",IF(AQ10<>"","PAGA",IF(AP10>0,"VENCIDA",IF(AP10>=-5,"POR VENCER","AL DÍA")))) | AU10: =IF(N($H10)<7,"",IF(AO10="","",AO10+31)) | AV10: =IF(AU10="","",TODAY()-AU10) | AY10: =IF(AU10="","SIN ESTADO",IF(AW10<>"","PAGA",IF(AV10>0,"VENCIDA",IF(AV10>=-5,"POR VENCER","AL DÍA")))) | BA10: =IF(N($H10)<8,"",IF(AU10="","",AU10+31)) | BB10: =IF(BA10="","",TODAY()-BA10) | BE10: =IF(BA10="","SIN ESTADO",IF(BC10<>"","PAGA",IF(BB10>0,"VENCIDA",IF(BB10>=-5,"POR VENCER","AL DÍA")))) | BG10: =IF(N($H10)<9,"",IF(BA10="","",BA10+31)) | BH10: =IF(BG10="","",TODAY()-BG10) | BK10: =IF(BG10="","SIN ESTADO",IF(BI10<>"","PAGA",IF(BH10>0,"VENCIDA",IF(BH10>=-5,"POR VENCER","AL DÍA")))) | BM10: =IF(N($H10)<10,"",IF(BG10="","",BG10+31)) | BN10: =IF(BM10="","",TODAY()-BM10) | BQ10: =IF(BM10="","SIN ESTADO",IF(BO10<>"","PAGA",IF(BN10>0,"VENCIDA",IF(BN10>=-5,"POR VENCER","AL DÍA")))) | BS10: =IF(N($H10)<11,"",IF(BM10="","",BM10+31)) | BT10: =IF(BS10="","",TODAY()-BS10) | BW10: =IF(BS10="","SIN ESTADO",IF(BU10<>"","PAGA",IF(BT10>0,"VENCIDA",IF(BT10>=-5,"POR VENCER","AL DÍA")))) | BY10: =IF(N($H10)<12,"",IF(BS10="","",BS10+31)) | BZ10: =IF(BY10="","",TODAY()-BY10) | CC10: =IF(BY10="","SIN ESTADO",IF(CA10<>"","PAGA",IF(BZ10>0,"VENCIDA",IF(BZ10>=-5,"POR VENCER","AL DÍA")))) | CE10: =IF(N($H10)<13,"",IF(BY10="","",BY10+31)) | CF10: =IF(CE10="","",TODAY()-CE10) | CI10: =IF(CE10="","SIN ESTADO",IF(CG10<>"","PAGA",IF(CF10>0,"VENCIDA",IF(CF10>=-5,"POR VENCER","AL DÍA")))) | CK10: =IF(N($H10)<14,"",IF(CE10="","",CE10+31)) | CL10: =IF(CK10="","",TODAY()-CK10) | CO10: =IF(CK10="","SIN ESTADO",IF(CM10<>"","PAGA",IF(CL10>0,"VENCIDA",IF(CL10>=-5,"POR VENCER","AL DÍA")))) | CQ10: =IF(N($H10)<15,"",IF(CK10="","",CK10+31)) | CR10: =IF(CQ10="","",TODAY()-CQ10) | CU10: =IF(CQ10="","SIN ESTADO",IF(CS10<>"","PAGA",IF(CR10>0,"VENCIDA",IF(CR10>=-5,"POR VENCER","AL DÍA")))) | CW10: =IF(N($H10)<16,"",IF(CQ10="","",CQ10+31)) | CX10: =IF(CW10="","",TODAY()-CW10) | DA10: =IF(CW10="","SIN ESTADO",IF(CY10<>"","PAGA",IF(CX10>0,"VENCIDA",IF(CX10>=-5,"POR VENCER","AL DÍA")))) | DC10: =IF(N($H10)<17,"",IF(CW10="","",CW10+31)) | DD10: =IF(DC10="","",TODAY()-DC10) | DG10: =IF(DC10="","SIN ESTADO",IF(DE10<>"","PAGA",IF(DD10>0,"VENCIDA",IF(DD10>=-5,"POR VENCER","AL DÍA")))) | DI10: =IF(N($H10)<18,"",IF(DC10="","",DC10+31)) | DJ10: =IF(DI10="","",TODAY()-DI10) | DM10: =IF(DI10="","SIN ESTADO",IF(DK10<>"","PAGA",IF(DJ10>0,"VENCIDA",IF(DJ10>=-5,"POR VENCER","AL DÍA")))) | DO10: =IF(N($H10)<19,"",IF(DI10="","",DI10+31)) | DP10: =IF(DO10="","",TODAY()-DO10) | DS10: =IF(DO10="","SIN ESTADO",IF(DQ10<>"","PAGA",IF(DP10>0,"VENCIDA",IF(DP10>=-5,"POR VENCER","AL DÍA")))) | DU10: =IF(N($H10)<20,"",IF(DO10="","",DO10+31)) | DV10: =IF(DU10="","",TODAY()-DU10) | DY10: =IF(DU10="","SIN ESTADO",IF(DW10<>"","PAGA",IF(DV10>0,"VENCIDA",IF(DV10>=-5,"POR VENCER","AL DÍA")))) | EA10: =IF(N($H10)<21,"",IF(DU10="","",DU10+31)) | EB10: =IF(EA10="","",TODAY()-EA10) | EE10: =IF(EA10="","SIN ESTADO",IF(EC10<>"","PAGA",IF(EB10>0,"VENCIDA",IF(EB10>=-5,"POR VENCER","AL DÍA")))) | EG10: =IF(N($H10)<22,"",IF(EA10="","",EA10+31)) | EH10: =IF(EG10="","",TODAY()-EG10) | EK10: =IF(EG10="","SIN ESTADO",IF(EI10<>"","PAGA",IF(EH10>0,"VENCIDA",IF(EH10>=-5,"POR VENCER","AL DÍA")))) | EM10: =IF(N($H10)<23,"",IF(EG10="","",EG10+31)) | EN10: =IF(EM10="","",TODAY()-EM10) | EQ10: =IF(EM10="","SIN ESTADO",IF(EO10<>"","PAGA",IF(EN10>0,"VENCIDA",IF(EN10>=-5,"POR VENCER","AL DÍA")))) | ES10: =IF(N($H10)<24,"",IF(EM10="","",EM10+31)) | ET10: =IF(ES10="","",TODAY()-ES10) | EW10: =IF(ES10="","SIN ESTADO",IF(EU10<>"","PAGA",IF(ET10>0,"VENCIDA",IF(ET10>=-5,"POR VENCER","AL DÍA")))) | EY10: =IF(N($H10)<25,"",IF(ES10="","",ES10+31)) | EZ10: =IF(EY10="","",TODAY()-EY10) | FC10: =IF(EY10="","SIN ESTADO",IF(FA10<>"","PAGA",IF(EZ10>0,"VENCIDA",IF(EZ10>=-5,"POR VENCER","AL DÍA")))) | FE10: =IF(N($H10)<26,"",IF(EY10="","",EY10+31)) | FF10: =IF(FE10="","",TODAY()-FE10) | FI10: =IF(FE10="","SIN ESTADO",IF(FG10<>"","PAGA",IF(FF10>0,"VENCIDA",IF(FF10>=-5,"POR VENCER","AL DÍA")))) | FK10: =IF(N($H10)<27,"",IF(FE10="","",FE10+31)) | FL10: =IF(FK10="","",TODAY()-FK10) | FO10: =IF(FK10="","SIN ESTADO",IF(FM10<>"","PAGA",IF(FL10>0,"VENCIDA",IF(FL10>=-5,"POR VENCER","AL DÍA")))) | FQ10: =IF(N($H10)<28,"",IF(FK10="","",FK10+31)) | FR10: =IF(FQ10="","",TODAY()-FQ10) | FU10: =IF(FQ10="","SIN ESTADO",IF(FS10<>"","PAGA",IF(FR10>0,"VENCIDA",IF(FR10>=-5,"POR VENCER","AL DÍA")))) | FW10: =IF(N($H10)<29,"",IF(FQ10="","",FQ10+31)) | FX10: =IF(FW10="","",TODAY()-FW10) | GA10: =IF(FW10="","SIN ESTADO",IF(FY10<>"","PAGA",IF(FX10>0,"VENCIDA",IF(FX10>=-5,"POR VENCER","AL DÍA")))) | GC10: =IF(N($H10)<30,"",IF(FW10="","",FW10+31)) | GD10: =IF(GC10="","",TODAY()-GC10) | GG10: =IF(GC10="","SIN ESTADO",IF(GE10<>"","PAGA",IF(GD10>0,"VENCIDA",IF(GD10>=-5,"POR VENCER","AL DÍA")))) | GI10: =IF(N($H10)<31,"",IF(GC10="","",GC10+31)) | GJ10: =IF(GI10="","",TODAY()-GI10) | GM10: =IF(GI10="","SIN ESTADO",IF(GK10<>"","PAGA",IF(GJ10>0,"VENCIDA",IF(GJ10>=-5,"POR VENCER","AL DÍA")))) | GO10: =IF(N($H10)<32,"",IF(GI10="","",GI10+31)) | GP10: =IF(GO10="","",TODAY()-GO10) | GS10: =IF(GO10="","SIN ESTADO",IF(GQ10<>"","PAGA",IF(GP10>0,"VENCIDA",IF(GP10>=-5,"POR VENCER","AL DÍA")))) | GU10: =IF(N($H10)<33,"",IF(GO10="","",GO10+31)) | GV10: =IF(GU10="","",TODAY()-GU10) | GY10: =IF(GU10="","SIN ESTADO",IF(GW10<>"","PAGA",IF(GV10>0,"VENCIDA",IF(GV10>=-5,"POR VENCER","AL DÍA")))) | HA10: =IF(N($H10)<34,"",IF(GU10="","",GU10+31)) | HB10: =IF(HA10="","",TODAY()-HA10) | HE10: =IF(HA10="","SIN ESTADO",IF(HC10<>"","PAGA",IF(HB10>0,"VENCIDA",IF(HB10>=-5,"POR VENCER","AL DÍA")))) | HG10: =IF(N($H10)<35,"",IF(HA10="","",HA10+31)) | HH10: =IF(HG10="","",TODAY()-HG10) | HK10: =IF(HG10="","SIN ESTADO",IF(HI10<>"","PAGA",IF(HH10>0,"VENCIDA",IF(HH10>=-5,"POR VENCER","AL DÍA")))) | HM10: =IF(N($H10)<36,"",IF(HG10="","",HG10+31)) | HN10: =IF(HM10="","",TODAY()-HM10) | HQ10: =IF(HM10="","SIN ESTADO",IF(HO10<>"","PAGA",IF(HN10>0,"VENCIDA",IF(HN10>=-5,"POR VENCER","AL DÍA")))) | HS10: =N10+T10+Z10+AF10+AL10+AR10+AX10+BD10+BJ10+BP10+BV10+CB10+CH10+CN10+CT10+CZ10+DF10+DL10+DR10+DX10+ED10+EJ10+EP10+EV10+FB10+FH10+FN10+FT10+FZ10+GF10+GL10+GR10+GX10+HD10+HJ10+HP10 | HU10: =IFERROR(N($J10),0) | HW10: =SUMPRODUCT((MOD(COLUMN($M10:$HR10)-COLUMN($M10),6)=0)*ISNUMBER($M10:$HR10)*($M10:$HR10>=RESUMEN!$C$26)*($M10:$HR10<=RESUMEN!$C$27)*IFERROR(N($N10:$HS10),0)) | HX10: =SUMPRODUCT((MOD(COLUMN($M10:$HR10)-COLUMN($M10),6)=0)*ISNUMBER($M10:$HR10)*($M10:$HR10>=RESUMEN!$C$26)*($M10:$HR10<=RESUMEN!$C$27))
B11: =VENTAS!A10 | C11: =VENTAS!B10 | D11: =VENTAS!C10 | E11: =VENTAS!D10 | F11: =VENTAS!J10 | G11: =VENTAS!F10 | H11: =VENTAS!K10 | I11: =VENTAS!M10 | J11: =VENTAS!L10 | K11: =IF(N($H11)<1,"",$G11+31) | L11: =IF(K11="","",TODAY()-K11) | O11: =IF(K11="","SIN ESTADO",IF(M11<>"","PAGA",IF(L11>0,"VENCIDA",IF(L11>=-5,"POR VENCER","AL DÍA")))) | Q11: =IF(N($H11)<2,"",IF(K11="","",K11+31)) | R11: =IF(Q11="","",TODAY()-Q11) | U11: =IF(Q11="","SIN ESTADO",IF(S11<>"","PAGA",IF(R11>0,"VENCIDA",IF(R11>=-5,"POR VENCER","AL DÍA")))) | W11: =IF(N($H11)<3,"",IF(Q11="","",Q11+31)) | X11: =IF(W11="","",TODAY()-W11) | AA11: =IF(W11="","SIN ESTADO",IF(Y11<>"","PAGA",IF(X11>0,"VENCIDA",IF(X11>=-5,"POR VENCER","AL DÍA")))) | AC11: =IF(N($H11)<4,"",IF(W11="","",W11+31)) | AD11: =IF(AC11="","",TODAY()-AC11) | AG11: =IF(AC11="","SIN ESTADO",IF(AE11<>"","PAGA",IF(AD11>0,"VENCIDA",IF(AD11>=-5,"POR VENCER","AL DÍA")))) | AI11: =IF(N($H11)<5,"",IF(AC11="","",AC11+31)) | AJ11: =IF(AI11="","",TODAY()-AI11) | AM11: =IF(AI11="","SIN ESTADO",IF(AK11<>"","PAGA",IF(AJ11>0,"VENCIDA",IF(AJ11>=-5,"POR VENCER","AL DÍA")))) | AO11: =IF(N($H11)<6,"",IF(AI11="","",AI11+31)) | AP11: =IF(AO11="","",TODAY()-AO11) | AS11: =IF(AO11="","SIN ESTADO",IF(AQ11<>"","PAGA",IF(AP11>0,"VENCIDA",IF(AP11>=-5,"POR VENCER","AL DÍA")))) | AU11: =IF(N($H11)<7,"",IF(AO11="","",AO11+31)) | AV11: =IF(AU11="","",TODAY()-AU11) | AY11: =IF(AU11="","SIN ESTADO",IF(AW11<>"","PAGA",IF(AV11>0,"VENCIDA",IF(AV11>=-5,"POR VENCER","AL DÍA")))) | BA11: =IF(N($H11)<8,"",IF(AU11="","",AU11+31)) | BB11: =IF(BA11="","",TODAY()-BA11) | BE11: =IF(BA11="","SIN ESTADO",IF(BC11<>"","PAGA",IF(BB11>0,"VENCIDA",IF(BB11>=-5,"POR VENCER","AL DÍA")))) | BG11: =IF(N($H11)<9,"",IF(BA11="","",BA11+31)) | BH11: =IF(BG11="","",TODAY()-BG11) | BK11: =IF(BG11="","SIN ESTADO",IF(BI11<>"","PAGA",IF(BH11>0,"VENCIDA",IF(BH11>=-5,"POR VENCER","AL DÍA")))) | BM11: =IF(N($H11)<10,"",IF(BG11="","",BG11+31)) | BN11: =IF(BM11="","",TODAY()-BM11) | BQ11: =IF(BM11="","SIN ESTADO",IF(BO11<>"","PAGA",IF(BN11>0,"VENCIDA",IF(BN11>=-5,"POR VENCER","AL DÍA")))) | BS11: =IF(N($H11)<11,"",IF(BM11="","",BM11+31)) | BT11: =IF(BS11="","",TODAY()-BS11) | BW11: =IF(BS11="","SIN ESTADO",IF(BU11<>"","PAGA",IF(BT11>0,"VENCIDA",IF(BT11>=-5,"POR VENCER","AL DÍA")))) | BY11: =IF(N($H11)<12,"",IF(BS11="","",BS11+31)) | BZ11: =IF(BY11="","",TODAY()-BY11) | CC11: =IF(BY11="","SIN ESTADO",IF(CA11<>"","PAGA",IF(BZ11>0,"VENCIDA",IF(BZ11>=-5,"POR VENCER","AL DÍA")))) | CE11: =IF(N($H11)<13,"",IF(BY11="","",BY11+31)) | CF11: =IF(CE11="","",TODAY()-CE11) | CI11: =IF(CE11="","SIN ESTADO",IF(CG11<>"","PAGA",IF(CF11>0,"VENCIDA",IF(CF11>=-5,"POR VENCER","AL DÍA")))) | CK11: =IF(N($H11)<14,"",IF(CE11="","",CE11+31)) | CL11: =IF(CK11="","",TODAY()-CK11) | CO11: =IF(CK11="","SIN ESTADO",IF(CM11<>"","PAGA",IF(CL11>0,"VENCIDA",IF(CL11>=-5,"POR VENCER","AL DÍA")))) | CQ11: =IF(N($H11)<15,"",IF(CK11="","",CK11+31)) | CR11: =IF(CQ11="","",TODAY()-CQ11) | CU11: =IF(CQ11="","SIN ESTADO",IF(CS11<>"","PAGA",IF(CR11>0,"VENCIDA",IF(CR11>=-5,"POR VENCER","AL DÍA")))) | CW11: =IF(N($H11)<16,"",IF(CQ11="","",CQ11+31)) | CX11: =IF(CW11="","",TODAY()-CW11) | DA11: =IF(CW11="","SIN ESTADO",IF(CY11<>"","PAGA",IF(CX11>0,"VENCIDA",IF(CX11>=-5,"POR VENCER","AL DÍA")))) | DC11: =IF(N($H11)<17,"",IF(CW11="","",CW11+31)) | DD11: =IF(DC11="","",TODAY()-DC11) | DG11: =IF(DC11="","SIN ESTADO",IF(DE11<>"","PAGA",IF(DD11>0,"VENCIDA",IF(DD11>=-5,"POR VENCER","AL DÍA")))) | DI11: =IF(N($H11)<18,"",IF(DC11="","",DC11+31)) | DJ11: =IF(DI11="","",TODAY()-DI11) | DM11: =IF(DI11="","SIN ESTADO",IF(DK11<>"","PAGA",IF(DJ11>0,"VENCIDA",IF(DJ11>=-5,"POR VENCER","AL DÍA")))) | DO11: =IF(N($H11)<19,"",IF(DI11="","",DI11+31)) | DP11: =IF(DO11="","",TODAY()-DO11) | DS11: =IF(DO11="","SIN ESTADO",IF(DQ11<>"","PAGA",IF(DP11>0,"VENCIDA",IF(DP11>=-5,"POR VENCER","AL DÍA")))) | DU11: =IF(N($H11)<20,"",IF(DO11="","",DO11+31)) | DV11: =IF(DU11="","",TODAY()-DU11) | DY11: =IF(DU11="","SIN ESTADO",IF(DW11<>"","PAGA",IF(DV11>0,"VENCIDA",IF(DV11>=-5,"POR VENCER","AL DÍA")))) | EA11: =IF(N($H11)<21,"",IF(DU11="","",DU11+31)) | EB11: =IF(EA11="","",TODAY()-EA11) | EE11: =IF(EA11="","SIN ESTADO",IF(EC11<>"","PAGA",IF(EB11>0,"VENCIDA",IF(EB11>=-5,"POR VENCER","AL DÍA")))) | EG11: =IF(N($H11)<22,"",IF(EA11="","",EA11+31)) | EH11: =IF(EG11="","",TODAY()-EG11) | EK11: =IF(EG11="","SIN ESTADO",IF(EI11<>"","PAGA",IF(EH11>0,"VENCIDA",IF(EH11>=-5,"POR VENCER","AL DÍA")))) | EM11: =IF(N($H11)<23,"",IF(EG11="","",EG11+31)) | EN11: =IF(EM11="","",TODAY()-EM11) | EQ11: =IF(EM11="","SIN ESTADO",IF(EO11<>"","PAGA",IF(EN11>0,"VENCIDA",IF(EN11>=-5,"POR VENCER","AL DÍA")))) | ES11: =IF(N($H11)<24,"",IF(EM11="","",EM11+31)) | ET11: =IF(ES11="","",TODAY()-ES11) | EW11: =IF(ES11="","SIN ESTADO",IF(EU11<>"","PAGA",IF(ET11>0,"VENCIDA",IF(ET11>=-5,"POR VENCER","AL DÍA")))) | EY11: =IF(N($H11)<25,"",IF(ES11="","",ES11+31)) | EZ11: =IF(EY11="","",TODAY()-EY11) | FC11: =IF(EY11="","SIN ESTADO",IF(FA11<>"","PAGA",IF(EZ11>0,"VENCIDA",IF(EZ11>=-5,"POR VENCER","AL DÍA")))) | FE11: =IF(N($H11)<26,"",IF(EY11="","",EY11+31)) | FF11: =IF(FE11="","",TODAY()-FE11) | FI11: =IF(FE11="","SIN ESTADO",IF(FG11<>"","PAGA",IF(FF11>0,"VENCIDA",IF(FF11>=-5,"POR VENCER","AL DÍA")))) | FK11: =IF(N($H11)<27,"",IF(FE11="","",FE11+31)) | FL11: =IF(FK11="","",TODAY()-FK11) | FO11: =IF(FK11="","SIN ESTADO",IF(FM11<>"","PAGA",IF(FL11>0,"VENCIDA",IF(FL11>=-5,"POR VENCER","AL DÍA")))) | FQ11: =IF(N($H11)<28,"",IF(FK11="","",FK11+31)) | FR11: =IF(FQ11="","",TODAY()-FQ11) | FU11: =IF(FQ11="","SIN ESTADO",IF(FS11<>"","PAGA",IF(FR11>0,"VENCIDA",IF(FR11>=-5,"POR VENCER","AL DÍA")))) | FW11: =IF(N($H11)<29,"",IF(FQ11="","",FQ11+31)) | FX11: =IF(FW11="","",TODAY()-FW11) | GA11: =IF(FW11="","SIN ESTADO",IF(FY11<>"","PAGA",IF(FX11>0,"VENCIDA",IF(FX11>=-5,"POR VENCER","AL DÍA")))) | GC11: =IF(N($H11)<30,"",IF(FW11="","",FW11+31)) | GD11: =IF(GC11="","",TODAY()-GC11) | GG11: =IF(GC11="","SIN ESTADO",IF(GE11<>"","PAGA",IF(GD11>0,"VENCIDA",IF(GD11>=-5,"POR VENCER","AL DÍA")))) | GI11: =IF(N($H11)<31,"",IF(GC11="","",GC11+31)) | GJ11: =IF(GI11="","",TODAY()-GI11) | GM11: =IF(GI11="","SIN ESTADO",IF(GK11<>"","PAGA",IF(GJ11>0,"VENCIDA",IF(GJ11>=-5,"POR VENCER","AL DÍA")))) | GO11: =IF(N($H11)<32,"",IF(GI11="","",GI11+31)) | GP11: =IF(GO11="","",TODAY()-GO11) | GS11: =IF(GO11="","SIN ESTADO",IF(GQ11<>"","PAGA",IF(GP11>0,"VENCIDA",IF(GP11>=-5,"POR VENCER","AL DÍA")))) | GU11: =IF(N($H11)<33,"",IF(GO11="","",GO11+31)) | GV11: =IF(GU11="","",TODAY()-GU11) | GY11: =IF(GU11="","SIN ESTADO",IF(GW11<>"","PAGA",IF(GV11>0,"VENCIDA",IF(GV11>=-5,"POR VENCER","AL DÍA")))) | HA11: =IF(N($H11)<34,"",IF(GU11="","",GU11+31)) | HB11: =IF(HA11="","",TODAY()-HA11) | HE11: =IF(HA11="","SIN ESTADO",IF(HC11<>"","PAGA",IF(HB11>0,"VENCIDA",IF(HB11>=-5,"POR VENCER","AL DÍA")))) | HG11: =IF(N($H11)<35,"",IF(HA11="","",HA11+31)) | HH11: =IF(HG11="","",TODAY()-HG11) | HK11: =IF(HG11="","SIN ESTADO",IF(HI11<>"","PAGA",IF(HH11>0,"VENCIDA",IF(HH11>=-5,"POR VENCER","AL DÍA")))) | HM11: =IF(N($H11)<36,"",IF(HG11="","",HG11+31)) | HN11: =IF(HM11="","",TODAY()-HM11) | HQ11: =IF(HM11="","SIN ESTADO",IF(HO11<>"","PAGA",IF(HN11>0,"VENCIDA",IF(HN11>=-5,"POR VENCER","AL DÍA")))) | HS11: =N11+T11+Z11+AF11+AL11+AR11+AX11+BD11+BJ11+BP11+BV11+CB11+CH11+CN11+CT11+CZ11+DF11+DL11+DR11+DX11+ED11+EJ11+EP11+EV11+FB11+FH11+FN11+FT11+FZ11+GF11+GL11+GR11+GX11+HD11+HJ11+HP11 | HU11: =IFERROR(N($J11),0) | HW11: =SUMPRODUCT((MOD(COLUMN($M11:$HR11)-COLUMN($M11),6)=0)*ISNUMBER($M11:$HR11)*($M11:$HR11>=RESUMEN!$C$26)*($M11:$HR11<=RESUMEN!$C$27)*IFERROR(N($N11:$HS11),0)) | HX11: =SUMPRODUCT((MOD(COLUMN($M11:$HR11)-COLUMN($M11),6)=0)*ISNUMBER($M11:$HR11)*($M11:$HR11>=RESUMEN!$C$26)*($M11:$HR11<=RESUMEN!$C$27))
B12: =VENTAS!A11 | C12: =VENTAS!B11 | D12: =VENTAS!C11 | E12: =VENTAS!D11 | F12: =VENTAS!J11 | G12: =VENTAS!F11 | H12: =VENTAS!K11 | I12: =VENTAS!M11 | J12: =VENTAS!L11 | K12: =IF(N($H12)<1,"",$G12+31) | L12: =IF(K12="","",TODAY()-K12) | O12: =IF(K12="","SIN ESTADO",IF(M12<>"","PAGA",IF(L12>0,"VENCIDA",IF(L12>=-5,"POR VENCER","AL DÍA")))) | Q12: =IF(N($H12)<2,"",IF(K12="","",K12+31)) | R12: =IF(Q12="","",TODAY()-Q12) | U12: =IF(Q12="","SIN ESTADO",IF(S12<>"","PAGA",IF(R12>0,"VENCIDA",IF(R12>=-5,"POR VENCER","AL DÍA")))) | W12: =IF(N($H12)<3,"",IF(Q12="","",Q12+31)) | X12: =IF(W12="","",TODAY()-W12) | AA12: =IF(W12="","SIN ESTADO",IF(Y12<>"","PAGA",IF(X12>0,"VENCIDA",IF(X12>=-5,"POR VENCER","AL DÍA")))) | AC12: =IF(N($H12)<4,"",IF(W12="","",W12+31)) | AD12: =IF(AC12="","",TODAY()-AC12) | AG12: =IF(AC12="","SIN ESTADO",IF(AE12<>"","PAGA",IF(AD12>0,"VENCIDA",IF(AD12>=-5,"POR VENCER","AL DÍA")))) | AI12: =IF(N($H12)<5,"",IF(AC12="","",AC12+31)) | AJ12: =IF(AI12="","",TODAY()-AI12) | AM12: =IF(AI12="","SIN ESTADO",IF(AK12<>"","PAGA",IF(AJ12>0,"VENCIDA",IF(AJ12>=-5,"POR VENCER","AL DÍA")))) | AO12: =IF(N($H12)<6,"",IF(AI12="","",AI12+31)) | AP12: =IF(AO12="","",TODAY()-AO12) | AS12: =IF(AO12="","SIN ESTADO",IF(AQ12<>"","PAGA",IF(AP12>0,"VENCIDA",IF(AP12>=-5,"POR VENCER","AL DÍA")))) | AU12: =IF(N($H12)<7,"",IF(AO12="","",AO12+31)) | AV12: =IF(AU12="","",TODAY()-AU12) | AY12: =IF(AU12="","SIN ESTADO",IF(AW12<>"","PAGA",IF(AV12>0,"VENCIDA",IF(AV12>=-5,"POR VENCER","AL DÍA")))) | BA12: =IF(N($H12)<8,"",IF(AU12="","",AU12+31)) | BB12: =IF(BA12="","",TODAY()-BA12) | BE12: =IF(BA12="","SIN ESTADO",IF(BC12<>"","PAGA",IF(BB12>0,"VENCIDA",IF(BB12>=-5,"POR VENCER","AL DÍA")))) | BG12: =IF(N($H12)<9,"",IF(BA12="","",BA12+31)) | BH12: =IF(BG12="","",TODAY()-BG12) | BK12: =IF(BG12="","SIN ESTADO",IF(BI12<>"","PAGA",IF(BH12>0,"VENCIDA",IF(BH12>=-5,"POR VENCER","AL DÍA")))) | BM12: =IF(N($H12)<10,"",IF(BG12="","",BG12+31)) | BN12: =IF(BM12="","",TODAY()-BM12) | BQ12: =IF(BM12="","SIN ESTADO",IF(BO12<>"","PAGA",IF(BN12>0,"VENCIDA",IF(BN12>=-5,"POR VENCER","AL DÍA")))) | BS12: =IF(N($H12)<11,"",IF(BM12="","",BM12+31)) | BT12: =IF(BS12="","",TODAY()-BS12) | BW12: =IF(BS12="","SIN ESTADO",IF(BU12<>"","PAGA",IF(BT12>0,"VENCIDA",IF(BT12>=-5,"POR VENCER","AL DÍA")))) | BY12: =IF(N($H12)<12,"",IF(BS12="","",BS12+31)) | BZ12: =IF(BY12="","",TODAY()-BY12) | CC12: =IF(BY12="","SIN ESTADO",IF(CA12<>"","PAGA",IF(BZ12>0,"VENCIDA",IF(BZ12>=-5,"POR VENCER","AL DÍA")))) | CE12: =IF(N($H12)<13,"",IF(BY12="","",BY12+31)) | CF12: =IF(CE12="","",TODAY()-CE12) | CI12: =IF(CE12="","SIN ESTADO",IF(CG12<>"","PAGA",IF(CF12>0,"VENCIDA",IF(CF12>=-5,"POR VENCER","AL DÍA")))) | CK12: =IF(N($H12)<14,"",IF(CE12="","",CE12+31)) | CL12: =IF(CK12="","",TODAY()-CK12) | CO12: =IF(CK12="","SIN ESTADO",IF(CM12<>"","PAGA",IF(CL12>0,"VENCIDA",IF(CL12>=-5,"POR VENCER","AL DÍA")))) | CQ12: =IF(N($H12)<15,"",IF(CK12="","",CK12+31)) | CR12: =IF(CQ12="","",TODAY()-CQ12) | CU12: =IF(CQ12="","SIN ESTADO",IF(CS12<>"","PAGA",IF(CR12>0,"VENCIDA",IF(CR12>=-5,"POR VENCER","AL DÍA")))) | CW12: =IF(N($H12)<16,"",IF(CQ12="","",CQ12+31)) | CX12: =IF(CW12="","",TODAY()-CW12) | DA12: =IF(CW12="","SIN ESTADO",IF(CY12<>"","PAGA",IF(CX12>0,"VENCIDA",IF(CX12>=-5,"POR VENCER","AL DÍA")))) | DC12: =IF(N($H12)<17,"",IF(CW12="","",CW12+31)) | DD12: =IF(DC12="","",TODAY()-DC12) | DG12: =IF(DC12="","SIN ESTADO",IF(DE12<>"","PAGA",IF(DD12>0,"VENCIDA",IF(DD12>=-5,"POR VENCER","AL DÍA")))) | DI12: =IF(N($H12)<18,"",IF(DC12="","",DC12+31)) | DJ12: =IF(DI12="","",TODAY()-DI12) | DM12: =IF(DI12="","SIN ESTADO",IF(DK12<>"","PAGA",IF(DJ12>0,"VENCIDA",IF(DJ12>=-5,"POR VENCER","AL DÍA")))) | DO12: =IF(N($H12)<19,"",IF(DI12="","",DI12+31)) | DP12: =IF(DO12="","",TODAY()-DO12) | DS12: =IF(DO12="","SIN ESTADO",IF(DQ12<>"","PAGA",IF(DP12>0,"VENCIDA",IF(DP12>=-5,"POR VENCER","AL DÍA")))) | DU12: =IF(N($H12)<20,"",IF(DO12="","",DO12+31)) | DV12: =IF(DU12="","",TODAY()-DU12) | DY12: =IF(DU12="","SIN ESTADO",IF(DW12<>"","PAGA",IF(DV12>0,"VENCIDA",IF(DV12>=-5,"POR VENCER","AL DÍA")))) | EA12: =IF(N($H12)<21,"",IF(DU12="","",DU12+31)) | EB12: =IF(EA12="","",TODAY()-EA12) | EE12: =IF(EA12="","SIN ESTADO",IF(EC12<>"","PAGA",IF(EB12>0,"VENCIDA",IF(EB12>=-5,"POR VENCER","AL DÍA")))) | EG12: =IF(N($H12)<22,"",IF(EA12="","",EA12+31)) | EH12: =IF(EG12="","",TODAY()-EG12) | EK12: =IF(EG12="","SIN ESTADO",IF(EI12<>"","PAGA",IF(EH12>0,"VENCIDA",IF(EH12>=-5,"POR VENCER","AL DÍA")))) | EM12: =IF(N($H12)<23,"",IF(EG12="","",EG12+31)) | EN12: =IF(EM12="","",TODAY()-EM12) | EQ12: =IF(EM12="","SIN ESTADO",IF(EO12<>"","PAGA",IF(EN12>0,"VENCIDA",IF(EN12>=-5,"POR VENCER","AL DÍA")))) | ES12: =IF(N($H12)<24,"",IF(EM12="","",EM12+31)) | ET12: =IF(ES12="","",TODAY()-ES12) | EW12: =IF(ES12="","SIN ESTADO",IF(EU12<>"","PAGA",IF(ET12>0,"VENCIDA",IF(ET12>=-5,"POR VENCER","AL DÍA")))) | EY12: =IF(N($H12)<25,"",IF(ES12="","",ES12+31)) | EZ12: =IF(EY12="","",TODAY()-EY12) | FC12: =IF(EY12="","SIN ESTADO",IF(FA12<>"","PAGA",IF(EZ12>0,"VENCIDA",IF(EZ12>=-5,"POR VENCER","AL DÍA")))) | FE12: =IF(N($H12)<26,"",IF(EY12="","",EY12+31)) | FF12: =IF(FE12="","",TODAY()-FE12) | FI12: =IF(FE12="","SIN ESTADO",IF(FG12<>"","PAGA",IF(FF12>0,"VENCIDA",IF(FF12>=-5,"POR VENCER","AL DÍA")))) | FK12: =IF(N($H12)<27,"",IF(FE12="","",FE12+31)) | FL12: =IF(FK12="","",TODAY()-FK12) | FO12: =IF(FK12="","SIN ESTADO",IF(FM12<>"","PAGA",IF(FL12>0,"VENCIDA",IF(FL12>=-5,"POR VENCER","AL DÍA")))) | FQ12: =IF(N($H12)<28,"",IF(FK12="","",FK12+31)) | FR12: =IF(FQ12="","",TODAY()-FQ12) | FU12: =IF(FQ12="","SIN ESTADO",IF(FS12<>"","PAGA",IF(FR12>0,"VENCIDA",IF(FR12>=-5,"POR VENCER","AL DÍA")))) | FW12: =IF(N($H12)<29,"",IF(FQ12="","",FQ12+31)) | FX12: =IF(FW12="","",TODAY()-FW12) | GA12: =IF(FW12="","SIN ESTADO",IF(FY12<>"","PAGA",IF(FX12>0,"VENCIDA",IF(FX12>=-5,"POR VENCER","AL DÍA")))) | GC12: =IF(N($H12)<30,"",IF(FW12="","",FW12+31)) | GD12: =IF(GC12="","",TODAY()-GC12) | GG12: =IF(GC12="","SIN ESTADO",IF(GE12<>"","PAGA",IF(GD12>0,"VENCIDA",IF(GD12>=-5,"POR VENCER","AL DÍA")))) | GI12: =IF(N($H12)<31,"",IF(GC12="","",GC12+31)) | GJ12: =IF(GI12="","",TODAY()-GI12) | GM12: =IF(GI12="","SIN ESTADO",IF(GK12<>"","PAGA",IF(GJ12>0,"VENCIDA",IF(GJ12>=-5,"POR VENCER","AL DÍA")))) | GO12: =IF(N($H12)<32,"",IF(GI12="","",GI12+31)) | GP12: =IF(GO12="","",TODAY()-GO12) | GS12: =IF(GO12="","SIN ESTADO",IF(GQ12<>"","PAGA",IF(GP12>0,"VENCIDA",IF(GP12>=-5,"POR VENCER","AL DÍA")))) | GU12: =IF(N($H12)<33,"",IF(GO12="","",GO12+31)) | GV12: =IF(GU12="","",TODAY()-GU12) | GY12: =IF(GU12="","SIN ESTADO",IF(GW12<>"","PAGA",IF(GV12>0,"VENCIDA",IF(GV12>=-5,"POR VENCER","AL DÍA")))) | HA12: =IF(N($H12)<34,"",IF(GU12="","",GU12+31)) | HB12: =IF(HA12="","",TODAY()-HA12) | HE12: =IF(HA12="","SIN ESTADO",IF(HC12<>"","PAGA",IF(HB12>0,"VENCIDA",IF(HB12>=-5,"POR VENCER","AL DÍA")))) | HG12: =IF(N($H12)<35,"",IF(HA12="","",HA12+31)) | HH12: =IF(HG12="","",TODAY()-HG12) | HK12: =IF(HG12="","SIN ESTADO",IF(HI12<>"","PAGA",IF(HH12>0,"VENCIDA",IF(HH12>=-5,"POR VENCER","AL DÍA")))) | HM12: =IF(N($H12)<36,"",IF(HG12="","",HG12+31)) | HN12: =IF(HM12="","",TODAY()-HM12) | HQ12: =IF(HM12="","SIN ESTADO",IF(HO12<>"","PAGA",IF(HN12>0,"VENCIDA",IF(HN12>=-5,"POR VENCER","AL DÍA")))) | HS12: =N12+T12+Z12+AF12+AL12+AR12+AX12+BD12+BJ12+BP12+BV12+CB12+CH12+CN12+CT12+CZ12+DF12+DL12+DR12+DX12+ED12+EJ12+EP12+EV12+FB12+FH12+FN12+FT12+FZ12+GF12+GL12+GR12+GX12+HD12+HJ12+HP12 | HU12: =IFERROR(N($J12),0) | HW12: =SUMPRODUCT((MOD(COLUMN($M12:$HR12)-COLUMN($M12),6)=0)*ISNUMBER($M12:$HR12)*($M12:$HR12>=RESUMEN!$C$26)*($M12:$HR12<=RESUMEN!$C$27)*IFERROR(N($N12:$HS12),0)) | HX12: =SUMPRODUCT((MOD(COLUMN($M12:$HR12)-COLUMN($M12),6)=0)*ISNUMBER($M12:$HR12)*($M12:$HR12>=RESUMEN!$C$26)*($M12:$HR12<=RESUMEN!$C$27))
B13: =VENTAS!A12 | C13: =VENTAS!B12 | D13: =VENTAS!C12 | E13: =VENTAS!D12 | F13: =VENTAS!J12 | G13: =VENTAS!F12 | H13: =VENTAS!K12 | I13: =VENTAS!M12 | J13: =VENTAS!L12 | K13: =IF(N($H13)<1,"",$G13+31) | L13: =IF(K13="","",TODAY()-K13) | M13: 46077 | N13: 1641000 | O13: =IF(K13="","SIN ESTADO",IF(M13<>"","PAGA",IF(L13>0,"VENCIDA",IF(L13>=-5,"POR VENCER","AL DÍA")))) | P13: TRANSFERENCIA | Q13: =IF(N($H13)<2,"",IF(K13="","",K13+31)) | R13: =IF(Q13="","",TODAY()-Q13) | S13: 46111 | T13: 1641000 | U13: =IF(Q13="","SIN ESTADO",IF(S13<>"","PAGA",IF(R13>0,"VENCIDA",IF(R13>=-5,"POR VENCER","AL DÍA")))) | V13: TRANSFERENCIA | W13: =IF(N($H13)<3,"",IF(Q13="","",Q13+31)) | X13: =IF(W13="","",TODAY()-W13) | Y13: 45946 | Z13: 875000 | AA13: =IF(W13="","SIN ESTADO",IF(Y13<>"","PAGA",IF(X13>0,"VENCIDA",IF(X13>=-5,"POR VENCER","AL DÍA")))) | AB13: TRANSFERENCIA | AC13: =IF(N($H13)<4,"",IF(W13="","",W13+31)) | AD13: =IF(AC13="","",TODAY()-AC13) | AE13: 45975 | AF13: 875000 | AG13: =IF(AC13="","SIN ESTADO",IF(AE13<>"","PAGA",IF(AD13>0,"VENCIDA",IF(AD13>=-5,"POR VENCER","AL DÍA")))) | AH13: TRANSFERENCIA | AI13: =IF(N($H13)<5,"",IF(AC13="","",AC13+31)) | AJ13: =IF(AI13="","",TODAY()-AI13) | AK13: 46010 | AL13: 875000 | AM13: =IF(AI13="","SIN ESTADO",IF(AK13<>"","PAGA",IF(AJ13>0,"VENCIDA",IF(AJ13>=-5,"POR VENCER","AL DÍA")))) | AN13: TRANSFERENCIA | AO13: =IF(N($H13)<6,"",IF(AI13="","",AI13+31)) | AP13: =IF(AO13="","",TODAY()-AO13) | AQ13: 46039 | AR13: 875000 | AS13: =IF(AO13="","SIN ESTADO",IF(AQ13<>"","PAGA",IF(AP13>0,"VENCIDA",IF(AP13>=-5,"POR VENCER","AL DÍA")))) | AT13: TRANSFERENCIA | AU13: =IF(N($H13)<7,"",IF(AO13="","",AO13+31)) | AV13: =IF(AU13="","",TODAY()-AU13) | AW13: 46097 | AX13: 875000 | AY13: =IF(AU13="","SIN ESTADO",IF(AW13<>"","PAGA",IF(AV13>0,"VENCIDA",IF(AV13>=-5,"POR VENCER","AL DÍA")))) | AZ13: TRANSFERENCIA | BA13: =IF(N($H13)<8,"",IF(AU13="","",AU13+31)) | BB13: =IF(BA13="","",TODAY()-BA13) | BC13: 46162 | BD13: 3282000 | BE13: =IF(BA13="","SIN ESTADO",IF(BC13<>"","PAGA",IF(BB13>0,"VENCIDA",IF(BB13>=-5,"POR VENCER","AL DÍA")))) | BF13: TRANSFERENCIA | BG13: =IF(N($H13)<9,"",IF(BA13="","",BA13+31)) | BH13: =IF(BG13="","",TODAY()-BG13) | BI13: 46240 | BJ13: 1641000 | BK13: =IF(BG13="","SIN ESTADO",IF(BI13<>"","PAGA",IF(BH13>0,"VENCIDA",IF(BH13>=-5,"POR VENCER","AL DÍA")))) | BL13: TRANSFERENCIA | BM13: =IF(N($H13)<10,"",IF(BG13="","",BG13+31)) | BN13: =IF(BM13="","",TODAY()-BM13) | BQ13: =IF(BM13="","SIN ESTADO",IF(BO13<>"","PAGA",IF(BN13>0,"VENCIDA",IF(BN13>=-5,"POR VENCER","AL DÍA")))) | BS13: =IF(N($H13)<11,"",IF(BM13="","",BM13+31)) | BT13: =IF(BS13="","",TODAY()-BS13) | BW13: =IF(BS13="","SIN ESTADO",IF(BU13<>"","PAGA",IF(BT13>0,"VENCIDA",IF(BT13>=-5,"POR VENCER","AL DÍA")))) | BY13: =IF(N($H13)<12,"",IF(BS13="","",BS13+31)) | BZ13: =IF(BY13="","",TODAY()-BY13) | CC13: =IF(BY13="","SIN ESTADO",IF(CA13<>"","PAGA",IF(BZ13>0,"VENCIDA",IF(BZ13>=-5,"POR VENCER","AL DÍA")))) | CE13: =IF(N($H13)<13,"",IF(BY13="","",BY13+31)) | CF13: =IF(CE13="","",TODAY()-CE13) | CI13: =IF(CE13="","SIN ESTADO",IF(CG13<>"","PAGA",IF(CF13>0,"VENCIDA",IF(CF13>=-5,"POR VENCER","AL DÍA")))) | CK13: =IF(N($H13)<14,"",IF(CE13="","",CE13+31)) | CL13: =IF(CK13="","",TODAY()-CK13) | CO13: =IF(CK13="","SIN ESTADO",IF(CM13<>"","PAGA",IF(CL13>0,"VENCIDA",IF(CL13>=-5,"POR VENCER","AL DÍA")))) | CQ13: =IF(N($H13)<15,"",IF(CK13="","",CK13+31)) | CR13: =IF(CQ13="","",TODAY()-CQ13) | CU13: =IF(CQ13="","SIN ESTADO",IF(CS13<>"","PAGA",IF(CR13>0,"VENCIDA",IF(CR13>=-5,"POR VENCER","AL DÍA")))) | CW13: =IF(N($H13)<16,"",IF(CQ13="","",CQ13+31)) | CX13: =IF(CW13="","",TODAY()-CW13) | DA13: =IF(CW13="","SIN ESTADO",IF(CY13<>"","PAGA",IF(CX13>0,"VENCIDA",IF(CX13>=-5,"POR VENCER","AL DÍA")))) | DC13: =IF(N($H13)<17,"",IF(CW13="","",CW13+31)) | DD13: =IF(DC13="","",TODAY()-DC13) | DG13: =IF(DC13="","SIN ESTADO",IF(DE13<>"","PAGA",IF(DD13>0,"VENCIDA",IF(DD13>=-5,"POR VENCER","AL DÍA")))) | DI13: =IF(N($H13)<18,"",IF(DC13="","",DC13+31)) | DJ13: =IF(DI13="","",TODAY()-DI13) | DM13: =IF(DI13="","SIN ESTADO",IF(DK13<>"","PAGA",IF(DJ13>0,"VENCIDA",IF(DJ13>=-5,"POR VENCER","AL DÍA")))) | DO13: =IF(N($H13)<19,"",IF(DI13="","",DI13+31)) | DP13: =IF(DO13="","",TODAY()-DO13) | DS13: =IF(DO13="","SIN ESTADO",IF(DQ13<>"","PAGA",IF(DP13>0,"VENCIDA",IF(DP13>=-5,"POR VENCER","AL DÍA")))) | DU13: =IF(N($H13)<20,"",IF(DO13="","",DO13+31)) | DV13: =IF(DU13="","",TODAY()-DU13) | DY13: =IF(DU13="","SIN ESTADO",IF(DW13<>"","PAGA",IF(DV13>0,"VENCIDA",IF(DV13>=-5,"POR VENCER","AL DÍA")))) | EA13: =IF(N($H13)<21,"",IF(DU13="","",DU13+31)) | EB13: =IF(EA13="","",TODAY()-EA13) | EE13: =IF(EA13="","SIN ESTADO",IF(EC13<>"","PAGA",IF(EB13>0,"VENCIDA",IF(EB13>=-5,"POR VENCER","AL DÍA")))) | EG13: =IF(N($H13)<22,"",IF(EA13="","",EA13+31)) | EH13: =IF(EG13="","",TODAY()-EG13) | EK13: =IF(EG13="","SIN ESTADO",IF(EI13<>"","PAGA",IF(EH13>0,"VENCIDA",IF(EH13>=-5,"POR VENCER","AL DÍA")))) | EM13: =IF(N($H13)<23,"",IF(EG13="","",EG13+31)) | EN13: =IF(EM13="","",TODAY()-EM13) | EQ13: =IF(EM13="","SIN ESTADO",IF(EO13<>"","PAGA",IF(EN13>0,"VENCIDA",IF(EN13>=-5,"POR VENCER","AL DÍA")))) | ES13: =IF(N($H13)<24,"",IF(EM13="","",EM13+31)) | ET13: =IF(ES13="","",TODAY()-ES13) | EW13: =IF(ES13="","SIN ESTADO",IF(EU13<>"","PAGA",IF(ET13>0,"VENCIDA",IF(ET13>=-5,"POR VENCER","AL DÍA")))) | EY13: =IF(N($H13)<25,"",IF(ES13="","",ES13+31)) | EZ13: =IF(EY13="","",TODAY()-EY13) | FC13: =IF(EY13="","SIN ESTADO",IF(FA13<>"","PAGA",IF(EZ13>0,"VENCIDA",IF(EZ13>=-5,"POR VENCER","AL DÍA")))) | FE13: =IF(N($H13)<26,"",IF(EY13="","",EY13+31)) | FF13: =IF(FE13="","",TODAY()-FE13) | FI13: =IF(FE13="","SIN ESTADO",IF(FG13<>"","PAGA",IF(FF13>0,"VENCIDA",IF(FF13>=-5,"POR VENCER","AL DÍA")))) | FK13: =IF(N($H13)<27,"",IF(FE13="","",FE13+31)) | FL13: =IF(FK13="","",TODAY()-FK13) | FO13: =IF(FK13="","SIN ESTADO",IF(FM13<>"","PAGA",IF(FL13>0,"VENCIDA",IF(FL13>=-5,"POR VENCER","AL DÍA")))) | FQ13: =IF(N($H13)<28,"",IF(FK13="","",FK13+31)) | FR13: =IF(FQ13="","",TODAY()-FQ13) | FU13: =IF(FQ13="","SIN ESTADO",IF(FS13<>"","PAGA",IF(FR13>0,"VENCIDA",IF(FR13>=-5,"POR VENCER","AL DÍA")))) | FW13: =IF(N($H13)<29,"",IF(FQ13="","",FQ13+31)) | FX13: =IF(FW13="","",TODAY()-FW13) | GA13: =IF(FW13="","SIN ESTADO",IF(FY13<>"","PAGA",IF(FX13>0,"VENCIDA",IF(FX13>=-5,"POR VENCER","AL DÍA")))) | GC13: =IF(N($H13)<30,"",IF(FW13="","",FW13+31)) | GD13: =IF(GC13="","",TODAY()-GC13) | GG13: =IF(GC13="","SIN ESTADO",IF(GE13<>"","PAGA",IF(GD13>0,"VENCIDA",IF(GD13>=-5,"POR VENCER","AL DÍA")))) | GI13: =IF(N($H13)<31,"",IF(GC13="","",GC13+31)) | GJ13: =IF(GI13="","",TODAY()-GI13) | GM13: =IF(GI13="","SIN ESTADO",IF(GK13<>"","PAGA",IF(GJ13>0,"VENCIDA",IF(GJ13>=-5,"POR VENCER","AL DÍA")))) | GO13: =IF(N($H13)<32,"",IF(GI13="","",GI13+31)) | GP13: =IF(GO13="","",TODAY()-GO13) | GS13: =IF(GO13="","SIN ESTADO",IF(GQ13<>"","PAGA",IF(GP13>0,"VENCIDA",IF(GP13>=-5,"POR VENCER","AL DÍA")))) | GU13: =IF(N($H13)<33,"",IF(GO13="","",GO13+31)) | GV13: =IF(GU13="","",TODAY()-GU13) | GY13: =IF(GU13="","SIN ESTADO",IF(GW13<>"","PAGA",IF(GV13>0,"VENCIDA",IF(GV13>=-5,"POR VENCER","AL DÍA")))) | HA13: =IF(N($H13)<34,"",IF(GU13="","",GU13+31)) | HB13: =IF(HA13="","",TODAY()-HA13) | HE13: =IF(HA13="","SIN ESTADO",IF(HC13<>"","PAGA",IF(HB13>0,"VENCIDA",IF(HB13>=-5,"POR VENCER","AL DÍA")))) | HG13: =IF(N($H13)<35,"",IF(HA13="","",HA13+31)) | HH13: =IF(HG13="","",TODAY()-HG13) | HK13: =IF(HG13="","SIN ESTADO",IF(HI13<>"","PAGA",IF(HH13>0,"VENCIDA",IF(HH13>=-5,"POR VENCER","AL DÍA")))) | HM13: =IF(N($H13)<36,"",IF(HG13="","",HG13+31)) | HN13: =IF(HM13="","",TODAY()-HM13) | HQ13: =IF(HM13="","SIN ESTADO",IF(HO13<>"","PAGA",IF(HN13>0,"VENCIDA",IF(HN13>=-5,"POR VENCER","AL DÍA")))) | HS13: =N13+T13+Z13+AF13+AL13+AR13+AX13+BD13+BJ13+BP13+BV13+CB13+CH13+CN13+CT13+CZ13+DF13+DL13+DR13+DX13+ED13+EJ13+EP13+EV13+FB13+FH13+FN13+FT13+FZ13+GF13+GL13+GR13+GX13+HD13+HJ13+HP13 | HU13: =IFERROR(N($J13),0) | HW13: =SUMPRODUCT((MOD(COLUMN($M13:$HR13)-COLUMN($M13),6)=0)*ISNUMBER($M13:$HR13)*($M13:$HR13>=RESUMEN!$C$26)*($M13:$HR13<=RESUMEN!$C$27)*IFERROR(N($N13:$HS13),0)) | HX13: =SUMPRODUCT((MOD(COLUMN($M13:$HR13)-COLUMN($M13),6)=0)*ISNUMBER($M13:$HR13)*($M13:$HR13>=RESUMEN!$C$26)*($M13:$HR13<=RESUMEN!$C$27))
B14: =VENTAS!A13 | C14: =VENTAS!B13 | D14: =VENTAS!C13 | E14: =VENTAS!D13 | F14: =VENTAS!J13 | G14: =VENTAS!F13 | H14: =VENTAS!K13 | I14: =VENTAS!M13 | J14: =VENTAS!L13 | K14: =IF(N($H14)<1,"",$G14+31) | L14: =IF(K14="","",TODAY()-K14) | M14: 45886 | N14: 875000 | O14: =IF(K14="","SIN ESTADO",IF(M14<>"","PAGA",IF(L14>0,"VENCIDA",IF(L14>=-5,"POR VENCER","AL DÍA")))) | P14: EFECTIVO | Q14: =IF(N($H14)<2,"",IF(K14="","",K14+31)) | R14: =IF(Q14="","",TODAY()-Q14) | S14: 46280 | T14: 875000 | U14: =IF(Q14="","SIN ESTADO",IF(S14<>"","PAGA",IF(R14>0,"VENCIDA",IF(R14>=-5,"POR VENCER","AL DÍA")))) | V14: TRANSFERENCIA | W14: =IF(N($H14)<3,"",IF(Q14="","",Q14+31)) | X14: =IF(W14="","",TODAY()-W14) | Y14: 45946 | Z14: 875000 | AA14: =IF(W14="","SIN ESTADO",IF(Y14<>"","PAGA",IF(X14>0,"VENCIDA",IF(X14>=-5,"POR VENCER","AL DÍA")))) | AB14: TRANSFERENCIA | AC14: =IF(N($H14)<4,"",IF(W14="","",W14+31)) | AD14: =IF(AC14="","",TODAY()-AC14) | AE14: 45975 | AF14: 875000 | AG14: =IF(AC14="","SIN ESTADO",IF(AE14<>"","PAGA",IF(AD14>0,"VENCIDA",IF(AD14>=-5,"POR VENCER","AL DÍA")))) | AH14: TRANSFERENCIA | AI14: =IF(N($H14)<5,"",IF(AC14="","",AC14+31)) | AJ14: =IF(AI14="","",TODAY()-AI14) | AK14: 46010 | AL14: 875000 | AM14: =IF(AI14="","SIN ESTADO",IF(AK14<>"","PAGA",IF(AJ14>0,"VENCIDA",IF(AJ14>=-5,"POR VENCER","AL DÍA")))) | AN14: TRANSFERENCIA | AO14: =IF(N($H14)<6,"",IF(AI14="","",AI14+31)) | AP14: =IF(AO14="","",TODAY()-AO14) | AQ14: 46039 | AR14: 875000 | AS14: =IF(AO14="","SIN ESTADO",IF(AQ14<>"","PAGA",IF(AP14>0,"VENCIDA",IF(AP14>=-5,"POR VENCER","AL DÍA")))) | AT14: TRANSFERENCIA | AU14: =IF(N($H14)<7,"",IF(AO14="","",AO14+31)) | AV14: =IF(AU14="","",TODAY()-AU14) | AW14: 46070 | AX14: 875000 | AY14: =IF(AU14="","SIN ESTADO",IF(AW14<>"","PAGA",IF(AV14>0,"VENCIDA",IF(AV14>=-5,"POR VENCER","AL DÍA")))) | AZ14: TRANSFERENCIA | BA14: =IF(N($H14)<8,"",IF(AU14="","",AU14+31)) | BB14: =IF(BA14="","",TODAY()-BA14) | BC14: 46097 | BD14: 875000 | BE14: =IF(BA14="","SIN ESTADO",IF(BC14<>"","PAGA",IF(BB14>0,"VENCIDA",IF(BB14>=-5,"POR VENCER","AL DÍA")))) | BF14: TRANSFERENCIA | BG14: =IF(N($H14)<9,"",IF(BA14="","",BA14+31)) | BH14: =IF(BG14="","",TODAY()-BG14) | BI14: 46128 | BJ14: 875000 | BK14: =IF(BG14="","SIN ESTADO",IF(BI14<>"","PAGA",IF(BH14>0,"VENCIDA",IF(BH14>=-5,"POR VENCER","AL DÍA")))) | BL14: TRANSFERENCIA | BM14: =IF(N($H14)<10,"",IF(BG14="","",BG14+31)) | BN14: =IF(BM14="","",TODAY()-BM14) | BO14: 46148 | BP14: 875000 | BQ14: =IF(BM14="","SIN ESTADO",IF(BO14<>"","PAGA",IF(BN14>0,"VENCIDA",IF(BN14>=-5,"POR VENCER","AL DÍA")))) | BR14: TRANSFERENCIA | BS14: =IF(N($H14)<11,"",IF(BM14="","",BM14+31)) | BT14: =IF(BS14="","",TODAY()-BS14) | BU14: 46190 | BV14: 875000 | BW14: =IF(BS14="","SIN ESTADO",IF(BU14<>"","PAGA",IF(BT14>0,"VENCIDA",IF(BT14>=-5,"POR VENCER","AL DÍA")))) | BX14: TRANSFERENCIA | BY14: =IF(N($H14)<12,"",IF(BS14="","",BS14+31)) | BZ14: =IF(BY14="","",TODAY()-BY14) | CA14: 46216 | CB14: 875000 | CC14: =IF(BY14="","SIN ESTADO",IF(CA14<>"","PAGA",IF(BZ14>0,"VENCIDA",IF(BZ14>=-5,"POR VENCER","AL DÍA")))) | CD14: TRANSFERENCIA | CE14: =IF(N($H14)<13,"",IF(BY14="","",BY14+31)) | CF14: =IF(CE14="","",TODAY()-CE14) | CG14: 46249 | CH14: 875000 | CI14: =IF(CE14="","SIN ESTADO",IF(CG14<>"","PAGA",IF(CF14>0,"VENCIDA",IF(CF14>=-5,"POR VENCER","AL DÍA")))) | CJ14: TRANSFERENCIA | CK14: =IF(N($H14)<14,"",IF(CE14="","",CE14+31)) | CL14: =IF(CK14="","",TODAY()-CK14) | CM14: 46281 | CN14: 875000 | CO14: =IF(CK14="","SIN ESTADO",IF(CM14<>"","PAGA",IF(CL14>0,"VENCIDA",IF(CL14>=-5,"POR VENCER","AL DÍA")))) | CP14: TRANSFERENCIA | CQ14: =IF(N($H14)<15,"",IF(CK14="","",CK14+31)) | CR14: =IF(CQ14="","",TODAY()-CQ14) | CU14: =IF(CQ14="","SIN ESTADO",IF(CS14<>"","PAGA",IF(CR14>0,"VENCIDA",IF(CR14>=-5,"POR VENCER","AL DÍA")))) | CW14: =IF(N($H14)<16,"",IF(CQ14="","",CQ14+31)) | CX14: =IF(CW14="","",TODAY()-CW14) | DA14: =IF(CW14="","SIN ESTADO",IF(CY14<>"","PAGA",IF(CX14>0,"VENCIDA",IF(CX14>=-5,"POR VENCER","AL DÍA")))) | DC14: =IF(N($H14)<17,"",IF(CW14="","",CW14+31)) | DD14: =IF(DC14="","",TODAY()-DC14) | DG14: =IF(DC14="","SIN ESTADO",IF(DE14<>"","PAGA",IF(DD14>0,"VENCIDA",IF(DD14>=-5,"POR VENCER","AL DÍA")))) | DI14: =IF(N($H14)<18,"",IF(DC14="","",DC14+31)) | DJ14: =IF(DI14="","",TODAY()-DI14) | DM14: =IF(DI14="","SIN ESTADO",IF(DK14<>"","PAGA",IF(DJ14>0,"VENCIDA",IF(DJ14>=-5,"POR VENCER","AL DÍA")))) | DO14: =IF(N($H14)<19,"",IF(DI14="","",DI14+31)) | DP14: =IF(DO14="","",TODAY()-DO14) | DS14: =IF(DO14="","SIN ESTADO",IF(DQ14<>"","PAGA",IF(DP14>0,"VENCIDA",IF(DP14>=-5,"POR VENCER","AL DÍA")))) | DU14: =IF(N($H14)<20,"",IF(DO14="","",DO14+31)) | DV14: =IF(DU14="","",TODAY()-DU14) | DY14: =IF(DU14="","SIN ESTADO",IF(DW14<>"","PAGA",IF(DV14>0,"VENCIDA",IF(DV14>=-5,"POR VENCER","AL DÍA")))) | EA14: =IF(N($H14)<21,"",IF(DU14="","",DU14+31)) | EB14: =IF(EA14="","",TODAY()-EA14) | EE14: =IF(EA14="","SIN ESTADO",IF(EC14<>"","PAGA",IF(EB14>0,"VENCIDA",IF(EB14>=-5,"POR VENCER","AL DÍA")))) | EG14: =IF(N($H14)<22,"",IF(EA14="","",EA14+31)) | EH14: =IF(EG14="","",TODAY()-EG14) | EK14: =IF(EG14="","SIN ESTADO",IF(EI14<>"","PAGA",IF(EH14>0,"VENCIDA",IF(EH14>=-5,"POR VENCER","AL DÍA")))) | EM14: =IF(N($H14)<23,"",IF(EG14="","",EG14+31)) | EN14: =IF(EM14="","",TODAY()-EM14) | EQ14: =IF(EM14="","SIN ESTADO",IF(EO14<>"","PAGA",IF(EN14>0,"VENCIDA",IF(EN14>=-5,"POR VENCER","AL DÍA")))) | ES14: =IF(N($H14)<24,"",IF(EM14="","",EM14+31)) | ET14: =IF(ES14="","",TODAY()-ES14) | EW14: =IF(ES14="","SIN ESTADO",IF(EU14<>"","PAGA",IF(ET14>0,"VENCIDA",IF(ET14>=-5,"POR VENCER","AL DÍA")))) | EY14: =IF(N($H14)<25,"",IF(ES14="","",ES14+31)) | EZ14: =IF(EY14="","",TODAY()-EY14) | FC14: =IF(EY14="","SIN ESTADO",IF(FA14<>"","PAGA",IF(EZ14>0,"VENCIDA",IF(EZ14>=-5,"POR VENCER","AL DÍA")))) | FE14: =IF(N($H14)<26,"",IF(EY14="","",EY14+31)) | FF14: =IF(FE14="","",TODAY()-FE14) | FI14: =IF(FE14="","SIN ESTADO",IF(FG14<>"","PAGA",IF(FF14>0,"VENCIDA",IF(FF14>=-5,"POR VENCER","AL DÍA")))) | FK14: =IF(N($H14)<27,"",IF(FE14="","",FE14+31)) | FL14: =IF(FK14="","",TODAY()-FK14) | FO14: =IF(FK14="","SIN ESTADO",IF(FM14<>"","PAGA",IF(FL14>0,"VENCIDA",IF(FL14>=-5,"POR VENCER","AL DÍA")))) | FQ14: =IF(N($H14)<28,"",IF(FK14="","",FK14+31)) | FR14: =IF(FQ14="","",TODAY()-FQ14) | FU14: =IF(FQ14="","SIN ESTADO",IF(FS14<>"","PAGA",IF(FR14>0,"VENCIDA",IF(FR14>=-5,"POR VENCER","AL DÍA")))) | FW14: =IF(N($H14)<29,"",IF(FQ14="","",FQ14+31)) | FX14: =IF(FW14="","",TODAY()-FW14) | GA14: =IF(FW14="","SIN ESTADO",IF(FY14<>"","PAGA",IF(FX14>0,"VENCIDA",IF(FX14>=-5,"POR VENCER","AL DÍA")))) | GC14: =IF(N($H14)<30,"",IF(FW14="","",FW14+31)) | GD14: =IF(GC14="","",TODAY()-GC14) | GG14: =IF(GC14="","SIN ESTADO",IF(GE14<>"","PAGA",IF(GD14>0,"VENCIDA",IF(GD14>=-5,"POR VENCER","AL DÍA")))) | GI14: =IF(N($H14)<31,"",IF(GC14="","",GC14+31)) | GJ14: =IF(GI14="","",TODAY()-GI14) | GM14: =IF(GI14="","SIN ESTADO",IF(GK14<>"","PAGA",IF(GJ14>0,"VENCIDA",IF(GJ14>=-5,"POR VENCER","AL DÍA")))) | GO14: =IF(N($H14)<32,"",IF(GI14="","",GI14+31)) | GP14: =IF(GO14="","",TODAY()-GO14) | GS14: =IF(GO14="","SIN ESTADO",IF(GQ14<>"","PAGA",IF(GP14>0,"VENCIDA",IF(GP14>=-5,"POR VENCER","AL DÍA")))) | GU14: =IF(N($H14)<33,"",IF(GO14="","",GO14+31)) | GV14: =IF(GU14="","",TODAY()-GU14) | GY14: =IF(GU14="","SIN ESTADO",IF(GW14<>"","PAGA",IF(GV14>0,"VENCIDA",IF(GV14>=-5,"POR VENCER","AL DÍA")))) | HA14: =IF(N($H14)<34,"",IF(GU14="","",GU14+31)) | HB14: =IF(HA14="","",TODAY()-HA14) | HE14: =IF(HA14="","SIN ESTADO",IF(HC14<>"","PAGA",IF(HB14>0,"VENCIDA",IF(HB14>=-5,"POR VENCER","AL DÍA")))) | HG14: =IF(N($H14)<35,"",IF(HA14="","",HA14+31)) | HH14: =IF(HG14="","",TODAY()-HG14) | HK14: =IF(HG14="","SIN ESTADO",IF(HI14<>"","PAGA",IF(HH14>0,"VENCIDA",IF(HH14>=-5,"POR VENCER","AL DÍA")))) | HM14: =IF(N($H14)<36,"",IF(HG14="","",HG14+31)) | HN14: =IF(HM14="","",TODAY()-HM14) | HQ14: =IF(HM14="","SIN ESTADO",IF(HO14<>"","PAGA",IF(HN14>0,"VENCIDA",IF(HN14>=-5,"POR VENCER","AL DÍA")))) | HS14: =N14+T14+Z14+AF14+AL14+AR14+AX14+BD14+BJ14+BP14+BV14+CB14+CH14+CN14+CT14+CZ14+DF14+DL14+DR14+DX14+ED14+EJ14+EP14+EV14+FB14+FH14+FN14+FT14+FZ14+GF14+GL14+GR14+GX14+HD14+HJ14+HP14 | HU14: =IFERROR(N($J14),0) | HW14: =SUMPRODUCT((MOD(COLUMN($M14:$HR14)-COLUMN($M14),6)=0)*ISNUMBER($M14:$HR14)*($M14:$HR14>=RESUMEN!$C$26)*($M14:$HR14<=RESUMEN!$C$27)*IFERROR(N($N14:$HS14),0)) | HX14: =SUMPRODUCT((MOD(COLUMN($M14:$HR14)-COLUMN($M14),6)=0)*ISNUMBER($M14:$HR14)*($M14:$HR14>=RESUMEN!$C$26)*($M14:$HR14<=RESUMEN!$C$27))
B15: =VENTAS!A14 | C15: =VENTAS!B14 | D15: =VENTAS!C14 | E15: =VENTAS!D14 | F15: =VENTAS!J14 | G15: =VENTAS!F14 | H15: =VENTAS!K14 | I15: =VENTAS!M14 | J15: =VENTAS!L14 | K15: =IF(N($H15)<1,"",$G15+31) | L15: =IF(K15="","",TODAY()-K15) | M15: 45936 | N15: 958300 | O15: =IF(K15="","SIN ESTADO",IF(M15<>"","PAGA",IF(L15>0,"VENCIDA",IF(L15>=-5,"POR VENCER","AL DÍA")))) | P15: TRANSFERENCIA | Q15: =IF(N($H15)<2,"",IF(K15="","",K15+31)) | R15: =IF(Q15="","",TODAY()-Q15) | S15: 45941 | T15: 1000000 | U15: =IF(Q15="","SIN ESTADO",IF(S15<>"","PAGA",IF(R15>0,"VENCIDA",IF(R15>=-5,"POR VENCER","AL DÍA")))) | V15: TRANSFERENCIA | W15: =IF(N($H15)<3,"",IF(Q15="","",Q15+31)) | X15: =IF(W15="","",TODAY()-W15) | Y15: 46338 | Z15: 3000000 | AA15: =IF(W15="","SIN ESTADO",IF(Y15<>"","PAGA",IF(X15>0,"VENCIDA",IF(X15>=-5,"POR VENCER","AL DÍA")))) | AB15: TRANSFERENCIA | AC15: =IF(N($H15)<4,"",IF(W15="","",W15+31)) | AD15: =IF(AC15="","",TODAY()-AC15) | AE15: 46368 | AF15: 1000000 | AG15: =IF(AC15="","SIN ESTADO",IF(AE15<>"","PAGA",IF(AD15>0,"VENCIDA",IF(AD15>=-5,"POR VENCER","AL DÍA")))) | AI15: =IF(N($H15)<5,"",IF(AC15="","",AC15+31)) | AJ15: =IF(AI15="","",TODAY()-AI15) | AM15: =IF(AI15="","SIN ESTADO",IF(AK15<>"","PAGA",IF(AJ15>0,"VENCIDA",IF(AJ15>=-5,"POR VENCER","AL DÍA")))) | AO15: =IF(N($H15)<6,"",IF(AI15="","",AI15+31)) | AP15: =IF(AO15="","",TODAY()-AO15) | AS15: =IF(AO15="","SIN ESTADO",IF(AQ15<>"","PAGA",IF(AP15>0,"VENCIDA",IF(AP15>=-5,"POR VENCER","AL DÍA")))) | AU15: =IF(N($H15)<7,"",IF(AO15="","",AO15+31)) | AV15: =IF(AU15="","",TODAY()-AU15) | AY15: =IF(AU15="","SIN ESTADO",IF(AW15<>"","PAGA",IF(AV15>0,"VENCIDA",IF(AV15>=-5,"POR VENCER","AL DÍA")))) | BA15: =IF(N($H15)<8,"",IF(AU15="","",AU15+31)) | BB15: =IF(BA15="","",TODAY()-BA15) | BE15: =IF(BA15="","SIN ESTADO",IF(BC15<>"","PAGA",IF(BB15>0,"VENCIDA",IF(BB15>=-5,"POR VENCER","AL DÍA")))) | BG15: =IF(N($H15)<9,"",IF(BA15="","",BA15+31)) | BH15: =IF(BG15="","",TODAY()-BG15) | BK15: =IF(BG15="","SIN ESTADO",IF(BI15<>"","PAGA",IF(BH15>0,"VENCIDA",IF(BH15>=-5,"POR VENCER","AL DÍA")))) | BM15: =IF(N($H15)<10,"",IF(BG15="","",BG15+31)) | BN15: =IF(BM15="","",TODAY()-BM15) | BQ15: =IF(BM15="","SIN ESTADO",IF(BO15<>"","PAGA",IF(BN15>0,"VENCIDA",IF(BN15>=-5,"POR VENCER","AL DÍA")))) | BS15: =IF(N($H15)<11,"",IF(BM15="","",BM15+31)) | BT15: =IF(BS15="","",TODAY()-BS15) | BW15: =IF(BS15="","SIN ESTADO",IF(BU15<>"","PAGA",IF(BT15>0,"VENCIDA",IF(BT15>=-5,"POR VENCER","AL DÍA")))) | BY15: =IF(N($H15)<12,"",IF(BS15="","",BS15+31)) | BZ15: =IF(BY15="","",TODAY()-BY15) | CC15: =IF(BY15="","SIN ESTADO",IF(CA15<>"","PAGA",IF(BZ15>0,"VENCIDA",IF(BZ15>=-5,"POR VENCER","AL DÍA")))) | CE15: =IF(N($H15)<13,"",IF(BY15="","",BY15+31)) | CF15: =IF(CE15="","",TODAY()-CE15) | CI15: =IF(CE15="","SIN ESTADO",IF(CG15<>"","PAGA",IF(CF15>0,"VENCIDA",IF(CF15>=-5,"POR VENCER","AL DÍA")))) | CK15: =IF(N($H15)<14,"",IF(CE15="","",CE15+31)) | CL15: =IF(CK15="","",TODAY()-CK15) | CO15: =IF(CK15="","SIN ESTADO",IF(CM15<>"","PAGA",IF(CL15>0,"VENCIDA",IF(CL15>=-5,"POR VENCER","AL DÍA")))) | CQ15: =IF(N($H15)<15,"",IF(CK15="","",CK15+31)) | CR15: =IF(CQ15="","",TODAY()-CQ15) | CU15: =IF(CQ15="","SIN ESTADO",IF(CS15<>"","PAGA",IF(CR15>0,"VENCIDA",IF(CR15>=-5,"POR VENCER","AL DÍA")))) | CW15: =IF(N($H15)<16,"",IF(CQ15="","",CQ15+31)) | CX15: =IF(CW15="","",TODAY()-CW15) | DA15: =IF(CW15="","SIN ESTADO",IF(CY15<>"","PAGA",IF(CX15>0,"VENCIDA",IF(CX15>=-5,"POR VENCER","AL DÍA")))) | DC15: =IF(N($H15)<17,"",IF(CW15="","",CW15+31)) | DD15: =IF(DC15="","",TODAY()-DC15) | DG15: =IF(DC15="","SIN ESTADO",IF(DE15<>"","PAGA",IF(DD15>0,"VENCIDA",IF(DD15>=-5,"POR VENCER","AL DÍA")))) | DI15: =IF(N($H15)<18,"",IF(DC15="","",DC15+31)) | DJ15: =IF(DI15="","",TODAY()-DI15) | DM15: =IF(DI15="","SIN ESTADO",IF(DK15<>"","PAGA",IF(DJ15>0,"VENCIDA",IF(DJ15>=-5,"POR VENCER","AL DÍA")))) | DO15: =IF(N($H15)<19,"",IF(DI15="","",DI15+31)) | DP15: =IF(DO15="","",TODAY()-DO15) | DS15: =IF(DO15="","SIN ESTADO",IF(DQ15<>"","PAGA",IF(DP15>0,"VENCIDA",IF(DP15>=-5,"POR VENCER","AL DÍA")))) | DU15: =IF(N($H15)<20,"",IF(DO15="","",DO15+31)) | DV15: =IF(DU15="","",TODAY()-DU15) | DY15: =IF(DU15="","SIN ESTADO",IF(DW15<>"","PAGA",IF(DV15>0,"VENCIDA",IF(DV15>=-5,"POR VENCER","AL DÍA")))) | EA15: =IF(N($H15)<21,"",IF(DU15="","",DU15+31)) | EB15: =IF(EA15="","",TODAY()-EA15) | EE15: =IF(EA15="","SIN ESTADO",IF(EC15<>"","PAGA",IF(EB15>0,"VENCIDA",IF(EB15>=-5,"POR VENCER","AL DÍA")))) | EG15: =IF(N($H15)<22,"",IF(EA15="","",EA15+31)) | EH15: =IF(EG15="","",TODAY()-EG15) | EK15: =IF(EG15="","SIN ESTADO",IF(EI15<>"","PAGA",IF(EH15>0,"VENCIDA",IF(EH15>=-5,"POR VENCER","AL DÍA")))) | EM15: =IF(N($H15)<23,"",IF(EG15="","",EG15+31)) | EN15: =IF(EM15="","",TODAY()-EM15) | EQ15: =IF(EM15="","SIN ESTADO",IF(EO15<>"","PAGA",IF(EN15>0,"VENCIDA",IF(EN15>=-5,"POR VENCER","AL DÍA")))) | ES15: =IF(N($H15)<24,"",IF(EM15="","",EM15+31)) | ET15: =IF(ES15="","",TODAY()-ES15) | EW15: =IF(ES15="","SIN ESTADO",IF(EU15<>"","PAGA",IF(ET15>0,"VENCIDA",IF(ET15>=-5,"POR VENCER","AL DÍA")))) | EY15: =IF(N($H15)<25,"",IF(ES15="","",ES15+31)) | EZ15: =IF(EY15="","",TODAY()-EY15) | FC15: =IF(EY15="","SIN ESTADO",IF(FA15<>"","PAGA",IF(EZ15>0,"VENCIDA",IF(EZ15>=-5,"POR VENCER","AL DÍA")))) | FE15: =IF(N($H15)<26,"",IF(EY15="","",EY15+31)) | FF15: =IF(FE15="","",TODAY()-FE15) | FI15: =IF(FE15="","SIN ESTADO",IF(FG15<>"","PAGA",IF(FF15>0,"VENCIDA",IF(FF15>=-5,"POR VENCER","AL DÍA")))) | FK15: =IF(N($H15)<27,"",IF(FE15="","",FE15+31)) | FL15: =IF(FK15="","",TODAY()-FK15) | FO15: =IF(FK15="","SIN ESTADO",IF(FM15<>"","PAGA",IF(FL15>0,"VENCIDA",IF(FL15>=-5,"POR VENCER","AL DÍA")))) | FQ15: =IF(N($H15)<28,"",IF(FK15="","",FK15+31)) | FR15: =IF(FQ15="","",TODAY()-FQ15) | FU15: =IF(FQ15="","SIN ESTADO",IF(FS15<>"","PAGA",IF(FR15>0,"VENCIDA",IF(FR15>=-5,"POR VENCER","AL DÍA")))) | FW15: =IF(N($H15)<29,"",IF(FQ15="","",FQ15+31)) | FX15: =IF(FW15="","",TODAY()-FW15) | GA15: =IF(FW15="","SIN ESTADO",IF(FY15<>"","PAGA",IF(FX15>0,"VENCIDA",IF(FX15>=-5,"POR VENCER","AL DÍA")))) | GC15: =IF(N($H15)<30,"",IF(FW15="","",FW15+31)) | GD15: =IF(GC15="","",TODAY()-GC15) | GG15: =IF(GC15="","SIN ESTADO",IF(GE15<>"","PAGA",IF(GD15>0,"VENCIDA",IF(GD15>=-5,"POR VENCER","AL DÍA")))) | GI15: =IF(N($H15)<31,"",IF(GC15="","",GC15+31)) | GJ15: =IF(GI15="","",TODAY()-GI15) | GM15: =IF(GI15="","SIN ESTADO",IF(GK15<>"","PAGA",IF(GJ15>0,"VENCIDA",IF(GJ15>=-5,"POR VENCER","AL DÍA")))) | GO15: =IF(N($H15)<32,"",IF(GI15="","",GI15+31)) | GP15: =IF(GO15="","",TODAY()-GO15) | GS15: =IF(GO15="","SIN ESTADO",IF(GQ15<>"","PAGA",IF(GP15>0,"VENCIDA",IF(GP15>=-5,"POR VENCER","AL DÍA")))) | GU15: =IF(N($H15)<33,"",IF(GO15="","",GO15+31)) | GV15: =IF(GU15="","",TODAY()-GU15) | GY15: =IF(GU15="","SIN ESTADO",IF(GW15<>"","PAGA",IF(GV15>0,"VENCIDA",IF(GV15>=-5,"POR VENCER","AL DÍA")))) | HA15: =IF(N($H15)<34,"",IF(GU15="","",GU15+31)) | HB15: =IF(HA15="","",TODAY()-HA15) | HE15: =IF(HA15="","SIN ESTADO",IF(HC15<>"","PAGA",IF(HB15>0,"VENCIDA",IF(HB15>=-5,"POR VENCER","AL DÍA")))) | HG15: =IF(N($H15)<35,"",IF(HA15="","",HA15+31)) | HH15: =IF(HG15="","",TODAY()-HG15) | HK15: =IF(HG15="","SIN ESTADO",IF(HI15<>"","PAGA",IF(HH15>0,"VENCIDA",IF(HH15>=-5,"POR VENCER","AL DÍA")))) | HM15: =IF(N($H15)<36,"",IF(HG15="","",HG15+31)) | HN15: =IF(HM15="","",TODAY()-HM15) | HQ15: =IF(HM15="","SIN ESTADO",IF(HO15<>"","PAGA",IF(HN15>0,"VENCIDA",IF(HN15>=-5,"POR VENCER","AL DÍA")))) | HS15: =N15+T15+Z15+AF15+AL15+AR15+AX15+BD15+BJ15+BP15+BV15+CB15+CH15+CN15+CT15+CZ15+DF15+DL15+DR15+DX15+ED15+EJ15+EP15+EV15+FB15+FH15+FN15+FT15+FZ15+GF15+GL15+GR15+GX15+HD15+HJ15+HP15 | HU15: =IFERROR(N($J15),0) | HW15: =SUMPRODUCT((MOD(COLUMN($M15:$HR15)-COLUMN($M15),6)=0)*ISNUMBER($M15:$HR15)*($M15:$HR15>=RESUMEN!$C$26)*($M15:$HR15<=RESUMEN!$C$27)*IFERROR(N($N15:$HS15),0)) | HX15: =SUMPRODUCT((MOD(COLUMN($M15:$HR15)-COLUMN($M15),6)=0)*ISNUMBER($M15:$HR15)*($M15:$HR15>=RESUMEN!$C$26)*($M15:$HR15<=RESUMEN!$C$27))
B16: =VENTAS!A15 | C16: =VENTAS!B15 | D16: =VENTAS!C15 | E16: =VENTAS!D15 | F16: =VENTAS!J15 | G16: =VENTAS!F15 | H16: =VENTAS!K15 | I16: =VENTAS!M15 | J16: =VENTAS!L15 | K16: =IF(N($H16)<1,"",$G16+31) | L16: =IF(K16="","",TODAY()-K16) | O16: =IF(K16="","SIN ESTADO",IF(M16<>"","PAGA",IF(L16>0,"VENCIDA",IF(L16>=-5,"POR VENCER","AL DÍA")))) | Q16: =IF(N($H16)<2,"",IF(K16="","",K16+31)) | R16: =IF(Q16="","",TODAY()-Q16) | U16: =IF(Q16="","SIN ESTADO",IF(S16<>"","PAGA",IF(R16>0,"VENCIDA",IF(R16>=-5,"POR VENCER","AL DÍA")))) | W16: =IF(N($H16)<3,"",IF(Q16="","",Q16+31)) | X16: =IF(W16="","",TODAY()-W16) | AA16: =IF(W16="","SIN ESTADO",IF(Y16<>"","PAGA",IF(X16>0,"VENCIDA",IF(X16>=-5,"POR VENCER","AL DÍA")))) | AC16: =IF(N($H16)<4,"",IF(W16="","",W16+31)) | AD16: =IF(AC16="","",TODAY()-AC16) | AG16: =IF(AC16="","SIN ESTADO",IF(AE16<>"","PAGA",IF(AD16>0,"VENCIDA",IF(AD16>=-5,"POR VENCER","AL DÍA")))) | AI16: =IF(N($H16)<5,"",IF(AC16="","",AC16+31)) | AJ16: =IF(AI16="","",TODAY()-AI16) | AM16: =IF(AI16="","SIN ESTADO",IF(AK16<>"","PAGA",IF(AJ16>0,"VENCIDA",IF(AJ16>=-5,"POR VENCER","AL DÍA")))) | AO16: =IF(N($H16)<6,"",IF(AI16="","",AI16+31)) | AP16: =IF(AO16="","",TODAY()-AO16) | AS16: =IF(AO16="","SIN ESTADO",IF(AQ16<>"","PAGA",IF(AP16>0,"VENCIDA",IF(AP16>=-5,"POR VENCER","AL DÍA")))) | AU16: =IF(N($H16)<7,"",IF(AO16="","",AO16+31)) | AV16: =IF(AU16="","",TODAY()-AU16) | AY16: =IF(AU16="","SIN ESTADO",IF(AW16<>"","PAGA",IF(AV16>0,"VENCIDA",IF(AV16>=-5,"POR VENCER","AL DÍA")))) | BA16: =IF(N($H16)<8,"",IF(AU16="","",AU16+31)) | BB16: =IF(BA16="","",TODAY()-BA16) | BE16: =IF(BA16="","SIN ESTADO",IF(BC16<>"","PAGA",IF(BB16>0,"VENCIDA",IF(BB16>=-5,"POR VENCER","AL DÍA")))) | BG16: =IF(N($H16)<9,"",IF(BA16="","",BA16+31)) | BH16: =IF(BG16="","",TODAY()-BG16) | BK16: =IF(BG16="","SIN ESTADO",IF(BI16<>"","PAGA",IF(BH16>0,"VENCIDA",IF(BH16>=-5,"POR VENCER","AL DÍA")))) | BM16: =IF(N($H16)<10,"",IF(BG16="","",BG16+31)) | BN16: =IF(BM16="","",TODAY()-BM16) | BQ16: =IF(BM16="","SIN ESTADO",IF(BO16<>"","PAGA",IF(BN16>0,"VENCIDA",IF(BN16>=-5,"POR VENCER","AL DÍA")))) | BS16: =IF(N($H16)<11,"",IF(BM16="","",BM16+31)) | BT16: =IF(BS16="","",TODAY()-BS16) | BW16: =IF(BS16="","SIN ESTADO",IF(BU16<>"","PAGA",IF(BT16>0,"VENCIDA",IF(BT16>=-5,"POR VENCER","AL DÍA")))) | BY16: =IF(N($H16)<12,"",IF(BS16="","",BS16+31)) | BZ16: =IF(BY16="","",TODAY()-BY16) | CC16: =IF(BY16="","SIN ESTADO",IF(CA16<>"","PAGA",IF(BZ16>0,"VENCIDA",IF(BZ16>=-5,"POR VENCER","AL DÍA")))) | CE16: =IF(N($H16)<13,"",IF(BY16="","",BY16+31)) | CF16: =IF(CE16="","",TODAY()-CE16) | CI16: =IF(CE16="","SIN ESTADO",IF(CG16<>"","PAGA",IF(CF16>0,"VENCIDA",IF(CF16>=-5,"POR VENCER","AL DÍA")))) | CK16: =IF(N($H16)<14,"",IF(CE16="","",CE16+31)) | CL16: =IF(CK16="","",TODAY()-CK16) | CO16: =IF(CK16="","SIN ESTADO",IF(CM16<>"","PAGA",IF(CL16>0,"VENCIDA",IF(CL16>=-5,"POR VENCER","AL DÍA")))) | CQ16: =IF(N($H16)<15,"",IF(CK16="","",CK16+31)) | CR16: =IF(CQ16="","",TODAY()-CQ16) | CU16: =IF(CQ16="","SIN ESTADO",IF(CS16<>"","PAGA",IF(CR16>0,"VENCIDA",IF(CR16>=-5,"POR VENCER","AL DÍA")))) | CW16: =IF(N($H16)<16,"",IF(CQ16="","",CQ16+31)) | CX16: =IF(CW16="","",TODAY()-CW16) | DA16: =IF(CW16="","SIN ESTADO",IF(CY16<>"","PAGA",IF(CX16>0,"VENCIDA",IF(CX16>=-5,"POR VENCER","AL DÍA")))) | DC16: =IF(N($H16)<17,"",IF(CW16="","",CW16+31)) | DD16: =IF(DC16="","",TODAY()-DC16) | DG16: =IF(DC16="","SIN ESTADO",IF(DE16<>"","PAGA",IF(DD16>0,"VENCIDA",IF(DD16>=-5,"POR VENCER","AL DÍA")))) | DI16: =IF(N($H16)<18,"",IF(DC16="","",DC16+31)) | DJ16: =IF(DI16="","",TODAY()-DI16) | DM16: =IF(DI16="","SIN ESTADO",IF(DK16<>"","PAGA",IF(DJ16>0,"VENCIDA",IF(DJ16>=-5,"POR VENCER","AL DÍA")))) | DO16: =IF(N($H16)<19,"",IF(DI16="","",DI16+31)) | DP16: =IF(DO16="","",TODAY()-DO16) | DS16: =IF(DO16="","SIN ESTADO",IF(DQ16<>"","PAGA",IF(DP16>0,"VENCIDA",IF(DP16>=-5,"POR VENCER","AL DÍA")))) | DU16: =IF(N($H16)<20,"",IF(DO16="","",DO16+31)) | DV16: =IF(DU16="","",TODAY()-DU16) | DY16: =IF(DU16="","SIN ESTADO",IF(DW16<>"","PAGA",IF(DV16>0,"VENCIDA",IF(DV16>=-5,"POR VENCER","AL DÍA")))) | EA16: =IF(N($H16)<21,"",IF(DU16="","",DU16+31)) | EB16: =IF(EA16="","",TODAY()-EA16) | EE16: =IF(EA16="","SIN ESTADO",IF(EC16<>"","PAGA",IF(EB16>0,"VENCIDA",IF(EB16>=-5,"POR VENCER","AL DÍA")))) | EG16: =IF(N($H16)<22,"",IF(EA16="","",EA16+31)) | EH16: =IF(EG16="","",TODAY()-EG16) | EK16: =IF(EG16="","SIN ESTADO",IF(EI16<>"","PAGA",IF(EH16>0,"VENCIDA",IF(EH16>=-5,"POR VENCER","AL DÍA")))) | EM16: =IF(N($H16)<23,"",IF(EG16="","",EG16+31)) | EN16: =IF(EM16="","",TODAY()-EM16) | EQ16: =IF(EM16="","SIN ESTADO",IF(EO16<>"","PAGA",IF(EN16>0,"VENCIDA",IF(EN16>=-5,"POR VENCER","AL DÍA")))) | ES16: =IF(N($H16)<24,"",IF(EM16="","",EM16+31)) | ET16: =IF(ES16="","",TODAY()-ES16) | EW16: =IF(ES16="","SIN ESTADO",IF(EU16<>"","PAGA",IF(ET16>0,"VENCIDA",IF(ET16>=-5,"POR VENCER","AL DÍA")))) | EY16: =IF(N($H16)<25,"",IF(ES16="","",ES16+31)) | EZ16: =IF(EY16="","",TODAY()-EY16) | FC16: =IF(EY16="","SIN ESTADO",IF(FA16<>"","PAGA",IF(EZ16>0,"VENCIDA",IF(EZ16>=-5,"POR VENCER","AL DÍA")))) | FE16: =IF(N($H16)<26,"",IF(EY16="","",EY16+31)) | FF16: =IF(FE16="","",TODAY()-FE16) | FI16: =IF(FE16="","SIN ESTADO",IF(FG16<>"","PAGA",IF(FF16>0,"VENCIDA",IF(FF16>=-5,"POR VENCER","AL DÍA")))) | FK16: =IF(N($H16)<27,"",IF(FE16="","",FE16+31)) | FL16: =IF(FK16="","",TODAY()-FK16) | FO16: =IF(FK16="","SIN ESTADO",IF(FM16<>"","PAGA",IF(FL16>0,"VENCIDA",IF(FL16>=-5,"POR VENCER","AL DÍA")))) | FQ16: =IF(N($H16)<28,"",IF(FK16="","",FK16+31)) | FR16: =IF(FQ16="","",TODAY()-FQ16) | FU16: =IF(FQ16="","SIN ESTADO",IF(FS16<>"","PAGA",IF(FR16>0,"VENCIDA",IF(FR16>=-5,"POR VENCER","AL DÍA")))) | FW16: =IF(N($H16)<29,"",IF(FQ16="","",FQ16+31)) | FX16: =IF(FW16="","",TODAY()-FW16) | GA16: =IF(FW16="","SIN ESTADO",IF(FY16<>"","PAGA",IF(FX16>0,"VENCIDA",IF(FX16>=-5,"POR VENCER","AL DÍA")))) | GC16: =IF(N($H16)<30,"",IF(FW16="","",FW16+31)) | GD16: =IF(GC16="","",TODAY()-GC16) | GG16: =IF(GC16="","SIN ESTADO",IF(GE16<>"","PAGA",IF(GD16>0,"VENCIDA",IF(GD16>=-5,"POR VENCER","AL DÍA")))) | GI16: =IF(N($H16)<31,"",IF(GC16="","",GC16+31)) | GJ16: =IF(GI16="","",TODAY()-GI16) | GM16: =IF(GI16="","SIN ESTADO",IF(GK16<>"","PAGA",IF(GJ16>0,"VENCIDA",IF(GJ16>=-5,"POR VENCER","AL DÍA")))) | GO16: =IF(N($H16)<32,"",IF(GI16="","",GI16+31)) | GP16: =IF(GO16="","",TODAY()-GO16) | GS16: =IF(GO16="","SIN ESTADO",IF(GQ16<>"","PAGA",IF(GP16>0,"VENCIDA",IF(GP16>=-5,"POR VENCER","AL DÍA")))) | GU16: =IF(N($H16)<33,"",IF(GO16="","",GO16+31)) | GV16: =IF(GU16="","",TODAY()-GU16) | GY16: =IF(GU16="","SIN ESTADO",IF(GW16<>"","PAGA",IF(GV16>0,"VENCIDA",IF(GV16>=-5,"POR VENCER","AL DÍA")))) | HA16: =IF(N($H16)<34,"",IF(GU16="","",GU16+31)) | HB16: =IF(HA16="","",TODAY()-HA16) | HE16: =IF(HA16="","SIN ESTADO",IF(HC16<>"","PAGA",IF(HB16>0,"VENCIDA",IF(HB16>=-5,"POR VENCER","AL DÍA")))) | HG16: =IF(N($H16)<35,"",IF(HA16="","",HA16+31)) | HH16: =IF(HG16="","",TODAY()-HG16) | HK16: =IF(HG16="","SIN ESTADO",IF(HI16<>"","PAGA",IF(HH16>0,"VENCIDA",IF(HH16>=-5,"POR VENCER","AL DÍA")))) | HM16: =IF(N($H16)<36,"",IF(HG16="","",HG16+31)) | HN16: =IF(HM16="","",TODAY()-HM16) | HQ16: =IF(HM16="","SIN ESTADO",IF(HO16<>"","PAGA",IF(HN16>0,"VENCIDA",IF(HN16>=-5,"POR VENCER","AL DÍA")))) | HS16: =N16+T16+Z16+AF16+AL16+AR16+AX16+BD16+BJ16+BP16+BV16+CB16+CH16+CN16+CT16+CZ16+DF16+DL16+DR16+DX16+ED16+EJ16+EP16+EV16+FB16+FH16+FN16+FT16+FZ16+GF16+GL16+GR16+GX16+HD16+HJ16+HP16 | HU16: =IFERROR(N($J16),0) | HW16: =SUMPRODUCT((MOD(COLUMN($M16:$HR16)-COLUMN($M16),6)=0)*ISNUMBER($M16:$HR16)*($M16:$HR16>=RESUMEN!$C$26)*($M16:$HR16<=RESUMEN!$C$27)*IFERROR(N($N16:$HS16),0)) | HX16: =SUMPRODUCT((MOD(COLUMN($M16:$HR16)-COLUMN($M16),6)=0)*ISNUMBER($M16:$HR16)*($M16:$HR16>=RESUMEN!$C$26)*($M16:$HR16<=RESUMEN!$C$27))
B17: =VENTAS!A16 | C17: =VENTAS!B16 | D17: =VENTAS!C16 | E17: =VENTAS!D16 | F17: =VENTAS!J16 | G17: =VENTAS!F16 | H17: =VENTAS!K16 | I17: =VENTAS!M16 | J17: =VENTAS!L16 | K17: =IF(N($H17)<1,"",$G17+31) | L17: =IF(K17="","",TODAY()-K17) | O17: =IF(K17="","SIN ESTADO",IF(M17<>"","PAGA",IF(L17>0,"VENCIDA",IF(L17>=-5,"POR VENCER","AL DÍA")))) | Q17: =IF(N($H17)<2,"",IF(K17="","",K17+31)) | R17: =IF(Q17="","",TODAY()-Q17) | U17: =IF(Q17="","SIN ESTADO",IF(S17<>"","PAGA",IF(R17>0,"VENCIDA",IF(R17>=-5,"POR VENCER","AL DÍA")))) | W17: =IF(N($H17)<3,"",IF(Q17="","",Q17+31)) | X17: =IF(W17="","",TODAY()-W17) | AA17: =IF(W17="","SIN ESTADO",IF(Y17<>"","PAGA",IF(X17>0,"VENCIDA",IF(X17>=-5,"POR VENCER","AL DÍA")))) | AC17: =IF(N($H17)<4,"",IF(W17="","",W17+31)) | AD17: =IF(AC17="","",TODAY()-AC17) | AG17: =IF(AC17="","SIN ESTADO",IF(AE17<>"","PAGA",IF(AD17>0,"VENCIDA",IF(AD17>=-5,"POR VENCER","AL DÍA")))) | AI17: =IF(N($H17)<5,"",IF(AC17="","",AC17+31)) | AJ17: =IF(AI17="","",TODAY()-AI17) | AM17: =IF(AI17="","SIN ESTADO",IF(AK17<>"","PAGA",IF(AJ17>0,"VENCIDA",IF(AJ17>=-5,"POR VENCER","AL DÍA")))) | AO17: =IF(N($H17)<6,"",IF(AI17="","",AI17+31)) | AP17: =IF(AO17="","",TODAY()-AO17) | AS17: =IF(AO17="","SIN ESTADO",IF(AQ17<>"","PAGA",IF(AP17>0,"VENCIDA",IF(AP17>=-5,"POR VENCER","AL DÍA")))) | AU17: =IF(N($H17)<7,"",IF(AO17="","",AO17+31)) | AV17: =IF(AU17="","",TODAY()-AU17) | AY17: =IF(AU17="","SIN ESTADO",IF(AW17<>"","PAGA",IF(AV17>0,"VENCIDA",IF(AV17>=-5,"POR VENCER","AL DÍA")))) | BA17: =IF(N($H17)<8,"",IF(AU17="","",AU17+31)) | BB17: =IF(BA17="","",TODAY()-BA17) | BE17: =IF(BA17="","SIN ESTADO",IF(BC17<>"","PAGA",IF(BB17>0,"VENCIDA",IF(BB17>=-5,"POR VENCER","AL DÍA")))) | BG17: =IF(N($H17)<9,"",IF(BA17="","",BA17+31)) | BH17: =IF(BG17="","",TODAY()-BG17) | BK17: =IF(BG17="","SIN ESTADO",IF(BI17<>"","PAGA",IF(BH17>0,"VENCIDA",IF(BH17>=-5,"POR VENCER","AL DÍA")))) | BM17: =IF(N($H17)<10,"",IF(BG17="","",BG17+31)) | BN17: =IF(BM17="","",TODAY()-BM17) | BQ17: =IF(BM17="","SIN ESTADO",IF(BO17<>"","PAGA",IF(BN17>0,"VENCIDA",IF(BN17>=-5,"POR VENCER","AL DÍA")))) | BS17: =IF(N($H17)<11,"",IF(BM17="","",BM17+31)) | BT17: =IF(BS17="","",TODAY()-BS17) | BW17: =IF(BS17="","SIN ESTADO",IF(BU17<>"","PAGA",IF(BT17>0,"VENCIDA",IF(BT17>=-5,"POR VENCER","AL DÍA")))) | BY17: =IF(N($H17)<12,"",IF(BS17="","",BS17+31)) | BZ17: =IF(BY17="","",TODAY()-BY17) | CC17: =IF(BY17="","SIN ESTADO",IF(CA17<>"","PAGA",IF(BZ17>0,"VENCIDA",IF(BZ17>=-5,"POR VENCER","AL DÍA")))) | CE17: =IF(N($H17)<13,"",IF(BY17="","",BY17+31)) | CF17: =IF(CE17="","",TODAY()-CE17) | CI17: =IF(CE17="","SIN ESTADO",IF(CG17<>"","PAGA",IF(CF17>0,"VENCIDA",IF(CF17>=-5,"POR VENCER","AL DÍA")))) | CK17: =IF(N($H17)<14,"",IF(CE17="","",CE17+31)) | CL17: =IF(CK17="","",TODAY()-CK17) | CO17: =IF(CK17="","SIN ESTADO",IF(CM17<>"","PAGA",IF(CL17>0,"VENCIDA",IF(CL17>=-5,"POR VENCER","AL DÍA")))) | CQ17: =IF(N($H17)<15,"",IF(CK17="","",CK17+31)) | CR17: =IF(CQ17="","",TODAY()-CQ17) | CU17: =IF(CQ17="","SIN ESTADO",IF(CS17<>"","PAGA",IF(CR17>0,"VENCIDA",IF(CR17>=-5,"POR VENCER","AL DÍA")))) | CW17: =IF(N($H17)<16,"",IF(CQ17="","",CQ17+31)) | CX17: =IF(CW17="","",TODAY()-CW17) | DA17: =IF(CW17="","SIN ESTADO",IF(CY17<>"","PAGA",IF(CX17>0,"VENCIDA",IF(CX17>=-5,"POR VENCER","AL DÍA")))) | DC17: =IF(N($H17)<17,"",IF(CW17="","",CW17+31)) | DD17: =IF(DC17="","",TODAY()-DC17) | DG17: =IF(DC17="","SIN ESTADO",IF(DE17<>"","PAGA",IF(DD17>0,"VENCIDA",IF(DD17>=-5,"POR VENCER","AL DÍA")))) | DI17: =IF(N($H17)<18,"",IF(DC17="","",DC17+31)) | DJ17: =IF(DI17="","",TODAY()-DI17) | DM17: =IF(DI17="","SIN ESTADO",IF(DK17<>"","PAGA",IF(DJ17>0,"VENCIDA",IF(DJ17>=-5,"POR VENCER","AL DÍA")))) | DO17: =IF(N($H17)<19,"",IF(DI17="","",DI17+31)) | DP17: =IF(DO17="","",TODAY()-DO17) | DS17: =IF(DO17="","SIN ESTADO",IF(DQ17<>"","PAGA",IF(DP17>0,"VENCIDA",IF(DP17>=-5,"POR VENCER","AL DÍA")))) | DU17: =IF(N($H17)<20,"",IF(DO17="","",DO17+31)) | DV17: =IF(DU17="","",TODAY()-DU17) | DY17: =IF(DU17="","SIN ESTADO",IF(DW17<>"","PAGA",IF(DV17>0,"VENCIDA",IF(DV17>=-5,"POR VENCER","AL DÍA")))) | EA17: =IF(N($H17)<21,"",IF(DU17="","",DU17+31)) | EB17: =IF(EA17="","",TODAY()-EA17) | EE17: =IF(EA17="","SIN ESTADO",IF(EC17<>"","PAGA",IF(EB17>0,"VENCIDA",IF(EB17>=-5,"POR VENCER","AL DÍA")))) | EG17: =IF(N($H17)<22,"",IF(EA17="","",EA17+31)) | EH17: =IF(EG17="","",TODAY()-EG17) | EK17: =IF(EG17="","SIN ESTADO",IF(EI17<>"","PAGA",IF(EH17>0,"VENCIDA",IF(EH17>=-5,"POR VENCER","AL DÍA")))) | EM17: =IF(N($H17)<23,"",IF(EG17="","",EG17+31)) | EN17: =IF(EM17="","",TODAY()-EM17) | EQ17: =IF(EM17="","SIN ESTADO",IF(EO17<>"","PAGA",IF(EN17>0,"VENCIDA",IF(EN17>=-5,"POR VENCER","AL DÍA")))) | ES17: =IF(N($H17)<24,"",IF(EM17="","",EM17+31)) | ET17: =IF(ES17="","",TODAY()-ES17) | EW17: =IF(ES17="","SIN ESTADO",IF(EU17<>"","PAGA",IF(ET17>0,"VENCIDA",IF(ET17>=-5,"POR VENCER","AL DÍA")))) | EY17: =IF(N($H17)<25,"",IF(ES17="","",ES17+31)) | EZ17: =IF(EY17="","",TODAY()-EY17) | FC17: =IF(EY17="","SIN ESTADO",IF(FA17<>"","PAGA",IF(EZ17>0,"VENCIDA",IF(EZ17>=-5,"POR VENCER","AL DÍA")))) | FE17: =IF(N($H17)<26,"",IF(EY17="","",EY17+31)) | FF17: =IF(FE17="","",TODAY()-FE17) | FI17: =IF(FE17="","SIN ESTADO",IF(FG17<>"","PAGA",IF(FF17>0,"VENCIDA",IF(FF17>=-5,"POR VENCER","AL DÍA")))) | FK17: =IF(N($H17)<27,"",IF(FE17="","",FE17+31)) | FL17: =IF(FK17="","",TODAY()-FK17) | FO17: =IF(FK17="","SIN ESTADO",IF(FM17<>"","PAGA",IF(FL17>0,"VENCIDA",IF(FL17>=-5,"POR VENCER","AL DÍA")))) | FQ17: =IF(N($H17)<28,"",IF(FK17="","",FK17+31)) | FR17: =IF(FQ17="","",TODAY()-FQ17) | FU17: =IF(FQ17="","SIN ESTADO",IF(FS17<>"","PAGA",IF(FR17>0,"VENCIDA",IF(FR17>=-5,"POR VENCER","AL DÍA")))) | FW17: =IF(N($H17)<29,"",IF(FQ17="","",FQ17+31)) | FX17: =IF(FW17="","",TODAY()-FW17) | GA17: =IF(FW17="","SIN ESTADO",IF(FY17<>"","PAGA",IF(FX17>0,"VENCIDA",IF(FX17>=-5,"POR VENCER","AL DÍA")))) | GC17: =IF(N($H17)<30,"",IF(FW17="","",FW17+31)) | GD17: =IF(GC17="","",TODAY()-GC17) | GG17: =IF(GC17="","SIN ESTADO",IF(GE17<>"","PAGA",IF(GD17>0,"VENCIDA",IF(GD17>=-5,"POR VENCER","AL DÍA")))) | GI17: =IF(N($H17)<31,"",IF(GC17="","",GC17+31)) | GJ17: =IF(GI17="","",TODAY()-GI17) | GM17: =IF(GI17="","SIN ESTADO",IF(GK17<>"","PAGA",IF(GJ17>0,"VENCIDA",IF(GJ17>=-5,"POR VENCER","AL DÍA")))) | GO17: =IF(N($H17)<32,"",IF(GI17="","",GI17+31)) | GP17: =IF(GO17="","",TODAY()-GO17) | GS17: =IF(GO17="","SIN ESTADO",IF(GQ17<>"","PAGA",IF(GP17>0,"VENCIDA",IF(GP17>=-5,"POR VENCER","AL DÍA")))) | GU17: =IF(N($H17)<33,"",IF(GO17="","",GO17+31)) | GV17: =IF(GU17="","",TODAY()-GU17) | GY17: =IF(GU17="","SIN ESTADO",IF(GW17<>"","PAGA",IF(GV17>0,"VENCIDA",IF(GV17>=-5,"POR VENCER","AL DÍA")))) | HA17: =IF(N($H17)<34,"",IF(GU17="","",GU17+31)) | HB17: =IF(HA17="","",TODAY()-HA17) | HE17: =IF(HA17="","SIN ESTADO",IF(HC17<>"","PAGA",IF(HB17>0,"VENCIDA",IF(HB17>=-5,"POR VENCER","AL DÍA")))) | HG17: =IF(N($H17)<35,"",IF(HA17="","",HA17+31)) | HH17: =IF(HG17="","",TODAY()-HG17) | HK17: =IF(HG17="","SIN ESTADO",IF(HI17<>"","PAGA",IF(HH17>0,"VENCIDA",IF(HH17>=-5,"POR VENCER","AL DÍA")))) | HM17: =IF(N($H17)<36,"",IF(HG17="","",HG17+31)) | HN17: =IF(HM17="","",TODAY()-HM17) | HQ17: =IF(HM17="","SIN ESTADO",IF(HO17<>"","PAGA",IF(HN17>0,"VENCIDA",IF(HN17>=-5,"POR VENCER","AL DÍA")))) | HS17: =N17+T17+Z17+AF17+AL17+AR17+AX17+BD17+BJ17+BP17+BV17+CB17+CH17+CN17+CT17+CZ17+DF17+DL17+DR17+DX17+ED17+EJ17+EP17+EV17+FB17+FH17+FN17+FT17+FZ17+GF17+GL17+GR17+GX17+HD17+HJ17+HP17 | HU17: =IFERROR(N($J17),0) | HW17: =SUMPRODUCT((MOD(COLUMN($M17:$HR17)-COLUMN($M17),6)=0)*ISNUMBER($M17:$HR17)*($M17:$HR17>=RESUMEN!$C$26)*($M17:$HR17<=RESUMEN!$C$27)*IFERROR(N($N17:$HS17),0)) | HX17: =SUMPRODUCT((MOD(COLUMN($M17:$HR17)-COLUMN($M17),6)=0)*ISNUMBER($M17:$HR17)*($M17:$HR17>=RESUMEN!$C$26)*($M17:$HR17<=RESUMEN!$C$27))
B18: =VENTAS!A17 | C18: =VENTAS!B17 | D18: =VENTAS!C17 | E18: =VENTAS!D17 | F18: =VENTAS!J17 | G18: =VENTAS!F17 | H18: =VENTAS!K17 | I18: =VENTAS!M17 | J18: =VENTAS!L17 | K18: =IF(N($H18)<1,"",$G18+31) | L18: =IF(K18="","",TODAY()-K18) | M18: 45960 | N18: 1000000 | O18: =IF(K18="","SIN ESTADO",IF(M18<>"","PAGA",IF(L18>0,"VENCIDA",IF(L18>=-5,"POR VENCER","AL DÍA")))) | P18: TRANSFERENCIA | Q18: =IF(N($H18)<2,"",IF(K18="","",K18+31)) | R18: =IF(Q18="","",TODAY()-Q18) | S18: 46000 | T18: 1000000 | U18: =IF(Q18="","SIN ESTADO",IF(S18<>"","PAGA",IF(R18>0,"VENCIDA",IF(R18>=-5,"POR VENCER","AL DÍA")))) | V18: TRANSFERENCIA | W18: =IF(N($H18)<3,"",IF(Q18="","",Q18+31)) | X18: =IF(W18="","",TODAY()-W18) | Y18: 45664 | Z18: 1000000 | AA18: =IF(W18="","SIN ESTADO",IF(Y18<>"","PAGA",IF(X18>0,"VENCIDA",IF(X18>=-5,"POR VENCER","AL DÍA")))) | AB18: TRANSFERENCIA | AC18: =IF(N($H18)<4,"",IF(W18="","",W18+31)) | AD18: =IF(AC18="","",TODAY()-AC18) | AE18: 46039 | AF18: 3000000 | AG18: =IF(AC18="","SIN ESTADO",IF(AE18<>"","PAGA",IF(AD18>0,"VENCIDA",IF(AD18>=-5,"POR VENCER","AL DÍA")))) | AH18: TRANSFERENCIA | AI18: =IF(N($H18)<5,"",IF(AC18="","",AC18+31)) | AJ18: =IF(AI18="","",TODAY()-AI18) | AK18: 46060 | AL18: 5000000 | AM18: =IF(AI18="","SIN ESTADO",IF(AK18<>"","PAGA",IF(AJ18>0,"VENCIDA",IF(AJ18>=-5,"POR VENCER","AL DÍA")))) | AN18: TRANSFERENCIA | AO18: =IF(N($H18)<6,"",IF(AI18="","",AI18+31)) | AP18: =IF(AO18="","",TODAY()-AO18) | AQ18: 46088 | AR18: 5000000 | AS18: =IF(AO18="","SIN ESTADO",IF(AQ18<>"","PAGA",IF(AP18>0,"VENCIDA",IF(AP18>=-5,"POR VENCER","AL DÍA")))) | AT18: TRANSFERENCIA | AU18: =IF(N($H18)<7,"",IF(AO18="","",AO18+31)) | AV18: =IF(AU18="","",TODAY()-AU18) | AW18: 46123 | AX18: 5000000 | AY18: =IF(AU18="","SIN ESTADO",IF(AW18<>"","PAGA",IF(AV18>0,"VENCIDA",IF(AV18>=-5,"POR VENCER","AL DÍA")))) | AZ18: TRANSFERENCIA | BA18: =IF(N($H18)<8,"",IF(AU18="","",AU18+31)) | BB18: =IF(BA18="","",TODAY()-BA18) | BC18: 46123 | BE18: =IF(BA18="","SIN ESTADO",IF(BC18<>"","PAGA",IF(BB18>0,"VENCIDA",IF(BB18>=-5,"POR VENCER","AL DÍA")))) | BG18: =IF(N($H18)<9,"",IF(BA18="","",BA18+31)) | BH18: =IF(BG18="","",TODAY()-BG18) | BI18: 46123 | BK18: =IF(BG18="","SIN ESTADO",IF(BI18<>"","PAGA",IF(BH18>0,"VENCIDA",IF(BH18>=-5,"POR VENCER","AL DÍA")))) | BM18: =IF(N($H18)<10,"",IF(BG18="","",BG18+31)) | BN18: =IF(BM18="","",TODAY()-BM18) | BO18: 46330 | BQ18: =IF(BM18="","SIN ESTADO",IF(BO18<>"","PAGA",IF(BN18>0,"VENCIDA",IF(BN18>=-5,"POR VENCER","AL DÍA")))) | BS18: =IF(N($H18)<11,"",IF(BM18="","",BM18+31)) | BT18: =IF(BS18="","",TODAY()-BS18) | BU18: 46123 | BW18: =IF(BS18="","SIN ESTADO",IF(BU18<>"","PAGA",IF(BT18>0,"VENCIDA",IF(BT18>=-5,"POR VENCER","AL DÍA")))) | BY18: =IF(N($H18)<12,"",IF(BS18="","",BS18+31)) | BZ18: =IF(BY18="","",TODAY()-BY18) | CA18: 46330 | CC18: =IF(BY18="","SIN ESTADO",IF(CA18<>"","PAGA",IF(BZ18>0,"VENCIDA",IF(BZ18>=-5,"POR VENCER","AL DÍA")))) | CE18: =IF(N($H18)<13,"",IF(BY18="","",BY18+31)) | CF18: =IF(CE18="","",TODAY()-CE18) | CG18: 46123 | CI18: =IF(CE18="","SIN ESTADO",IF(CG18<>"","PAGA",IF(CF18>0,"VENCIDA",IF(CF18>=-5,"POR VENCER","AL DÍA")))) | CK18: =IF(N($H18)<14,"",IF(CE18="","",CE18+31)) | CL18: =IF(CK18="","",TODAY()-CK18) | CM18: 46123 | CO18: =IF(CK18="","SIN ESTADO",IF(CM18<>"","PAGA",IF(CL18>0,"VENCIDA",IF(CL18>=-5,"POR VENCER","AL DÍA")))) | CQ18: =IF(N($H18)<15,"",IF(CK18="","",CK18+31)) | CR18: =IF(CQ18="","",TODAY()-CQ18) | CS18: 46123 | CU18: =IF(CQ18="","SIN ESTADO",IF(CS18<>"","PAGA",IF(CR18>0,"VENCIDA",IF(CR18>=-5,"POR VENCER","AL DÍA")))) | CW18: =IF(N($H18)<16,"",IF(CQ18="","",CQ18+31)) | CX18: =IF(CW18="","",TODAY()-CW18) | CY18: 46123 | DA18: =IF(CW18="","SIN ESTADO",IF(CY18<>"","PAGA",IF(CX18>0,"VENCIDA",IF(CX18>=-5,"POR VENCER","AL DÍA")))) | DC18: =IF(N($H18)<17,"",IF(CW18="","",CW18+31)) | DD18: =IF(DC18="","",TODAY()-DC18) | DE18: 46123 | DG18: =IF(DC18="","SIN ESTADO",IF(DE18<>"","PAGA",IF(DD18>0,"VENCIDA",IF(DD18>=-5,"POR VENCER","AL DÍA")))) | DI18: =IF(N($H18)<18,"",IF(DC18="","",DC18+31)) | DJ18: =IF(DI18="","",TODAY()-DI18) | DK18: 46123 | DM18: =IF(DI18="","SIN ESTADO",IF(DK18<>"","PAGA",IF(DJ18>0,"VENCIDA",IF(DJ18>=-5,"POR VENCER","AL DÍA")))) | DO18: =IF(N($H18)<19,"",IF(DI18="","",DI18+31)) | DP18: =IF(DO18="","",TODAY()-DO18) | DQ18: 46123 | DS18: =IF(DO18="","SIN ESTADO",IF(DQ18<>"","PAGA",IF(DP18>0,"VENCIDA",IF(DP18>=-5,"POR VENCER","AL DÍA")))) | DU18: =IF(N($H18)<20,"",IF(DO18="","",DO18+31)) | DV18: =IF(DU18="","",TODAY()-DU18) | DW18: 46123 | DY18: =IF(DU18="","SIN ESTADO",IF(DW18<>"","PAGA",IF(DV18>0,"VENCIDA",IF(DV18>=-5,"POR VENCER","AL DÍA")))) | EA18: =IF(N($H18)<21,"",IF(DU18="","",DU18+31)) | EB18: =IF(EA18="","",TODAY()-EA18) | EC18: 46123 | EE18: =IF(EA18="","SIN ESTADO",IF(EC18<>"","PAGA",IF(EB18>0,"VENCIDA",IF(EB18>=-5,"POR VENCER","AL DÍA")))) | EG18: =IF(N($H18)<22,"",IF(EA18="","",EA18+31)) | EH18: =IF(EG18="","",TODAY()-EG18) | EI18: 46123 | EK18: =IF(EG18="","SIN ESTADO",IF(EI18<>"","PAGA",IF(EH18>0,"VENCIDA",IF(EH18>=-5,"POR VENCER","AL DÍA")))) | EM18: =IF(N($H18)<23,"",IF(EG18="","",EG18+31)) | EN18: =IF(EM18="","",TODAY()-EM18) | EO18: 46123 | EQ18: =IF(EM18="","SIN ESTADO",IF(EO18<>"","PAGA",IF(EN18>0,"VENCIDA",IF(EN18>=-5,"POR VENCER","AL DÍA")))) | ES18: =IF(N($H18)<24,"",IF(EM18="","",EM18+31)) | ET18: =IF(ES18="","",TODAY()-ES18) | EU18: 46123 | EW18: =IF(ES18="","SIN ESTADO",IF(EU18<>"","PAGA",IF(ET18>0,"VENCIDA",IF(ET18>=-5,"POR VENCER","AL DÍA")))) | EY18: =IF(N($H18)<25,"",IF(ES18="","",ES18+31)) | EZ18: =IF(EY18="","",TODAY()-EY18) | FC18: =IF(EY18="","SIN ESTADO",IF(FA18<>"","PAGA",IF(EZ18>0,"VENCIDA",IF(EZ18>=-5,"POR VENCER","AL DÍA")))) | FE18: =IF(N($H18)<26,"",IF(EY18="","",EY18+31)) | FF18: =IF(FE18="","",TODAY()-FE18) | FI18: =IF(FE18="","SIN ESTADO",IF(FG18<>"","PAGA",IF(FF18>0,"VENCIDA",IF(FF18>=-5,"POR VENCER","AL DÍA")))) | FK18: =IF(N($H18)<27,"",IF(FE18="","",FE18+31)) | FL18: =IF(FK18="","",TODAY()-FK18) | FO18: =IF(FK18="","SIN ESTADO",IF(FM18<>"","PAGA",IF(FL18>0,"VENCIDA",IF(FL18>=-5,"POR VENCER","AL DÍA")))) | FQ18: =IF(N($H18)<28,"",IF(FK18="","",FK18+31)) | FR18: =IF(FQ18="","",TODAY()-FQ18) | FU18: =IF(FQ18="","SIN ESTADO",IF(FS18<>"","PAGA",IF(FR18>0,"VENCIDA",IF(FR18>=-5,"POR VENCER","AL DÍA")))) | FW18: =IF(N($H18)<29,"",IF(FQ18="","",FQ18+31)) | FX18: =IF(FW18="","",TODAY()-FW18) | GA18: =IF(FW18="","SIN ESTADO",IF(FY18<>"","PAGA",IF(FX18>0,"VENCIDA",IF(FX18>=-5,"POR VENCER","AL DÍA")))) | GC18: =IF(N($H18)<30,"",IF(FW18="","",FW18+31)) | GD18: =IF(GC18="","",TODAY()-GC18) | GG18: =IF(GC18="","SIN ESTADO",IF(GE18<>"","PAGA",IF(GD18>0,"VENCIDA",IF(GD18>=-5,"POR VENCER","AL DÍA")))) | GI18: =IF(N($H18)<31,"",IF(GC18="","",GC18+31)) | GJ18: =IF(GI18="","",TODAY()-GI18) | GM18: =IF(GI18="","SIN ESTADO",IF(GK18<>"","PAGA",IF(GJ18>0,"VENCIDA",IF(GJ18>=-5,"POR VENCER","AL DÍA")))) | GO18: =IF(N($H18)<32,"",IF(GI18="","",GI18+31)) | GP18: =IF(GO18="","",TODAY()-GO18) | GS18: =IF(GO18="","SIN ESTADO",IF(GQ18<>"","PAGA",IF(GP18>0,"VENCIDA",IF(GP18>=-5,"POR VENCER","AL DÍA")))) | GU18: =IF(N($H18)<33,"",IF(GO18="","",GO18+31)) | GV18: =IF(GU18="","",TODAY()-GU18) | GY18: =IF(GU18="","SIN ESTADO",IF(GW18<>"","PAGA",IF(GV18>0,"VENCIDA",IF(GV18>=-5,"POR VENCER","AL DÍA")))) | HA18: =IF(N($H18)<34,"",IF(GU18="","",GU18+31)) | HB18: =IF(HA18="","",TODAY()-HA18) | HE18: =IF(HA18="","SIN ESTADO",IF(HC18<>"","PAGA",IF(HB18>0,"VENCIDA",IF(HB18>=-5,"POR VENCER","AL DÍA")))) | HG18: =IF(N($H18)<35,"",IF(HA18="","",HA18+31)) | HH18: =IF(HG18="","",TODAY()-HG18) | HK18: =IF(HG18="","SIN ESTADO",IF(HI18<>"","PAGA",IF(HH18>0,"VENCIDA",IF(HH18>=-5,"POR VENCER","AL DÍA")))) | HM18: =IF(N($H18)<36,"",IF(HG18="","",HG18+31)) | HN18: =IF(HM18="","",TODAY()-HM18) | HQ18: =IF(HM18="","SIN ESTADO",IF(HO18<>"","PAGA",IF(HN18>0,"VENCIDA",IF(HN18>=-5,"POR VENCER","AL DÍA")))) | HS18: =N18+T18+Z18+AF18+AL18+AR18+AX18+BD18+BJ18+BP18+BV18+CB18+CH18+CN18+CT18+CZ18+DF18+DL18+DR18+DX18+ED18+EJ18+EP18+EV18+FB18+FH18+FN18+FT18+FZ18+GF18+GL18+GR18+GX18+HD18+HJ18+HP18 | HU18: =IFERROR(N($J18),0) | HW18: =SUMPRODUCT((MOD(COLUMN($M18:$HR18)-COLUMN($M18),6)=0)*ISNUMBER($M18:$HR18)*($M18:$HR18>=RESUMEN!$C$26)*($M18:$HR18<=RESUMEN!$C$27)*IFERROR(N($N18:$HS18),0)) | HX18: =SUMPRODUCT((MOD(COLUMN($M18:$HR18)-COLUMN($M18),6)=0)*ISNUMBER($M18:$HR18)*($M18:$HR18>=RESUMEN!$C$26)*($M18:$HR18<=RESUMEN!$C$27))
